Workbook

Sheet Controle
B2: Controle Capex | M2: Suporte lista
B3: # | C3: UFV | D3: CNPJ | E3: Unidade | F3: Frente | G3: Portfólio | H3: Contrato | I3: Medição | J3: Saldo a medir | K3: Avanço | M3: Natureza
B4: 1 | C4: Diamantina 1 | D4: MORI GERACAO II | E4: Mori II | F4: 3 | G4: Mori | H4: =SUMIFS('Controle Projetos_Ciclo2'!$O:$O,'Controle Projetos_Ciclo2'!$B:$B,$C4,'Controle Projetos_Ciclo2'!$F:$F,"Total") -> 0 | I4: =SUMIFS('Controle Projetos_Ciclo2'!$R:$R,'Controle Projetos_Ciclo2'!$B:$B,$C4,'Controle Projetos_Ciclo2'!$F:$F,"Total") -> 0 | J4: =SUMIFS('Controle Projetos_Ciclo2'!S:S,'Controle Projetos_Ciclo2'!$B:$B,$C4,'Controle Projetos_Ciclo2'!$F:$F,"Total") -> 0 | K4: =IFERROR(I4/H4,0) -> 0 | M4: Conexão AT - Obras
B5: =B4+1 -> 2 | C5: Diamantina 2 | D5: MORI GERACAO II | E5: Mori II | F5: 3 | G5: Mori | H5: =SUMIFS('Controle Projetos_Ciclo2'!$O:$O,'Controle Projetos_Ciclo2'!$B:$B,$C5,'Controle Projetos_Ciclo2'!$F:$F,"Total") -> 2348118.8 | I5: =SUMIFS('Controle Projetos_Ciclo2'!$R:$R,'Controle Projetos_Ciclo2'!$B:$B,$C5,'Controle Projetos_Ciclo2'!$F:$F,"Total") -> 2290918.8 | J5: =SUMIFS('Controle Projetos_Ciclo2'!S:S,'Controle Projetos_Ciclo2'!$B:$B,$C5,'Controle Projetos_Ciclo2'!$F:$F,"Total") -> 57200 | K5: =IFERROR(I5/H5,0) -> 0.97564007 | M5: Conexão MT - Obras
B6: =B5+1 -> 3 | C6: Frei Inocêncio 1 | D6: MORI GERACAO II | E6: Mori II | F6: Weg | G6: Mori | H6: =SUMIFS('Controle Projetos_Ciclo2'!$O:$O,'Controle Projetos_Ciclo2'!$B:$B,$C6,'Controle Projetos_Ciclo2'!$F:$F,"Total") -> 0 | I6: =SUMIFS('Controle Projetos_Ciclo2'!$R:$R,'Controle Projetos_Ciclo2'!$B:$B,$C6,'Controle Projetos_Ciclo2'!$F:$F,"Total") -> 0 | J6: =SUMIFS('Controle Projetos_Ciclo2'!S:S,'Controle Projetos_Ciclo2'!$B:$B,$C6,'Controle Projetos_Ciclo2'!$F:$F,"Total") -> 0 | K6: =IFERROR(I6/H6,0) -> 0 | M6: Construção - Serviços de Construção
B7: =B6+1 -> 4 | C7: Lagoa Formosa 1 | D7: MORI GERACAO II | E7: Mori II | F7: 1 | G7: Mori | H7: =SUMIFS('Controle Projetos_Ciclo2'!$O:$O,'Controle Projetos_Ciclo2'!$B:$B,$C7,'Controle Projetos_Ciclo2'!$F:$F,"Total") -> 0 | I7: =SUMIFS('Controle Projetos_Ciclo2'!$R:$R,'Controle Projetos_Ciclo2'!$B:$B,$C7,'Controle Projetos_Ciclo2'!$F:$F,"Total") -> 0 | J7: =SUMIFS('Controle Projetos_Ciclo2'!S:S,'Controle Projetos_Ciclo2'!$B:$B,$C7,'Controle Projetos_Ciclo2'!$F:$F,"Total") -> 0 | K7: =IFERROR(I7/H7,0) -> 0 | M7: Construção - Serviços de Construção - Substituição
B8: =B7+1 -> 5 | C8: Nova Ponte 1 | D8: MORI GERACAO II | E8: Mori II | F8: Weg | G8: Mori | H8: =SUMIFS('Controle Projetos_Ciclo2'!$O:$O,'Controle Projetos_Ciclo2'!$B:$B,$C8,'Controle Projetos_Ciclo2'!$F:$F,"Total") -> 0 | I8: =SUMIFS('Controle Projetos_Ciclo2'!$R:$R,'Controle Projetos_Ciclo2'!$B:$B,$C8,'Controle Projetos_Ciclo2'!$F:$F,"Total") -> 0 | J8: =SUMIFS('Controle Projetos_Ciclo2'!S:S,'Controle Projetos_Ciclo2'!$B:$B,$C8,'Controle Projetos_Ciclo2'!$F:$F,"Total") -> 0 | K8: =IFERROR(I8/H8,0) -> 0 | M8: Construção - RDA Interno
B9: =B8+1 -> 6 | C9: Paracatu 8 | D9: MORI GERACAO II | E9: Mori II | F9: Weg | G9: Mori | H9: =SUMIFS('Controle Projetos_Ciclo2'!$O:$O,'Controle Projetos_Ciclo2'!$B:$B,$C9,'Controle Projetos_Ciclo2'!$F:$F,"Total") -> 0 | I9: =SUMIFS('Controle Projetos_Ciclo2'!$R:$R,'Controle Projetos_Ciclo2'!$B:$B,$C9,'Controle Projetos_Ciclo2'!$F:$F,"Total") -> 0 | J9: =SUMIFS('Controle Projetos_Ciclo2'!S:S,'Controle Projetos_Ciclo2'!$B:$B,$C9,'Controle Projetos_Ciclo2'!$F:$F,"Total") -> 0 | K9: =IFERROR(I9/H9,0) -> 0 | M9: Full EPC - Contrato
B10: =B9+1 -> 7 | C10: Patos de Minas 1 | D10: MORI GERACAO II | E10: Mori II | F10: 1 | G10: Mori | H10: =SUMIFS('Controle Projetos_Ciclo2'!$O:$O,'Controle Projetos_Ciclo2'!$B:$B,$C10,'Controle Projetos_Ciclo2'!$F:$F,"Total") -> 0 | I10: =SUMIFS('Controle Projetos_Ciclo2'!$R:$R,'Controle Projetos_Ciclo2'!$B:$B,$C10,'Controle Projetos_Ciclo2'!$F:$F,"Total") -> 0 | J10: =SUMIFS('Controle Projetos_Ciclo2'!S:S,'Controle Projetos_Ciclo2'!$B:$B,$C10,'Controle Projetos_Ciclo2'!$F:$F,"Total") -> 0 | K10: =IFERROR(I10/H10,0) -> 0 | M10: Equipamentos Curva A - Outros (Transformadores)
B11: =B10+1 -> 8 | C11: Patos de Minas 3 | D11: MORI GERACAO II | E11: Mori II | F11: 2 | G11: Mori | H11: =SUMIFS('Controle Projetos_Ciclo2'!$O:$O,'Controle Projetos_Ciclo2'!$B:$B,$C11,'Controle Projetos_Ciclo2'!$F:$F,"Total") -> 0 | I11: =SUMIFS('Controle Projetos_Ciclo2'!$R:$R,'Controle Projetos_Ciclo2'!$B:$B,$C11,'Controle Projetos_Ciclo2'!$F:$F,"Total") -> 0 | J11: =SUMIFS('Controle Projetos_Ciclo2'!S:S,'Controle Projetos_Ciclo2'!$B:$B,$C11,'Controle Projetos_Ciclo2'!$F:$F,"Total") -> 0 | K11: =IFERROR(I11/H11,0) -> 0 | M11: Equipamentos Curva A - Outros (Cabine + Skid)
B12: =B11+1 -> 9 | C12: Patos de Minas 4 | D12: MORI GERACAO II | E12: Mori II | F12: 1 | G12: Mori | H12: =SUMIFS('Controle Projetos_Ciclo2'!$O:$O,'Controle Projetos_Ciclo2'!$B:$B,$C12,'Controle Projetos_Ciclo2'!$F:$F,"Total") -> 0 | I12: =SUMIFS('Controle Projetos_Ciclo2'!$R:$R,'Controle Projetos_Ciclo2'!$B:$B,$C12,'Controle Projetos_Ciclo2'!$F:$F,"Total") -> 0 | J12: =SUMIFS('Controle Projetos_Ciclo2'!S:S,'Controle Projetos_Ciclo2'!$B:$B,$C12,'Controle Projetos_Ciclo2'!$F:$F,"Total") -> 0 | K12: =IFERROR(I12/H12,0) -> 0 | M12: Equipamentos Curva A - Outros (Cabine + Skid + Transformador)
B13: =B12+1 -> 10 | C13: Patos de Minas 7 | D13: MORI GERACAO II | E13: Mori II | F13: 1 | G13: Mori | H13: =SUMIFS('Controle Projetos_Ciclo2'!$O:$O,'Controle Projetos_Ciclo2'!$B:$B,$C13,'Controle Projetos_Ciclo2'!$F:$F,"Total") -> 0 | I13: =SUMIFS('Controle Projetos_Ciclo2'!$R:$R,'Controle Projetos_Ciclo2'!$B:$B,$C13,'Controle Projetos_Ciclo2'!$F:$F,"Total") -> 0 | J13: =SUMIFS('Controle Projetos_Ciclo2'!S:S,'Controle Projetos_Ciclo2'!$B:$B,$C13,'Controle Projetos_Ciclo2'!$F:$F,"Total") -> 0 | K13: =IFERROR(I13/H13,0) -> 0 | M13: Desenvolvimento de projeto - Projetos - (Eng° Proprietario)
B14: =B13+1 -> 11 | C14: Patos de Minas 8 | D14: MORI GERACAO II | E14: Mori II | F14: 1 | G14: Mori | H14: =SUMIFS('Controle Projetos_Ciclo2'!$O:$O,'Controle Projetos_Ciclo2'!$B:$B,$C14,'Controle Projetos_Ciclo2'!$F:$F,"Total") -> 0 | I14: =SUMIFS('Controle Projetos_Ciclo2'!$R:$R,'Controle Projetos_Ciclo2'!$B:$B,$C14,'Controle Projetos_Ciclo2'!$F:$F,"Total") -> 0 | J14: =SUMIFS('Controle Projetos_Ciclo2'!S:S,'Controle Projetos_Ciclo2'!$B:$B,$C14,'Controle Projetos_Ciclo2'!$F:$F,"Total") -> 0 | K14: =IFERROR(I14/H14,0) -> 0 | M14: Desenvolvimento de projeto - Projetos - Executivos
B15: =B14+1 -> 12 | C15: Patrocínio 2 | D15: MORI GERACAO II | E15: Mori II | F15: 1 | G15: Mori | H15: =SUMIFS('Controle Projetos_Ciclo2'!$O:$O,'Controle Projetos_Ciclo2'!$B:$B,$C15,'Controle Projetos_Ciclo2'!$F:$F,"Total") -> 0 | I15: =SUMIFS('Controle Projetos_Ciclo2'!$R:$R,'Controle Projetos_Ciclo2'!$B:$B,$C15,'Controle Projetos_Ciclo2'!$F:$F,"Total") -> 0 | J15: =SUMIFS('Controle Projetos_Ciclo2'!S:S,'Controle Projetos_Ciclo2'!$B:$B,$C15,'Controle Projetos_Ciclo2'!$F:$F,"Total") -> 0 | K15: =IFERROR(I15/H15,0) -> 0 | M15: Desenvolvimento de projeto - Projetos Básica
B16: =B15+1 -> 13 | C16: Patrocínio 3 | D16: MORI GERACAO II | E16: Mori II | F16: 1 | G16: Mori | H16: =SUMIFS('Controle Projetos_Ciclo2'!$O:$O,'Controle Projetos_Ciclo2'!$B:$B,$C16,'Controle Projetos_Ciclo2'!$F:$F,"Total") -> 0 | I16: =SUMIFS('Controle Projetos_Ciclo2'!$R:$R,'Controle Projetos_Ciclo2'!$B:$B,$C16,'Controle Projetos_Ciclo2'!$F:$F,"Total") -> 0 | J16: =SUMIFS('Controle Projetos_Ciclo2'!S:S,'Controle Projetos_Ciclo2'!$B:$B,$C16,'Controle Projetos_Ciclo2'!$F:$F,"Total") -> 0 | K16: =IFERROR(I16/H16,0) -> 0 | M16: Desenvolvimento de projeto - Projetos Detalhada
B17: =B16+1 -> 14 | C17: Varjão de Minas 1 | D17: MORI GERACAO II | E17: Mori II | F17: Weg | G17: Mori | H17: =SUMIFS('Controle Projetos_Ciclo2'!$O:$O,'Controle Projetos_Ciclo2'!$B:$B,$C17,'Controle Projetos_Ciclo2'!$F:$F,"Total") -> 0 | I17: =SUMIFS('Controle Projetos_Ciclo2'!$R:$R,'Controle Projetos_Ciclo2'!$B:$B,$C17,'Controle Projetos_Ciclo2'!$F:$F,"Total") -> 0 | J17: =SUMIFS('Controle Projetos_Ciclo2'!S:S,'Controle Projetos_Ciclo2'!$B:$B,$C17,'Controle Projetos_Ciclo2'!$F:$F,"Total") -> 0 | K17: =IFERROR(I17/H17,0) -> 0 | M17: Desenvolvimento de projeto - Ambiental / Outros
B18: =B17+1 -> 15 | C18: Varjão de Minas 4 | D18: MORI GERACAO II | E18: Mori II | F18: 2 | G18: Mori | H18: =SUMIFS('Controle Projetos_Ciclo2'!$O:$O,'Controle Projetos_Ciclo2'!$B:$B,$C18,'Controle Projetos_Ciclo2'!$F:$F,"Total") -> 0 | I18: =SUMIFS('Controle Projetos_Ciclo2'!$R:$R,'Controle Projetos_Ciclo2'!$B:$B,$C18,'Controle Projetos_Ciclo2'!$F:$F,"Total") -> 0 | J18: =SUMIFS('Controle Projetos_Ciclo2'!S:S,'Controle Projetos_Ciclo2'!$B:$B,$C18,'Controle Projetos_Ciclo2'!$F:$F,"Total") -> 0 | K18: =IFERROR(I18/H18,0) -> 0 | M18: Desenvolvimento de projeto - Coordenograma
B19: =B18+1 -> 16 | C19: Buritizeiro 1 | D19: ESTRELA DO NORTE | E19: EDN | F19: 1 | G19: Apolo | H19: =SUMIFS('Controle Projetos_Ciclo2'!$O:$O,'Controle Projetos_Ciclo2'!$B:$B,$C19,'Controle Projetos_Ciclo2'!$F:$F,"Total") -> 0 | I19: =SUMIFS('Controle Projetos_Ciclo2'!$R:$R,'Controle Projetos_Ciclo2'!$B:$B,$C19,'Controle Projetos_Ciclo2'!$F:$F,"Total") -> 0 | J19: =SUMIFS('Controle Projetos_Ciclo2'!S:S,'Controle Projetos_Ciclo2'!$B:$B,$C19,'Controle Projetos_Ciclo2'!$F:$F,"Total") -> 0 | K19: =IFERROR(I19/H19,0) -> 0 | M19: Sistemas de Monitoramento - Supervisório
B20: =B19+1 -> 17 | C20: Buritizeiro 2 | D20: ESTRELA DO NORTE | E20: EDN | F20: 1 | G20: Apolo | H20: =SUMIFS('Controle Projetos_Ciclo2'!$O:$O,'Controle Projetos_Ciclo2'!$B:$B,$C20,'Controle Projetos_Ciclo2'!$F:$F,"Total") -> 0 | I20: =SUMIFS('Controle Projetos_Ciclo2'!$R:$R,'Controle Projetos_Ciclo2'!$B:$B,$C20,'Controle Projetos_Ciclo2'!$F:$F,"Total") -> 0 | J20: =SUMIFS('Controle Projetos_Ciclo2'!S:S,'Controle Projetos_Ciclo2'!$B:$B,$C20,'Controle Projetos_Ciclo2'!$F:$F,"Total") -> 0 | K20: =IFERROR(I20/H20,0) -> 0 | M20: Sistemas de Monitoramento - Estações Solarimétricas
B21: =B20+1 -> 18 | C21: Guarda-Mor | D21: ESTRELA DO NORTE | E21: EDN | F21: Weg | G21: Apolo | H21: =SUMIFS('Controle Projetos_Ciclo2'!$O:$O,'Controle Projetos_Ciclo2'!$B:$B,$C21,'Controle Projetos_Ciclo2'!$F:$F,"Total") -> 0 | I21: =SUMIFS('Controle Projetos_Ciclo2'!$R:$R,'Controle Projetos_Ciclo2'!$B:$B,$C21,'Controle Projetos_Ciclo2'!$F:$F,"Total") -> 0 | J21: =SUMIFS('Controle Projetos_Ciclo2'!S:S,'Controle Projetos_Ciclo2'!$B:$B,$C21,'Controle Projetos_Ciclo2'!$F:$F,"Total") -> 0 | K21: =IFERROR(I21/H21,0) -> 0 | M21: Sistemas de Monitoramento - CFTV
B22: =B21+1 -> 19 | C22: Indaiabira 1 | D22: ESTRELA DO NORTE | E22: EDN | F22: Weg | G22: Apolo | H22: =SUMIFS('Controle Projetos_Ciclo2'!$O:$O,'Controle Projetos_Ciclo2'!$B:$B,$C22,'Controle Projetos_Ciclo2'!$F:$F,"Total") -> 0 | I22: =SUMIFS('Controle Projetos_Ciclo2'!$R:$R,'Controle Projetos_Ciclo2'!$B:$B,$C22,'Controle Projetos_Ciclo2'!$F:$F,"Total") -> 0 | J22: =SUMIFS('Controle Projetos_Ciclo2'!S:S,'Controle Projetos_Ciclo2'!$B:$B,$C22,'Controle Projetos_Ciclo2'!$F:$F,"Total") -> 0 | K22: =IFERROR(I22/H22,0) -> 0 | M22: Serviços Auxiliares - Drenagem
B23: =B22+1 -> 20 | C23: Indaiabira 2 | D23: ESTRELA DO NORTE | E23: EDN | F23: Weg | G23: Apolo | H23: =SUMIFS('Controle Projetos_Ciclo2'!$O:$O,'Controle Projetos_Ciclo2'!$B:$B,$C23,'Controle Projetos_Ciclo2'!$F:$F,"Total") -> 0 | I23: =SUMIFS('Controle Projetos_Ciclo2'!$R:$R,'Controle Projetos_Ciclo2'!$B:$B,$C23,'Controle Projetos_Ciclo2'!$F:$F,"Total") -> 0 | J23: =SUMIFS('Controle Projetos_Ciclo2'!S:S,'Controle Projetos_Ciclo2'!$B:$B,$C23,'Controle Projetos_Ciclo2'!$F:$F,"Total") -> 0 | K23: =IFERROR(I23/H23,0) -> 0 | M23: Serviços Auxiliares - Terraplanagem
B24: =B23+1 -> 21 | C24: Indaiabira 3 | D24: ESTRELA DO NORTE | E24: EDN | F24: 1 | G24: Apolo | H24: =SUMIFS('Controle Projetos_Ciclo2'!$O:$O,'Controle Projetos_Ciclo2'!$B:$B,$C24,'Controle Projetos_Ciclo2'!$F:$F,"Total") -> 0 | I24: =SUMIFS('Controle Projetos_Ciclo2'!$R:$R,'Controle Projetos_Ciclo2'!$B:$B,$C24,'Controle Projetos_Ciclo2'!$F:$F,"Total") -> 0 | J24: =SUMIFS('Controle Projetos_Ciclo2'!S:S,'Controle Projetos_Ciclo2'!$B:$B,$C24,'Controle Projetos_Ciclo2'!$F:$F,"Total") -> 0 | K24: =IFERROR(I24/H24,0) -> 0 | M24: Serviços Auxiliares - Supressão Vegetal
B25: =B24+1 -> 22 | C25: Indaiabira 4 | D25: ESTRELA DO NORTE | E25: EDN | F25: 1 | G25: Apolo | H25: =SUMIFS('Controle Projetos_Ciclo2'!$O:$O,'Controle Projetos_Ciclo2'!$B:$B,$C25,'Controle Projetos_Ciclo2'!$F:$F,"Total") -> 0 | I25: =SUMIFS('Controle Projetos_Ciclo2'!$R:$R,'Controle Projetos_Ciclo2'!$B:$B,$C25,'Controle Projetos_Ciclo2'!$F:$F,"Total") -> 0 | J25: =SUMIFS('Controle Projetos_Ciclo2'!S:S,'Controle Projetos_Ciclo2'!$B:$B,$C25,'Controle Projetos_Ciclo2'!$F:$F,"Total") -> 0 | K25: =IFERROR(I25/H25,0) -> 0 | M25: RDR-Rede de Distribuição Rural
B26: =B25+1 -> 23 | C26: Jaboticatubas | D26: ESTRELA DO NORTE | E26: EDN | F26: 3 | G26: Apolo | H26: =SUMIFS('Controle Projetos_Ciclo2'!$O:$O,'Controle Projetos_Ciclo2'!$B:$B,$C26,'Controle Projetos_Ciclo2'!$F:$F,"Total") -> 0 | I26: =SUMIFS('Controle Projetos_Ciclo2'!$R:$R,'Controle Projetos_Ciclo2'!$B:$B,$C26,'Controle Projetos_Ciclo2'!$F:$F,"Total") -> 0 | J26: =SUMIFS('Controle Projetos_Ciclo2'!S:S,'Controle Projetos_Ciclo2'!$B:$B,$C26,'Controle Projetos_Ciclo2'!$F:$F,"Total") -> 0 | K26: =IFERROR(I26/H26,0) -> 0 | M26: Escopo COMERC
B27: =B26+1 -> 24 | C27: São Sebastião 0 | D27: ESTRELA DO NORTE | E27: EDN | F27: 3 | G27: Apolo | H27: =SUMIFS('Controle Projetos_Ciclo2'!$O:$O,'Controle Projetos_Ciclo2'!$B:$B,$C27,'Controle Projetos_Ciclo2'!$F:$F,"Total") -> 0 | I27: =SUMIFS('Controle Projetos_Ciclo2'!$R:$R,'Controle Projetos_Ciclo2'!$B:$B,$C27,'Controle Projetos_Ciclo2'!$F:$F,"Total") -> 0 | J27: =SUMIFS('Controle Projetos_Ciclo2'!S:S,'Controle Projetos_Ciclo2'!$B:$B,$C27,'Controle Projetos_Ciclo2'!$F:$F,"Total") -> 0 | K27: =IFERROR(I27/H27,0) -> 0 | M27: Não Controlado
B28: =B27+1 -> 25 | C28: Divinópolis 1 | D28: ESTRELA DO NORTE | E28: EDN | F28: 2 | G28: Apolo | H28: =SUMIFS('Controle Projetos_Ciclo2'!$O:$O,'Controle Projetos_Ciclo2'!$B:$B,$C28,'Controle Projetos_Ciclo2'!$F:$F,"Total") -> 0 | I28: =SUMIFS('Controle Projetos_Ciclo2'!$R:$R,'Controle Projetos_Ciclo2'!$B:$B,$C28,'Controle Projetos_Ciclo2'!$F:$F,"Total") -> 0 | J28: =SUMIFS('Controle Projetos_Ciclo2'!S:S,'Controle Projetos_Ciclo2'!$B:$B,$C28,'Controle Projetos_Ciclo2'!$F:$F,"Total") -> 0 | K28: =IFERROR(I28/H28,0) -> 0 | M28: Controle da Lais
B29: =B28+1 -> 26 | C29: Divinópolis 2 | D29: ESTRELA DO NORTE | E29: EDN | F29: 2 | G29: Apolo | H29: =SUMIFS('Controle Projetos_Ciclo2'!$O:$O,'Controle Projetos_Ciclo2'!$B:$B,$C29,'Controle Projetos_Ciclo2'!$F:$F,"Total") -> 0 | I29: =SUMIFS('Controle Projetos_Ciclo2'!$R:$R,'Controle Projetos_Ciclo2'!$B:$B,$C29,'Controle Projetos_Ciclo2'!$F:$F,"Total") -> 0 | J29: =SUMIFS('Controle Projetos_Ciclo2'!S:S,'Controle Projetos_Ciclo2'!$B:$B,$C29,'Controle Projetos_Ciclo2'!$F:$F,"Total") -> 0 | K29: =IFERROR(I29/H29,0) -> 0 | M29: Escopo COMERC - Segurança
B30: =B29+1 -> 27 | C30: Divinópolis 3 | D30: ESTRELA DO NORTE | E30: EDN | F30: 1 | G30: Apolo | H30: =SUMIFS('Controle Projetos_Ciclo2'!$O:$O,'Controle Projetos_Ciclo2'!$B:$B,$C30,'Controle Projetos_Ciclo2'!$F:$F,"Total") -> 0 | I30: =SUMIFS('Controle Projetos_Ciclo2'!$R:$R,'Controle Projetos_Ciclo2'!$B:$B,$C30,'Controle Projetos_Ciclo2'!$F:$F,"Total") -> 0 | J30: =SUMIFS('Controle Projetos_Ciclo2'!S:S,'Controle Projetos_Ciclo2'!$B:$B,$C30,'Controle Projetos_Ciclo2'!$F:$F,"Total") -> 0 | K30: =IFERROR(I30/H30,0) -> 0 | M30: Conexão MT - Obras Transferencia
B31: =B30+1 -> 28 | C31: Pedra do Indaiá 1 | D31: ESTRELA DO NORTE | E31: EDN | F31: 1 | G31: Apolo | H31: =SUMIFS('Controle Projetos_Ciclo2'!$O:$O,'Controle Projetos_Ciclo2'!$B:$B,$C31,'Controle Projetos_Ciclo2'!$F:$F,"Total") -> 0 | I31: =SUMIFS('Controle Projetos_Ciclo2'!$R:$R,'Controle Projetos_Ciclo2'!$B:$B,$C31,'Controle Projetos_Ciclo2'!$F:$F,"Total") -> 0 | J31: =SUMIFS('Controle Projetos_Ciclo2'!S:S,'Controle Projetos_Ciclo2'!$B:$B,$C31,'Controle Projetos_Ciclo2'!$F:$F,"Total") -> 0 | K31: =IFERROR(I31/H31,0) -> 0 | M31: Bases de Contaniers
B32: =B31+1 -> 29 | C32: Pedra do Indaiá 3 | D32: ESTRELA DO NORTE | E32: EDN | F32: 1 | G32: Apolo | H32: =SUMIFS('Controle Projetos_Ciclo2'!$O:$O,'Controle Projetos_Ciclo2'!$B:$B,$C32,'Controle Projetos_Ciclo2'!$F:$F,"Total") -> 0 | I32: =SUMIFS('Controle Projetos_Ciclo2'!$R:$R,'Controle Projetos_Ciclo2'!$B:$B,$C32,'Controle Projetos_Ciclo2'!$F:$F,"Total") -> 0 | J32: =SUMIFS('Controle Projetos_Ciclo2'!S:S,'Controle Projetos_Ciclo2'!$B:$B,$C32,'Controle Projetos_Ciclo2'!$F:$F,"Total") -> 0 | K32: =IFERROR(I32/H32,0) -> 0 | M32: Construção - Serviços de Construção - Ase Engenharia
B33: =B32+1 -> 30 | C33: Pedra do Indaiá 5 | D33: ESTRELA DO NORTE | E33: EDN | F33: 1 | G33: Apolo | H33: =SUMIFS('Controle Projetos_Ciclo2'!$O:$O,'Controle Projetos_Ciclo2'!$B:$B,$C33,'Controle Projetos_Ciclo2'!$F:$F,"Total") -> 0 | I33: =SUMIFS('Controle Projetos_Ciclo2'!$R:$R,'Controle Projetos_Ciclo2'!$B:$B,$C33,'Controle Projetos_Ciclo2'!$F:$F,"Total") -> 0 | J33: =SUMIFS('Controle Projetos_Ciclo2'!S:S,'Controle Projetos_Ciclo2'!$B:$B,$C33,'Controle Projetos_Ciclo2'!$F:$F,"Total") -> 0 | K33: =IFERROR(I33/H33,0) -> 0 | M33: Full EPC - Contrato Sobressalentes
B34: =B33+1 -> 31 | C34: Pains 1 | D34: ESTRELA DO NORTE | E34: EDN | F34: 3 | G34: Apolo | H34: =SUMIFS('Controle Projetos_Ciclo2'!$O:$O,'Controle Projetos_Ciclo2'!$B:$B,$C34,'Controle Projetos_Ciclo2'!$F:$F,"Total") -> 0 | I34: =SUMIFS('Controle Projetos_Ciclo2'!$R:$R,'Controle Projetos_Ciclo2'!$B:$B,$C34,'Controle Projetos_Ciclo2'!$F:$F,"Total") -> 0 | J34: =SUMIFS('Controle Projetos_Ciclo2'!S:S,'Controle Projetos_Ciclo2'!$B:$B,$C34,'Controle Projetos_Ciclo2'!$F:$F,"Total") -> 0 | K34: =IFERROR(I34/H34,0) -> 0 | M34: Construção - Serviços de Construção - NOVA MORADA
B35: =B34+1 -> 32 | C35: Pains 2 | D35: ESTRELA DO NORTE | E35: EDN | F35: 3 | G35: Apolo | H35: =SUMIFS('Controle Projetos_Ciclo2'!$O:$O,'Controle Projetos_Ciclo2'!$B:$B,$C35,'Controle Projetos_Ciclo2'!$F:$F,"Total") -> 0 | I35: =SUMIFS('Controle Projetos_Ciclo2'!$R:$R,'Controle Projetos_Ciclo2'!$B:$B,$C35,'Controle Projetos_Ciclo2'!$F:$F,"Total") -> 0 | J35: =SUMIFS('Controle Projetos_Ciclo2'!S:S,'Controle Projetos_Ciclo2'!$B:$B,$C35,'Controle Projetos_Ciclo2'!$F:$F,"Total") -> 0 | K35: =IFERROR(I35/H35,0) -> 0 | M35: Equipamentos Curva A - Contrato Sobressalentes - SETTA
... B40: =B39+1 -> 37 | C40: Paracatu 5 | D40: ESTRELA DO NORTE | E40: EDN | F40: 3 | G40: Apolo | H40: =SUMIFS('Controle Projetos_Ciclo2'!$O:$O,'Controle Projetos_Ciclo2'!$B:$B,$C40,'Controle Projetos_Ciclo2'!$F:$F,"Total") -> 0 | I40: =SUMIFS('Controle Projetos_Ciclo2'!$R:$R,'Controle Projetos_Ciclo2'!$B:$B,$C40,'Controle Projetos_Ciclo2'!$F:$F,"Total") -> 0 | J40: =SUMIFS('Controle Projetos_Ciclo2'!S:S,'Controle Projetos_Ciclo2'!$B:$B,$C40,'Controle Projetos_Ciclo2'!$F:$F,"Total") -> 0 | K40: =IFERROR(I40/H40,0) -> 0 | M40: *
B41: =B40+1 -> 38 | C41: Alfenas 4 | D41: MORI MINAS V | E41: NewCo V | F41: 2 | G41: Solatio | H41: =SUMIFS('Controle Projetos_Ciclo2'!$O:$O,'Controle Projetos_Ciclo2'!$B:$B,$C41,'Controle Projetos_Ciclo2'!$F:$F,"Total") -> 2771538.7 | I41: =SUMIFS('Controle Projetos_Ciclo2'!$R:$R,'Controle Projetos_Ciclo2'!$B:$B,$C41,'Controle Projetos_Ciclo2'!$F:$F,"Total") -> 2686059.9 | J41: =SUMIFS('Controle Projetos_Ciclo2'!S:S,'Controle Projetos_Ciclo2'!$B:$B,$C41,'Controle Projetos_Ciclo2'!$F:$F,"Total") -> 85478.84 | K41: =IFERROR(I41/H41,0) -> 0.96915835
B42: =B41+1 -> 39 | C42: Arcos 7 | D42: MORI MINAS IV | E42: NewCo IV | F42: 1 | G42: Solatio | H42: =SUMIFS('Controle Projetos_Ciclo2'!$O:$O,'Controle Projetos_Ciclo2'!$B:$B,$C42,'Controle Projetos_Ciclo2'!$F:$F,"Total") -> 0 | I42: =SUMIFS('Controle Projetos_Ciclo2'!$R:$R,'Controle Projetos_Ciclo2'!$B:$B,$C42,'Controle Projetos_Ciclo2'!$F:$F,"Total") -> 0 | J42: =SUMIFS('Controle Projetos_Ciclo2'!S:S,'Controle Projetos_Ciclo2'!$B:$B,$C42,'Controle Projetos_Ciclo2'!$F:$F,"Total") -> 0 | K42: =IFERROR(I42/H42,0) -> 0
B43: =B42+1 -> 40 | C43: Bambuí 1.1 | D43: MORI MINAS IV | E43: NewCo IV | F43: Weg | G43: Solatio | H43: =SUMIFS('Controle Projetos_Ciclo2'!$O:$O,'Controle Projetos_Ciclo2'!$B:$B,$C43,'Controle Projetos_Ciclo2'!$F:$F,"Total") -> 0 | I43: =SUMIFS('Controle Projetos_Ciclo2'!$R:$R,'Controle Projetos_Ciclo2'!$B:$B,$C43,'Controle Projetos_Ciclo2'!$F:$F,"Total") -> 0 | J43: =SUMIFS('Controle Projetos_Ciclo2'!S:S,'Controle Projetos_Ciclo2'!$B:$B,$C43,'Controle Projetos_Ciclo2'!$F:$F,"Total") -> 0 | K43: =IFERROR(I43/H43,0) -> 0
B44: =B43+1 -> 41 | C44: Bambuí 1.2 | D44: MORI MINAS V | E44: NewCo V | F44: Weg | G44: Solatio | H44: =SUMIFS('Controle Projetos_Ciclo2'!$O:$O,'Controle Projetos_Ciclo2'!$B:$B,$C44,'Controle Projetos_Ciclo2'!$F:$F,"Total") -> 0 | I44: =SUMIFS('Controle Projetos_Ciclo2'!$R:$R,'Controle Projetos_Ciclo2'!$B:$B,$C44,'Controle Projetos_Ciclo2'!$F:$F,"Total") -> 0 | J44: =SUMIFS('Controle Projetos_Ciclo2'!S:S,'Controle Projetos_Ciclo2'!$B:$B,$C44,'Controle Projetos_Ciclo2'!$F:$F,"Total") -> 0 | K44: =IFERROR(I44/H44,0) -> 0
B45: =B44+1 -> 42 | C45: Campo Belo 1 | D45: MORI MINAS IV | E45: NewCo IV | F45: 2 | G45: Solatio | H45: =SUMIFS('Controle Projetos_Ciclo2'!$O:$O,'Controle Projetos_Ciclo2'!$B:$B,$C45,'Controle Projetos_Ciclo2'!$F:$F,"Total") -> 0 | I45: =SUMIFS('Controle Projetos_Ciclo2'!$R:$R,'Controle Projetos_Ciclo2'!$B:$B,$C45,'Controle Projetos_Ciclo2'!$F:$F,"Total") -> 0 | J45: =SUMIFS('Controle Projetos_Ciclo2'!S:S,'Controle Projetos_Ciclo2'!$B:$B,$C45,'Controle Projetos_Ciclo2'!$F:$F,"Total") -> 0 | K45: =IFERROR(I45/H45,0) -> 0
B46: =B45+1 -> 43 | C46: Campo Belo 2 | D46: MORI MINAS V | E46: NewCo V | F46: 2 | G46: Solatio | H46: =SUMIFS('Controle Projetos_Ciclo2'!$O:$O,'Controle Projetos_Ciclo2'!$B:$B,$C46,'Controle Projetos_Ciclo2'!$F:$F,"Total") -> 0 | I46: =SUMIFS('Controle Projetos_Ciclo2'!$R:$R,'Controle Projetos_Ciclo2'!$B:$B,$C46,'Controle Projetos_Ciclo2'!$F:$F,"Total") -> 0 | J46: =SUMIFS('Controle Projetos_Ciclo2'!S:S,'Controle Projetos_Ciclo2'!$B:$B,$C46,'Controle Projetos_Ciclo2'!$F:$F,"Total") -> 0 | K46: =IFERROR(I46/H46,0) -> 0
B47: =B46+1 -> 44 | C47: Campo Belo 3 | D47: MORI MINAS IV | E47: NewCo IV | F47: Weg | G47: Solatio | H47: =SUMIFS('Controle Projetos_Ciclo2'!$O:$O,'Controle Projetos_Ciclo2'!$B:$B,$C47,'Controle Projetos_Ciclo2'!$F:$F,"Total") -> 0 | I47: =SUMIFS('Controle Projetos_Ciclo2'!$R:$R,'Controle Projetos_Ciclo2'!$B:$B,$C47,'Controle Projetos_Ciclo2'!$F:$F,"Total") -> 0 | J47: =SUMIFS('Controle Projetos_Ciclo2'!S:S,'Controle Projetos_Ciclo2'!$B:$B,$C47,'Controle Projetos_Ciclo2'!$F:$F,"Total") -> 0 | K47: =IFERROR(I47/H47,0) -> 0
B48: =B47+1 -> 45 | C48: Campo Belo 4 | D48: MORI MINAS V | E48: NewCo V | F48: Weg | G48: Solatio | H48: =SUMIFS('Controle Projetos_Ciclo2'!$O:$O,'Controle Projetos_Ciclo2'!$B:$B,$C48,'Controle Projetos_Ciclo2'!$F:$F,"Total") -> 0 | I48: =SUMIFS('Controle Projetos_Ciclo2'!$R:$R,'Controle Projetos_Ciclo2'!$B:$B,$C48,'Controle Projetos_Ciclo2'!$F:$F,"Total") -> 0 | J48: =SUMIFS('Controle Projetos_Ciclo2'!S:S,'Controle Projetos_Ciclo2'!$B:$B,$C48,'Controle Projetos_Ciclo2'!$F:$F,"Total") -> 0 | K48: =IFERROR(I48/H48,0) -> 0
B49: =B48+1 -> 46 | C49: Campo Belo 5 | D49: MORI MINAS IV | E49: NewCo IV | F49: 1 | G49: Solatio | H49: =SUMIFS('Controle Projetos_Ciclo2'!$O:$O,'Controle Projetos_Ciclo2'!$B:$B,$C49,'Controle Projetos_Ciclo2'!$F:$F,"Total") -> 2390751.2 | I49: =SUMIFS('Controle Projetos_Ciclo2'!$R:$R,'Controle Projetos_Ciclo2'!$B:$B,$C49,'Controle Projetos_Ciclo2'!$F:$F,"Total") -> 2330205.1 | J49: =SUMIFS('Controle Projetos_Ciclo2'!S:S,'Controle Projetos_Ciclo2'!$B:$B,$C49,'Controle Projetos_Ciclo2'!$F:$F,"Total") -> 60546.04 | K49: =IFERROR(I49/H49,0) -> 0.97467489
B50: =B49+1 -> 47 | C50: Cássia 1 | D50: MORI MINAS IV | E50: NewCo IV | F50: Weg | G50: Solatio | H50: =SUMIFS('Controle Projetos_Ciclo2'!$O:$O,'Controle Projetos_Ciclo2'!$B:$B,$C50,'Controle Projetos_Ciclo2'!$F:$F,"Total") -> 0 | I50: =SUMIFS('Controle Projetos_Ciclo2'!$R:$R,'Controle Projetos_Ciclo2'!$B:$B,$C50,'Controle Projetos_Ciclo2'!$F:$F,"Total") -> 0 | J50: =SUMIFS('Controle Projetos_Ciclo2'!S:S,'Controle Projetos_Ciclo2'!$B:$B,$C50,'Controle Projetos_Ciclo2'!$F:$F,"Total") -> 0 | K50: =IFERROR(I50/H50,0) -> 0
B51: =B50+1 -> 48 | C51: Cássia 2 | D51: MORI MINAS V | E51: NewCo V | F51: Weg | G51: Solatio | H51: =SUMIFS('Controle Projetos_Ciclo2'!$O:$O,'Controle Projetos_Ciclo2'!$B:$B,$C51,'Controle Projetos_Ciclo2'!$F:$F,"Total") -> 0 | I51: =SUMIFS('Controle Projetos_Ciclo2'!$R:$R,'Controle Projetos_Ciclo2'!$B:$B,$C51,'Controle Projetos_Ciclo2'!$F:$F,"Total") -> 0 | J51: =SUMIFS('Controle Projetos_Ciclo2'!S:S,'Controle Projetos_Ciclo2'!$B:$B,$C51,'Controle Projetos_Ciclo2'!$F:$F,"Total") -> 0 | K51: =IFERROR(I51/H51,0) -> 0
B52: =B51+1 -> 49 | C52: Formiga 6 | D52: MORI MINAS V | E52: NewCo V | F52: 1 | G52: Solatio | H52: =SUMIFS('Controle Projetos_Ciclo2'!$O:$O,'Controle Projetos_Ciclo2'!$B:$B,$C52,'Controle Projetos_Ciclo2'!$F:$F,"Total") -> 0 | I52: =SUMIFS('Controle Projetos_Ciclo2'!$R:$R,'Controle Projetos_Ciclo2'!$B:$B,$C52,'Controle Projetos_Ciclo2'!$F:$F,"Total") -> 0 | J52: =SUMIFS('Controle Projetos_Ciclo2'!S:S,'Controle Projetos_Ciclo2'!$B:$B,$C52,'Controle Projetos_Ciclo2'!$F:$F,"Total") -> 0 | K52: =IFERROR(I52/H52,0) -> 0
B53: =B52+1 -> 50 | C53: Passos 4 | D53: MORI MINAS V | E53: NewCo V | F53: 3 | G53: Solatio | H53: =SUMIFS('Controle Projetos_Ciclo2'!$O:$O,'Controle Projetos_Ciclo2'!$B:$B,$C53,'Controle Projetos_Ciclo2'!$F:$F,"Total") -> 0 | I53: =SUMIFS('Controle Projetos_Ciclo2'!$R:$R,'Controle Projetos_Ciclo2'!$B:$B,$C53,'Controle Projetos_Ciclo2'!$F:$F,"Total") -> 0 | J53: =SUMIFS('Controle Projetos_Ciclo2'!S:S,'Controle Projetos_Ciclo2'!$B:$B,$C53,'Controle Projetos_Ciclo2'!$F:$F,"Total") -> 0 | K53: =IFERROR(I53/H53,0) -> 0
B54: =B53+1 -> 51 | C54: Paraguaçu 1 | D54: MORI MINAS IV | E54: NewCo IV | F54: 3 | G54: Solatio | H54: =SUMIFS('Controle Projetos_Ciclo2'!$O:$O,'Controle Projetos_Ciclo2'!$B:$B,$C54,'Controle Projetos_Ciclo2'!$F:$F,"Total") -> 0 | I54: =SUMIFS('Controle Projetos_Ciclo2'!$R:$R,'Controle Projetos_Ciclo2'!$B:$B,$C54,'Controle Projetos_Ciclo2'!$F:$F,"Total") -> 0 | J54: =SUMIFS('Controle Projetos_Ciclo2'!S:S,'Controle Projetos_Ciclo2'!$B:$B,$C54,'Controle Projetos_Ciclo2'!$F:$F,"Total") -> 0 | K54: =IFERROR(I54/H54,0) -> 0
B55: =B54+1 -> 52 | C55: Santo Antônio 1 | D55: MORI MINAS IV | E55: NewCo IV | F55: 2 | G55: Solatio | H55: =SUMIFS('Controle Projetos_Ciclo2'!$O:$O,'Controle Projetos_Ciclo2'!$B:$B,$C55,'Controle Projetos_Ciclo2'!$F:$F,"Total") -> 2350720.5 | I55: =SUMIFS('Controle Projetos_Ciclo2'!$R:$R,'Controle Projetos_Ciclo2'!$B:$B,$C55,'Controle Projetos_Ciclo2'!$F:$F,"Total") -> 2241416.1 | J55: =SUMIFS('Controle Projetos_Ciclo2'!S:S,'Controle Projetos_Ciclo2'!$B:$B,$C55,'Controle Projetos_Ciclo2'!$F:$F,"Total") -> 109304.41 | K55: =IFERROR(I55/H55,0) -> 0.95350174
B56: =B55+1 -> 53 | C56: São Sebastião 1 | D56: MORI MINAS IV | E56: NewCo IV | F56: weg | G56: Solatio | H56: =SUMIFS('Controle Projetos_Ciclo2'!$O:$O,'Controle Projetos_Ciclo2'!$B:$B,$C56,'Controle Projetos_Ciclo2'!$F:$F,"Total") -> 0 | I56: =SUMIFS('Controle Projetos_Ciclo2'!$R:$R,'Controle Projetos_Ciclo2'!$B:$B,$C56,'Controle Projetos_Ciclo2'!$F:$F,"Total") -> 0 | J56: =SUMIFS('Controle Projetos_Ciclo2'!S:S,'Controle Projetos_Ciclo2'!$B:$B,$C56,'Controle Projetos_Ciclo2'!$F:$F,"Total") -> 0 | K56: =IFERROR(I56/H56,0) -> 0
B57: =B56+1 -> 54 | C57: São Sebastião 3 | D57: MORI MINAS V | E57: NewCo V | F57: weg | G57: Solatio | H57: =SUMIFS('Controle Projetos_Ciclo2'!$O:$O,'Controle Projetos_Ciclo2'!$B:$B,$C57,'Controle Projetos_Ciclo2'!$F:$F,"Total") -> 0 | I57: =SUMIFS('Controle Projetos_Ciclo2'!$R:$R,'Controle Projetos_Ciclo2'!$B:$B,$C57,'Controle Projetos_Ciclo2'!$F:$F,"Total") -> 0 | J57: =SUMIFS('Controle Projetos_Ciclo2'!S:S,'Controle Projetos_Ciclo2'!$B:$B,$C57,'Controle Projetos_Ciclo2'!$F:$F,"Total") -> 0 | K57: =IFERROR(I57/H57,0) -> 0
B58: =B57+1 -> 55 | C58: São Sebastião 4 | D58: MORI MINAS IV | E58: NewCo IV | F58: 3 | G58: Solatio | H58: =SUMIFS('Controle Projetos_Ciclo2'!$O:$O,'Controle Projetos_Ciclo2'!$B:$B,$C58,'Controle Projetos_Ciclo2'!$F:$F,"Total") -> 0 | I58: =SUMIFS('Controle Projetos_Ciclo2'!$R:$R,'Controle Projetos_Ciclo2'!$B:$B,$C58,'Controle Projetos_Ciclo2'!$F:$F,"Total") -> 0 | J58: =SUMIFS('Controle Projetos_Ciclo2'!S:S,'Controle Projetos_Ciclo2'!$B:$B,$C58,'Controle Projetos_Ciclo2'!$F:$F,"Total") -> 0 | K58: =IFERROR(I58/H58,0) -> 0
B59: =B58+1 -> 56 | C59: São Sebastião 5 | D59: MORI MINAS V | E59: NewCo V | F59: Weg | G59: Solatio | H59: =SUMIFS('Controle Projetos_Ciclo2'!$O:$O,'Controle Projetos_Ciclo2'!$B:$B,$C59,'Controle Projetos_Ciclo2'!$F:$F,"Total") -> 0 | I59: =SUMIFS('Controle Projetos_Ciclo2'!$R:$R,'Controle Projetos_Ciclo2'!$B:$B,$C59,'Controle Projetos_Ciclo2'!$F:$F,"Total") -> 0 | J59: =SUMIFS('Controle Projetos_Ciclo2'!S:S,'Controle Projetos_Ciclo2'!$B:$B,$C59,'Controle Projetos_Ciclo2'!$F:$F,"Total") -> 0 | K59: =IFERROR(I59/H59,0) -> 0
B60: =B59+1 -> 57 | C60: Varginha 1 | D60: MORI MINAS IV | E60: NewCo IV | F60: 1 | G60: Solatio | H60: =SUMIFS('Controle Projetos_Ciclo2'!$O:$O,'Controle Projetos_Ciclo2'!$B:$B,$C60,'Controle Projetos_Ciclo2'!$F:$F,"Total") -> 0 | I60: =SUMIFS('Controle Projetos_Ciclo2'!$R:$R,'Controle Projetos_Ciclo2'!$B:$B,$C60,'Controle Projetos_Ciclo2'!$F:$F,"Total") -> 0 | J60: =SUMIFS('Controle Projetos_Ciclo2'!S:S,'Controle Projetos_Ciclo2'!$B:$B,$C60,'Controle Projetos_Ciclo2'!$F:$F,"Total") -> 0 | K60: =IFERROR(I60/H60,0) -> 0
B61: =B60+1 -> 58 | C61: Varginha 2 | D61: MORI MINAS V | E61: NewCo V | F61: 1 | G61: Solatio | H61: =SUMIFS('Controle Projetos_Ciclo2'!$O:$O,'Controle Projetos_Ciclo2'!$B:$B,$C61,'Controle Projetos_Ciclo2'!$F:$F,"Total") -> 0 | I61: =SUMIFS('Controle Projetos_Ciclo2'!$R:$R,'Controle Projetos_Ciclo2'!$B:$B,$C61,'Controle Projetos_Ciclo2'!$F:$F,"Total") -> 0 | J61: =SUMIFS('Controle Projetos_Ciclo2'!S:S,'Controle Projetos_Ciclo2'!$B:$B,$C61,'Controle Projetos_Ciclo2'!$F:$F,"Total") -> 0 | K61: =IFERROR(I61/H61,0) -> 0
B62: =B61+1 -> 59 | C62: Varginha 5 | D62: MORI MINAS IV | E62: NewCo IV | F62: 1 | G62: Solatio | H62: =SUMIFS('Controle Projetos_Ciclo2'!$O:$O,'Controle Projetos_Ciclo2'!$B:$B,$C62,'Controle Projetos_Ciclo2'!$F:$F,"Total") -> 0 | I62: =SUMIFS('Controle Projetos_Ciclo2'!$R:$R,'Controle Projetos_Ciclo2'!$B:$B,$C62,'Controle Projetos_Ciclo2'!$F:$F,"Total") -> 0 | J62: =SUMIFS('Controle Projetos_Ciclo2'!S:S,'Controle Projetos_Ciclo2'!$B:$B,$C62,'Controle Projetos_Ciclo2'!$F:$F,"Total") -> 0 | K62: =IFERROR(I62/H62,0) -> 0
B63: =B62+1 -> 60 | C63: Três Corações 3 | D63: MORI MINAS IV | E63: NewCo IV | F63: 3 | G63: Solatio | H63: =SUMIFS('Controle Projetos_Ciclo2'!$O:$O,'Controle Projetos_Ciclo2'!$B:$B,$C63,'Controle Projetos_Ciclo2'!$F:$F,"Total") -> 2856667 | I63: =SUMIFS('Controle Projetos_Ciclo2'!$R:$R,'Controle Projetos_Ciclo2'!$B:$B,$C63,'Controle Projetos_Ciclo2'!$F:$F,"Total") -> 2653487.6 | J63: =SUMIFS('Controle Projetos_Ciclo2'!S:S,'Controle Projetos_Ciclo2'!$B:$B,$C63,'Controle Projetos_Ciclo2'!$F:$F,"Total") -> 203179.44 | K63: =IFERROR(I63/H63,0) -> 0.92887535
B64: =B63+1 -> 61 | C64: Ouro Fino 2 | D64: MORI MINAS IV | E64: NewCo IV | F64: 3 | G64: Solatio | H64: =SUMIFS('Controle Projetos_Ciclo2'!$O:$O,'Controle Projetos_Ciclo2'!$B:$B,$C64,'Controle Projetos_Ciclo2'!$F:$F,"Total") -> 0 | I64: =SUMIFS('Controle Projetos_Ciclo2'!$R:$R,'Controle Projetos_Ciclo2'!$B:$B,$C64,'Controle Projetos_Ciclo2'!$F:$F,"Total") -> 0 | J64: =SUMIFS('Controle Projetos_Ciclo2'!S:S,'Controle Projetos_Ciclo2'!$B:$B,$C64,'Controle Projetos_Ciclo2'!$F:$F,"Total") -> 0 | K64: =IFERROR(I64/H64,0) -> 0
B65: =B64+1 -> 62 | C65: Mori II | D65: MORI GERACAO II | E65: =C65 -> Mori II | F65: 0 | G65: Mori | H65: =SUMIFS('Controle Projetos_Ciclo2'!$O:$O,'Controle Projetos_Ciclo2'!$B:$B,$C65,'Controle Projetos_Ciclo2'!$F:$F,"Total") -> 0 | I65: =SUMIFS('Controle Projetos_Ciclo2'!$R:$R,'Controle Projetos_Ciclo2'!$B:$B,$C65,'Controle Projetos_Ciclo2'!$F:$F,"Total") -> 0 | J65: =SUMIFS('Controle Projetos_Ciclo2'!S:S,'Controle Projetos_Ciclo2'!$B:$B,$C65,'Controle Projetos_Ciclo2'!$F:$F,"Total") -> 0 | K65: =IFERROR(I65/H65,0) -> 0
B66: =B65+1 -> 63 | C66: NewCo IV | D66: MORI MINAS IV | E66: =C66 -> NewCo IV | F66: 0 | G66: Solatio | H66: =SUMIFS('Controle Projetos_Ciclo2'!$O:$O,'Controle Projetos_Ciclo2'!$B:$B,$C66,'Controle Projetos_Ciclo2'!$F:$F,"Total") -> 0 | I66: =SUMIFS('Controle Projetos_Ciclo2'!$R:$R,'Controle Projetos_Ciclo2'!$B:$B,$C66,'Controle Projetos_Ciclo2'!$F:$F,"Total") -> 0 | J66: =SUMIFS('Controle Projetos_Ciclo2'!S:S,'Controle Projetos_Ciclo2'!$B:$B,$C66,'Controle Projetos_Ciclo2'!$F:$F,"Total") -> 0 | K66: =IFERROR(I66/H66,0) -> 0
B67: =B66+1 -> 64 | C67: NewCo V | D67: MORI MINAS V | E67: =C67 -> NewCo V | F67: 0 | G67: Solatio | H67: =SUMIFS('Controle Projetos_Ciclo2'!$O:$O,'Controle Projetos_Ciclo2'!$B:$B,$C67,'Controle Projetos_Ciclo2'!$F:$F,"Total") -> 0 | I67: =SUMIFS('Controle Projetos_Ciclo2'!$R:$R,'Controle Projetos_Ciclo2'!$B:$B,$C67,'Controle Projetos_Ciclo2'!$F:$F,"Total") -> 0 | J67: =SUMIFS('Controle Projetos_Ciclo2'!S:S,'Controle Projetos_Ciclo2'!$B:$B,$C67,'Controle Projetos_Ciclo2'!$F:$F,"Total") -> 0 | K67: =IFERROR(I67/H67,0) -> 0
B68: =B67+1 -> 65 | C68: EDN | D68: ESTRELA DO NORTE | E68: =C68 -> EDN | F68: 0 | G68: Apolo | H68: =SUMIFS('Controle Projetos_Ciclo2'!$O:$O,'Controle Projetos_Ciclo2'!$B:$B,$C68,'Controle Projetos_Ciclo2'!$F:$F,"Total") -> 0 | I68: =SUMIFS('Controle Projetos_Ciclo2'!$R:$R,'Controle Projetos_Ciclo2'!$B:$B,$C68,'Controle Projetos_Ciclo2'!$F:$F,"Total") -> 0 | J68: =SUMIFS('Controle Projetos_Ciclo2'!S:S,'Controle Projetos_Ciclo2'!$B:$B,$C68,'Controle Projetos_Ciclo2'!$F:$F,"Total") -> 0 | K68: =IFERROR(I68/H68,0) -> 0
B69: 0 | C69: 0 | D69: 0 | E69: Mori II | F69: 0 | G69: 0 | H69: =SUMIFS(H$4:H$68,$E$4:$E$68,$E69) -> 2348118.8 | I69: =SUMIFS(I$4:I$68,$E$4:$E$68,$E69) -> 2290918.8 | J69: =SUMIFS(J$4:J$68,$E$4:$E$68,$E69) -> 57200 | K69: =IFERROR(I69/H69,0) -> 0.97564007
B70: 0 | C70: 0 | D70: 0 | E70: NewCo IV | F70: 0 | G70: 0 | H70: =SUMIFS(H$4:H$68,$E$4:$E$68,$E70) -> 7598138.7 | I70: =SUMIFS(I$4:I$68,$E$4:$E$68,$E70) -> 7225108.8 | J70: =SUMIFS(J$4:J$68,$E$4:$E$68,$E70) -> 373029.89 | K70: =IFERROR(I70/H70,0) -> 0.9509051
B71: 0 | C71: 0 | D71: 0 | E71: NewCo V | F71: 0 | G71: 0 | H71: =SUMIFS(H$4:H$68,$E$4:$E$68,$E71) -> 2771538.7 | I71: =SUMIFS(I$4:I$68,$E$4:$E$68,$E71) -> 2686059.9 | J71: =SUMIFS(J$4:J$68,$E$4:$E$68,$E71) -> 85478.84 | K71: =IFERROR(I71/H71,0) -> 0.96915835
B72: 0 | C72: 0 | D72: 0 | E72: EDN | F72: 0 | G72: 0 | H72: =SUMIFS(H$4:H$68,$E$4:$E$68,$E72) -> 0 | I72: =SUMIFS(I$4:I$68,$E$4:$E$68,$E72) -> 0 | J72: =SUMIFS(J$4:J$68,$E$4:$E$68,$E72) -> 0 | K72: =IFERROR(I72/H72,0) -> 0
E73: Ciclo 2 | H73: =SUM(H69:H72) -> 12717796 | I73: =SUM(I69:I72) -> 12202087 | J73: =SUM(J69:J72) -> 515708.73 | K73: =IFERROR(I73/H73,0) -> 0.95944984
G75: Ckek | H75: 8.2457299e+08 | I75: 7.594754e+08 | J75: 65097583 | K75: 0.92105298

Sheet Controle Projetos_Ciclo3
A1: N° | B1: UFV | C1: CNPJ | D1: Unidade | E1: Frente | F1: Natureza | G1: Portfólio | H1: Fornecedor | I1: Contrato original | J1: Aditivo 1 | K1: Aditivo 2 | L1: Aditivo 3 | M1: Aditivo 4 | N1: Aditivo 5 | O1: Valor total | P1: FD.Medido | Q1: Medição | R1: FD+Medição | S1: Saldo a Medir | T1: Avanço Contratual% | U1: Avanço OBRA% | V1: OBS:
A2: 1 | B2: Diamantina 1 | C2: MORI GERACAO II | D2: Mori II | E2: 3 | F2: Conexão AT - Obras | G2: Mori | H2: MBA | I2: 308990.19 | J2: 0 | K2: 0 | L2: 0 | M2: 0 | N2: 0 | O2: 308990.19
A3: 1 | B3: Diamantina 1 | C3: MORI GERACAO II | D3: Mori II | E3: 3 | F3: Conexão MT - Obras | G3: Mori | H3: MBA | I3: 735500 | J3: 0 | K3: 0 | L3: 0 | M3: 0 | N3: 0 | O3: 735500
A4: 1 | B4: Diamantina 1 | C4: MORI GERACAO II | D4: Mori II | E4: 3 | F4: Construção - Serviços de Construção | G4: Mori | H4: Implantar | I4: 2556450 | J4: 157000 | K4: 91704.15 | L4: 251404.62 | M4: 44129.95 | N4: 0 | O4: 3100688.7
A5: 1 | B5: Diamantina 1 | C5: MORI GERACAO II | D5: Mori II | E5: 3 | F5: Construção - Serviços de Construção - Substituição | G5: Mori | H5: 0 | I5: 0 | J5: 0 | K5: 0 | L5: 0 | M5: 0 | N5: 0 | O5: 0
A6: 1 | B6: Diamantina 1 | C6: MORI GERACAO II | D6: Mori II | E6: 3 | F6: Construção - RDA Interno | G6: Mori | H6: Eletrocamp | I6: 402477.3 | J6: 6400 | K6: 7304.5454 | L6: 0 | M6: 0 | N6: 0 | O6: 416182.01
A7: 1 | B7: Diamantina 1 | C7: MORI GERACAO II | D7: Mori II | E7: 3 | F7: Full EPC - Contrato | G7: Mori | H7: 0 | I7: 0 | J7: 0 | K7: 0 | L7: 0 | M7: 0 | N7: 0 | O7: 0
A8: 1 | B8: Diamantina 1 | C8: MORI GERACAO II | D8: Mori II | E8: 3 | F8: Equipamentos Curva A - Outros (Transformadores) | G8: Mori | H8: 0 | I8: 0 | J8: 0 | K8: 0 | L8: 0 | M8: 0 | N8: 0 | O8: 0
A9: 1 | B9: Diamantina 1 | C9: MORI GERACAO II | D9: Mori II | E9: 3 | F9: Equipamentos Curva A - Outros (Cabine + Skid) | G9: Mori | H9: 0 | I9: 0 | J9: 0 | K9: 0 | L9: 0 | M9: 0 | N9: 0 | O9: 0
A10: 1 | B10: Diamantina 1 | C10: MORI GERACAO II | D10: Mori II | E10: 3 | F10: Equipamentos Curva A - Outros (Cabine + Skid + Transformador) | G10: Mori | H10: Romagnole | I10: 1200784.7 | J10: 0 | K10: 0 | L10: 0 | M10: 0 | N10: 0 | O10: 1200784.7
A11: 1 | B11: Diamantina 1 | C11: MORI GERACAO II | D11: Mori II | E11: 3 | F11: Desenvolvimento de projeto - Projetos - (Eng° Proprietario) | G11: Mori | H11: LM Eng. | I11: 0 | J11: 0 | K11: 0 | L11: 0 | M11: 0 | N11: 0 | O11: 0
A12: 1 | B12: Diamantina 1 | C12: MORI GERACAO II | D12: Mori II | E12: 3 | F12: Desenvolvimento de projeto - Projetos - Executivos | G12: Mori | H12: Enersolar | I12: 36466.7 | J12: 0 | K12: 0 | L12: 0 | M12: 0 | N12: 0 | O12: 36466.7
A13: 1 | B13: Diamantina 1 | C13: MORI GERACAO II | D13: Mori II | E13: 3 | F13: Desenvolvimento de projeto - Projetos Básica | G13: Mori | H13: 0 | I13: 0 | J13: 0 | K13: 0 | L13: 0 | M13: 0 | N13: 0 | O13: 0
A14: 1 | B14: Diamantina 1 | C14: MORI GERACAO II | D14: Mori II | E14: 3 | F14: Desenvolvimento de projeto - Projetos Detalhada | G14: Mori | H14: GLD | I14: 93783 | J14: 42026.46 | K14: 0 | L14: 0 | M14: 0 | N14: 0 | O14: 135809.46
A15: 1 | B15: Diamantina 1 | C15: MORI GERACAO II | D15: Mori II | E15: 3 | F15: Desenvolvimento de projeto - Ambiental / Outros | G15: Mori | H15: Varios | I15: 155757.91 | J15: 0 | K15: 0 | L15: 0 | M15: 0 | N15: 0 | O15: 155757.91
A16: 1 | B16: Diamantina 1 | C16: MORI GERACAO II | D16: Mori II | E16: 3 | F16: Desenvolvimento de projeto - Coordenograma | G16: Mori | H16: PROJETTI | I16: 6207 | J16: 0 | K16: 0 | L16: 0 | M16: 0 | N16: 0 | O16: 6207
A17: 1 | B17: Diamantina 1 | C17: MORI GERACAO II | D17: Mori II | E17: 3 | F17: Sistemas de Monitoramento - Supervisório | G17: Mori | H17: ATI | I17: 136693.98 | K17: 0 | L17: 0 | M17: 0 | N17: 0 | O17: 136693.98
A18: 1 | B18: Diamantina 1 | C18: MORI GERACAO II | D18: Mori II | E18: 3 | F18: Sistemas de Monitoramento - Estações Solarimétricas | G18: Mori | H18: Hukseflux | I18: 48276.516 | J18: 0 | K18: 0 | L18: 0 | M18: 0 | N18: 0 | O18: 48276.516
A19: 1 | B19: Diamantina 1 | C19: MORI GERACAO II | D19: Mori II | E19: 3 | F19: Sistemas de Monitoramento - CFTV | G19: Mori | H19: Maxvision | I19: 248414.57 | J19: 0 | K19: 0 | L19: 0 | M19: 0 | N19: 0 | O19: 248414.57
A20: 1 | B20: Diamantina 1 | C20: MORI GERACAO II | D20: Mori II | E20: 3 | F20: Serviços Auxiliares - Drenagem | G20: Mori | H20: CONSPLAN / ORCI | I20: 839026.26 | J20: 293286.3 | K20: 188709 | L20: 0 | M20: 0 | N20: 0 | O20: 1321021.6
A21: 1 | B21: Diamantina 1 | C21: MORI GERACAO II | D21: Mori II | E21: 3 | F21: Serviços Auxiliares - Terraplanagem | G21: Mori | H21: MRO | I21: 1108130.6 | J21: 0 | K21: 0 | L21: 0 | M21: 0 | N21: 0 | O21: 1108130.6
A22: 1 | B22: Diamantina 1 | C22: MORI GERACAO II | D22: Mori II | E22: 3 | F22: Serviços Auxiliares - Supressão Vegetal | G22: Mori | H22: Rima | I22: 50000 | J22: 3500 | K22: 30000 | L22: 0 | M22: 0 | N22: 0 | O22: 83500
A23: 1 | B23: Diamantina 1 | C23: MORI GERACAO II | D23: Mori II | E23: 3 | F23: RDR-Rede de Distribuição Rural | G23: Mori | H23: 0 | I23: 0 | J23: 0 | K23: 0 | L23: 0 | M23: 0 | N23: 0 | O23: 0
A24: 1 | B24: Diamantina 1 | C24: MORI GERACAO II | D24: Mori II | E24: 3 | F24: Escopo COMERC | G24: Mori | H24: 0 | I24: 352962.83 | J24: 538750 | K24: 0 | L24: 0 | M24: 0 | N24: 0 | O24: 891712.83
A25: 1 | B25: Diamantina 1 | C25: MORI GERACAO II | D25: Mori II | E25: 3 | F25: Escopo COMERC - Segurança | G25: Mori | H25: 0 | I25: 94500 | J25: 0 | K25: 0 | L25: 0 | M25: 0 | N25: 0 | O25: 94500
A26: 1 | B26: Diamantina 1 | C26: MORI GERACAO II | D26: Mori II | E26: 3 | F26: Conexão MT - Obras Transferencia | G26: Mori | H26: ENGELUZ | I26: 3677500 | J26: 0 | K26: 0 | L26: 0 | M26: 0 | N26: 0 | O26: 3677500
A27: 1 | B27: Diamantina 1 | C27: MORI GERACAO II | D27: Mori II | E27: 3 | F27: Bases de Contaniers | G27: Mori | H27: 0 | I27: 0 | J27: 0 | K27: 0 | L27: 0 | M27: 0 | N27: 0 | O27: 0
A28: 1 | B28: Diamantina 1 | C28: MORI GERACAO II | D28: Mori II | E28: 3 | F28: Construção - Serviços de Construção - Ase Engenharia | G28: Mori | H28: 0 | I28: 0 | J28: 0 | K28: 0 | L28: 0 | M28: 0 | N28: 0 | O28: 0
A29: 1 | B29: Diamantina 1 | C29: MORI GERACAO II | D29: Mori II | E29: 3 | F29: Full EPC - Contrato Sobressalentes | G29: Mori | H29: 0 | I29: 0 | J29: 0 | K29: 0 | L29: 0 | M29: 0 | N29: 0 | O29: 0
A30: 1 | B30: Diamantina 1 | C30: MORI GERACAO II | D30: Mori II | E30: 3 | F30: Construção - Serviços de Construção - NOVA MORADA | G30: Mori | H30: 0 | I30: 0 | J30: 0 | K30: 0 | L30: 0 | M30: 0 | N30: 0 | O30: 0
A31: 1 | B31: Diamantina 1 | C31: MORI GERACAO II | D31: Mori II | E31: 3 | F31: Add. | G31: Mori | H31: 0 | I31: 0 | J31: 0 | K31: 0 | L31: 0 | M31: 0 | N31: 0 | O31: 0
A32: 1 | B32: Diamantina 1 | C32: MORI GERACAO II | D32: Mori II | E32: 3 | F32: Add. | G32: Mori | H32: 0 | I32: 0 | J32: 0 | K32: 0 | L32: 0 | M32: 0 | N32: 0 | O32: 0
A33: 1 | B33: Diamantina 1 | C33: MORI GERACAO II | D33: Mori II | E33: 3 | F33: Add. | G33: Mori | H33: 0 | I33: 0 | J33: 0 | K33: 0 | L33: 0 | M33: 0 | N33: 0 | O33: 0
A34: 1 | B34: Diamantina 1 | C34: MORI GERACAO II | D34: Mori II | E34: 3 | F34: Total | G34: Mori | I34: 3677500 | J34: 0 | K34: 0 | L34: 0 | M34: 0 | N34: 0 | O34: 3677500

Sheet GLD
D3: GLD
D4: MORI GERACAO II | E4: 111378.32 | F4: =E4 -> 111378.32
D5: EDN | E5: 4828
D6: EDN | E6: 4346.36
D7: EDN | E7: 40104.26
D8: EDN | E8: 122496.81 | F8: =SUM(E5:E8) -> 171775.43
D9: NewCo IV | E9: 50084.37
D10: NewCo IV | E10: 5373.56
D11: NewCo IV | E11: 9928.56
D12: NewCo IV | E12: 88298.31
D13: NewCo IV | E13: 5893.74
D14: NewCo IV | E14: 78094.07
D15: NewCo IV | E15: 0.0099999998
D16: NewCo IV | E16: 10.01
D17: NewCo IV | E17: 688958.09
D18: NewCo IV | E18: 578091.13 | F18: =SUM(E9:E18) -> 1504731.9
D19: NewCo V | E19: 10769.86
D20: NewCo V | E20: 7230.04
D21: NewCo V | E21: 424454.62
D22: NewCo V | E22: 0 | F22: =SUM(E19:E22) -> 442454.52
E24: Total: | F24: =SUM(F4:F22) -> 2230340.1

Sheet Controle Projetos_Ciclo2
A1: /;., 3 | B1: UFV | C1: CNPJ | D1: Unidade | E1: Frente | F1: Natureza | G1: Portfólio | H1: Fornecedor | I1: Contrato original | J1: Aditivo 1 | K1: Aditivo 2 | L1: Aditivo 3 | M1: Aditivo 4 | N1: Aditivo 5 | O1: Valor total | P1: FD.Medido | Q1: Medição | R1: FD+Medição | S1: Saldo a Medir | T1: Avanço Contratual% | U1: Pagamento? Sim / Não | V1: OBS:
A2: 1 | B2: =VLOOKUP($A2,Controle!$B$4:$F$68,2,FALSE) -> Diamantina 1 | C2: =VLOOKUP($A2,Controle!$B$4:$F$68,3,FALSE) -> MORI GERACAO II | D2: =VLOOKUP($A2,Controle!$B$4:$F$68,4,FALSE) -> Mori II | E2: =VLOOKUP($A2,Controle!$B$4:$F$68,5,FALSE) -> 3 | F2: Conexão AT - Obras | G2: =VLOOKUP($A2,Controle!$B$4:$G$68,6,FALSE) -> Mori | H2: MBA | I2: 308990.19 | J2: 0 | K2: 0 | L2: 0 | M2: 0 | N2: 0 | O2: =SUM(I2:N2) -> 308990.19 | P2: =SUMIFS('Desenvolvimento diário'!$H:$H,'Desenvolvimento diário'!$Q:$Q,$B2,'Desenvolvimento diário'!$P:$P,$F2,'Desenvolvimento diário'!$R:$R,"Sim") -> 99490.19 | Q2: =SUMIFS('Desenvolvimento diário'!$H:$H,'Desenvolvimento diário'!$Q:$Q,$B2,'Desenvolvimento diário'!$P:$P,$F2,'Desenvolvimento diário'!$R:$R,"Não") -> 209500 | R2: =SUM(P2:Q2) -> 308990.19 | S2: =O2-R2 -> 0 | T2: =IFERROR(R2/O2,0) -> 1
A3: =A2 -> 1 | B3: =VLOOKUP($A3,Controle!$B$4:$F$68,2,FALSE) -> Diamantina 1 | C3: =VLOOKUP($A3,Controle!$B$4:$F$68,3,FALSE) -> MORI GERACAO II | D3: =VLOOKUP($A3,Controle!$B$4:$F$68,4,FALSE) -> Mori II | E3: =VLOOKUP($A3,Controle!$B$4:$F$68,5,FALSE) -> 3 | F3: Conexão MT - Obras | G3: =VLOOKUP($A3,Controle!$B$4:$G$68,6,FALSE) -> Mori | H3: MBA | I3: 735500 | J3: =(-78468+0.23) -> -78467.77 | K3: 0 | L3: 0 | M3: 0 | N3: 0 | O3: =SUM(I3:N3) -> 657032.23 | P3: =SUMIFS('Desenvolvimento diário'!$H:$H,'Desenvolvimento diário'!$Q:$Q,$B3,'Desenvolvimento diário'!$P:$P,$F3,'Desenvolvimento diário'!$R:$R,"Sim") -> 197032.23 | Q3: =SUMIFS('Desenvolvimento diário'!$H:$H,'Desenvolvimento diário'!$Q:$Q,$B3,'Desenvolvimento diário'!$P:$P,$F3,'Desenvolvimento diário'!$R:$R,"Não") -> 460000 | R3: =SUM(P3:Q3) -> 657032.23 | S3: =O3-R3 -> 0 | T3: =IFERROR(R3/O3,0) -> 1
A4: =A3 -> 1 | B4: =VLOOKUP($A4,Controle!$B$4:$F$68,2,FALSE) -> Diamantina 1 | C4: =VLOOKUP($A4,Controle!$B$4:$F$68,3,FALSE) -> MORI GERACAO II | D4: =VLOOKUP($A4,Controle!$B$4:$F$68,4,FALSE) -> Mori II | E4: =VLOOKUP($A4,Controle!$B$4:$F$68,5,FALSE) -> 3 | F4: Construção - Serviços de Construção | G4: =VLOOKUP($A4,Controle!$B$4:$G$68,6,FALSE) -> Mori | H4: Implantar | I4: 2556450 | J4: 157000 | K4: 91704.15 | L4: 251404.62 | M4: 44129.95 | N4: 0 | O4: =SUM(I4:N4) -> 3100688.7 | P4: =SUMIFS('Desenvolvimento diário'!$H:$H,'Desenvolvimento diário'!$Q:$Q,$B4,'Desenvolvimento diário'!$P:$P,$F4,'Desenvolvimento diário'!$R:$R,"Sim") -> 1313672.7 | Q4: =SUMIFS('Desenvolvimento diário'!$H:$H,'Desenvolvimento diário'!$Q:$Q,$B4,'Desenvolvimento diário'!$P:$P,$F4,'Desenvolvimento diário'!$R:$R,"Não") -> 1778347.1 | R4: =SUM(P4:Q4) -> 3092019.8 | S4: =O4-R4 -> 8668.9 | T4: =IFERROR(R4/O4,0) -> 0.9972042 | U4: N | V4: Em Processo Judicial
A5: =A4 -> 1 | B5: =VLOOKUP($A5,Controle!$B$4:$F$68,2,FALSE) -> Diamantina 1 | C5: =VLOOKUP($A5,Controle!$B$4:$F$68,3,FALSE) -> MORI GERACAO II | D5: =VLOOKUP($A5,Controle!$B$4:$F$68,4,FALSE) -> Mori II | E5: =VLOOKUP($A5,Controle!$B$4:$F$68,5,FALSE) -> 3 | F5: Construção - Serviços de Construção - Substituição | G5: =VLOOKUP($A5,Controle!$B$4:$G$68,6,FALSE) -> Mori | H5: 0 | I5: 0 | J5: 0 | K5: 0 | L5: 0 | M5: 0 | N5: 0 | O5: =SUM(I5:N5) -> 0 | P5: =SUMIFS('Desenvolvimento diário'!$H:$H,'Desenvolvimento diário'!$Q:$Q,$B5,'Desenvolvimento diário'!$P:$P,$F5,'Desenvolvimento diário'!$R:$R,"Sim") -> 0 | Q5: =SUMIFS('Desenvolvimento diário'!$H:$H,'Desenvolvimento diário'!$Q:$Q,$B5,'Desenvolvimento diário'!$P:$P,$F5,'Desenvolvimento diário'!$R:$R,"Não") -> 0 | R5: =SUM(P5:Q5) -> 0 | S5: =O5-R5 -> 0 | T5: =IFERROR(R5/O5,0) -> 0
A6: =A5 -> 1 | B6: =VLOOKUP($A6,Controle!$B$4:$F$68,2,FALSE) -> Diamantina 1 | C6: =VLOOKUP($A6,Controle!$B$4:$F$68,3,FALSE) -> MORI GERACAO II | D6: =VLOOKUP($A6,Controle!$B$4:$F$68,4,FALSE) -> Mori II | E6: =VLOOKUP($A6,Controle!$B$4:$F$68,5,FALSE) -> 3 | F6: Construção - RDA Interno | G6: =VLOOKUP($A6,Controle!$B$4:$G$68,6,FALSE) -> Mori | H6: Eletrocamp | I6: 402477.3 | J6: 6400 | K6: 7304.5454 | L6: 0 | M6: 0 | N6: 0 | O6: =SUM(I6:N6)+0.1646 -> 416182.01 | P6: =SUMIFS('Desenvolvimento diário'!$H:$H,'Desenvolvimento diário'!$Q:$Q,$B6,'Desenvolvimento diário'!$P:$P,$F6,'Desenvolvimento diário'!$R:$R,"Sim") -> 0 | Q6: =SUMIFS('Desenvolvimento diário'!$H:$H,'Desenvolvimento diário'!$Q:$Q,$B6,'Desenvolvimento diário'!$P:$P,$F6,'Desenvolvimento diário'!$R:$R,"Não") -> 416182.01 | R6: =SUM(P6:Q6) -> 416182.01 | S6: =O6-R6 -> 0 | T6: =IFERROR(R6/O6,0) -> 1
A7: =A6 -> 1 | B7: =VLOOKUP($A7,Controle!$B$4:$F$68,2,FALSE) -> Diamantina 1 | C7: =VLOOKUP($A7,Controle!$B$4:$F$68,3,FALSE) -> MORI GERACAO II | D7: =VLOOKUP($A7,Controle!$B$4:$F$68,4,FALSE) -> Mori II | E7: =VLOOKUP($A7,Controle!$B$4:$F$68,5,FALSE) -> 3 | F7: Full EPC - Contrato | G7: =VLOOKUP($A7,Controle!$B$4:$G$68,6,FALSE) -> Mori | H7: 0 | I7: 0 | J7: 0 | K7: 0 | L7: 0 | M7: 0 | N7: 0 | O7: =SUM(I7:N7) -> 0 | P7: =SUMIFS('Desenvolvimento diário'!$H:$H,'Desenvolvimento diário'!$Q:$Q,$B7,'Desenvolvimento diário'!$P:$P,$F7,'Desenvolvimento diário'!$R:$R,"Sim") -> 0 | Q7: =SUMIFS('Desenvolvimento diário'!$H:$H,'Desenvolvimento diário'!$Q:$Q,$B7,'Desenvolvimento diário'!$P:$P,$F7,'Desenvolvimento diário'!$R:$R,"Não") -> 0 | R7: =SUM(P7:Q7) -> 0 | S7: =O7-R7 -> 0 | T7: =IFERROR(R7/O7,0) -> 0
A8: =A7 -> 1 | B8: =VLOOKUP($A8,Controle!$B$4:$F$68,2,FALSE) -> Diamantina 1 | C8: =VLOOKUP($A8,Controle!$B$4:$F$68,3,FALSE) -> MORI GERACAO II | D8: =VLOOKUP($A8,Controle!$B$4:$F$68,4,FALSE) -> Mori II | E8: =VLOOKUP($A8,Controle!$B$4:$F$68,5,FALSE) -> 3 | F8: Equipamentos Curva A - Outros (Transformadores) | G8: =VLOOKUP($A8,Controle!$B$4:$G$68,6,FALSE) -> Mori | H8: 0 | I8: 0 | J8: 0 | K8: 0 | L8: 0 | M8: 0 | N8: 0 | O8: =SUM(I8:N8) -> 0 | P8: =SUMIFS('Desenvolvimento diário'!$H:$H,'Desenvolvimento diário'!$Q:$Q,$B8,'Desenvolvimento diário'!$P:$P,$F8,'Desenvolvimento diário'!$R:$R,"Sim") -> 0 | Q8: =SUMIFS('Desenvolvimento diário'!$H:$H,'Desenvolvimento diário'!$Q:$Q,$B8,'Desenvolvimento diário'!$P:$P,$F8,'Desenvolvimento diário'!$R:$R,"Não") -> 0 | R8: =SUM(P8:Q8) -> 0 | S8: =O8-R8 -> 0 | T8: =IFERROR(R8/O8,0) -> 0
A9: =A8 -> 1 | B9: =VLOOKUP($A9,Controle!$B$4:$F$68,2,FALSE) -> Diamantina 1 | C9: =VLOOKUP($A9,Controle!$B$4:$F$68,3,FALSE) -> MORI GERACAO II | D9: =VLOOKUP($A9,Controle!$B$4:$F$68,4,FALSE) -> Mori II | E9: =VLOOKUP($A9,Controle!$B$4:$F$68,5,FALSE) -> 3 | F9: Equipamentos Curva A - Outros (Cabine + Skid) | G9: =VLOOKUP($A9,Controle!$B$4:$G$68,6,FALSE) -> Mori | H9: 0 | I9: 0 | J9: 0 | K9: 0 | L9: 0 | M9: 0 | N9: 0 | O9: =SUM(I9:N9) -> 0 | P9: =SUMIFS('Desenvolvimento diário'!$H:$H,'Desenvolvimento diário'!$Q:$Q,$B9,'Desenvolvimento diário'!$P:$P,$F9,'Desenvolvimento diário'!$R:$R,"Sim") -> 0 | Q9: =SUMIFS('Desenvolvimento diário'!$H:$H,'Desenvolvimento diário'!$Q:$Q,$B9,'Desenvolvimento diário'!$P:$P,$F9,'Desenvolvimento diário'!$R:$R,"Não") -> 0 | R9: =SUM(P9:Q9) -> 0 | S9: =O9-R9 -> 0 | T9: =IFERROR(R9/O9,0) -> 0
A10: =A9 -> 1 | B10: =VLOOKUP($A10,Controle!$B$4:$F$68,2,FALSE) -> Diamantina 1 | C10: =VLOOKUP($A10,Controle!$B$4:$F$68,3,FALSE) -> MORI GERACAO II | D10: =VLOOKUP($A10,Controle!$B$4:$F$68,4,FALSE) -> Mori II | E10: =VLOOKUP($A10,Controle!$B$4:$F$68,5,FALSE) -> 3 | F10: Equipamentos Curva A - Outros (Cabine + Skid + Transformador) | G10: =VLOOKUP($A10,Controle!$B$4:$G$68,6,FALSE) -> Mori | H10: Romagnole | I10: 1200784.7 | J10: 0 | K10: 0 | L10: 0 | M10: 0 | N10: 0 | O10: =SUM(I10:N10) -> 1200784.7 | P10: =SUMIFS('Desenvolvimento diário'!$H:$H,'Desenvolvimento diário'!$Q:$Q,$B10,'Desenvolvimento diário'!$P:$P,$F10,'Desenvolvimento diário'!$R:$R,"Sim") -> 0 | Q10: =SUMIFS('Desenvolvimento diário'!$H:$H,'Desenvolvimento diário'!$Q:$Q,$B10,'Desenvolvimento diário'!$P:$P,$F10,'Desenvolvimento diário'!$R:$R,"Não") -> 1200784.7 | R10: =SUM(P10:Q10) -> 1200784.7 | S10: =O10-R10 -> 0 | T10: =IFERROR(R10/O10,0) -> 1
A11: =A10 -> 1 | B11: =VLOOKUP($A11,Controle!$B$4:$F$68,2,FALSE) -> Diamantina 1 | C11: =VLOOKUP($A11,Controle!$B$4:$F$68,3,FALSE) -> MORI GERACAO II | D11: =VLOOKUP($A11,Controle!$B$4:$F$68,4,FALSE) -> Mori II | E11: =VLOOKUP($A11,Controle!$B$4:$F$68,5,FALSE) -> 3 | F11: Desenvolvimento de projeto - Projetos - (Eng° Proprietario) | G11: =VLOOKUP($A11,Controle!$B$4:$G$68,6,FALSE) -> Mori | H11: LM Eng. | I11: 0 | J11: 0 | K11: 0 | L11: 0 | M11: 0 | N11: 0 | O11: =SUM(I11:N11) -> 0 | P11: =SUMIFS('Desenvolvimento diário'!$H:$H,'Desenvolvimento diário'!$Q:$Q,$B11,'Desenvolvimento diário'!$P:$P,$F11,'Desenvolvimento diário'!$R:$R,"Sim") -> 0 | Q11: =SUMIFS('Desenvolvimento diário'!$H:$H,'Desenvolvimento diário'!$Q:$Q,$B11,'Desenvolvimento diário'!$P:$P,$F11,'Desenvolvimento diário'!$R:$R,"Não") -> 0 | R11: =SUM(P11:Q11) -> 0 | S11: =O11-R11 -> 0 | T11: =IFERROR(R11/O11,0) -> 0
A12: =A11 -> 1 | B12: =VLOOKUP($A12,Controle!$B$4:$F$68,2,FALSE) -> Diamantina 1 | C12: =VLOOKUP($A12,Controle!$B$4:$F$68,3,FALSE) -> MORI GERACAO II | D12: =VLOOKUP($A12,Controle!$B$4:$F$68,4,FALSE) -> Mori II | E12: =VLOOKUP($A12,Controle!$B$4:$F$68,5,FALSE) -> 3 | F12: Desenvolvimento de projeto - Projetos - Executivos | G12: =VLOOKUP($A12,Controle!$B$4:$G$68,6,FALSE) -> Mori | H12: Enersolar | I12: Feito com a GLD | J12: 0 | K12: 0 | L12: 0 | M12: 0 | N12: 0 | O12: =SUM(I12:N12) -> 0 | P12: =SUMIFS('Desenvolvimento diário'!$H:$H,'Desenvolvimento diário'!$Q:$Q,$B12,'Desenvolvimento diário'!$P:$P,$F12,'Desenvolvimento diário'!$R:$R,"Sim") -> 0 | Q12: =SUMIFS('Desenvolvimento diário'!$H:$H,'Desenvolvimento diário'!$Q:$Q,$B12,'Desenvolvimento diário'!$P:$P,$F12,'Desenvolvimento diário'!$R:$R,"Não") -> 0 | R12: =SUM(P12:Q12) -> 0 | S12: =O12-R12 -> 0 | T12: =IFERROR(R12/O12,0) -> 0
A13: =A12 -> 1 | B13: =VLOOKUP($A13,Controle!$B$4:$F$68,2,FALSE) -> Diamantina 1 | C13: =VLOOKUP($A13,Controle!$B$4:$F$68,3,FALSE) -> MORI GERACAO II | D13: =VLOOKUP($A13,Controle!$B$4:$F$68,4,FALSE) -> Mori II | E13: =VLOOKUP($A13,Controle!$B$4:$F$68,5,FALSE) -> 3 | F13: Desenvolvimento de projeto - Projetos Básica | G13: =VLOOKUP($A13,Controle!$B$4:$G$68,6,FALSE) -> Mori | H13: 0 | I13: 0 | J13: 0 | K13: 0 | L13: 0 | M13: 0 | N13: 0 | O13: =SUM(I13:N13) -> 0 | P13: =SUMIFS('Desenvolvimento diário'!$H:$H,'Desenvolvimento diário'!$Q:$Q,$B13,'Desenvolvimento diário'!$P:$P,$F13,'Desenvolvimento diário'!$R:$R,"Sim") -> 0 | Q13: =SUMIFS('Desenvolvimento diário'!$H:$H,'Desenvolvimento diário'!$Q:$Q,$B13,'Desenvolvimento diário'!$P:$P,$F13,'Desenvolvimento diário'!$R:$R,"Não") -> 0 | R13: =SUM(P13:Q13) -> 0 | S13: =O13-R13 -> 0 | T13: =IFERROR(R13/O13,0) -> 0
A14: =A13 -> 1 | B14: =VLOOKUP($A14,Controle!$B$4:$F$68,2,FALSE) -> Diamantina 1 | C14: =VLOOKUP($A14,Controle!$B$4:$F$68,3,FALSE) -> MORI GERACAO II | D14: =VLOOKUP($A14,Controle!$B$4:$F$68,4,FALSE) -> Mori II | E14: =VLOOKUP($A14,Controle!$B$4:$F$68,5,FALSE) -> 3 | F14: Desenvolvimento de projeto - Projetos Detalhada | G14: =VLOOKUP($A14,Controle!$B$4:$G$68,6,FALSE) -> Mori | H14: GLD | I14: 93783 | J14: 42026.46 | K14: 0 | L14: 0 | M14: 0 | N14: 0 | O14: =SUM(I14:N14) -> 135809.46 | P14: =SUMIFS('Desenvolvimento diário'!$H:$H,'Desenvolvimento diário'!$Q:$Q,$B14,'Desenvolvimento diário'!$P:$P,$F14,'Desenvolvimento diário'!$R:$R,"Sim") -> 0 | Q14: =SUMIFS('Desenvolvimento diário'!$H:$H,'Desenvolvimento diário'!$Q:$Q,$B14,'Desenvolvimento diário'!$P:$P,$F14,'Desenvolvimento diário'!$R:$R,"Não") -> 135809.46 | R14: =SUM(P14:Q14) -> 135809.46 | S14: =O14-R14 -> 0 | T14: =IFERROR(R14/O14,0) -> 1
A15: =A14 -> 1 | B15: =VLOOKUP($A15,Controle!$B$4:$F$68,2,FALSE) -> Diamantina 1 | C15: =VLOOKUP($A15,Controle!$B$4:$F$68,3,FALSE) -> MORI GERACAO II | D15: =VLOOKUP($A15,Controle!$B$4:$F$68,4,FALSE) -> Mori II | E15: =VLOOKUP($A15,Controle!$B$4:$F$68,5,FALSE) -> 3 | F15: Desenvolvimento de projeto - Ambiental / Outros | G15: =VLOOKUP($A15,Controle!$B$4:$G$68,6,FALSE) -> Mori | H15: Varios | I15: =R15 -> 177481.41 | J15: 0 | K15: 0 | L15: 0 | M15: 0 | N15: 0 | O15: =SUM(I15:N15) -> 177481.41 | P15: =SUMIFS('Desenvolvimento diário'!$H:$H,'Desenvolvimento diário'!$Q:$Q,$B15,'Desenvolvimento diário'!$P:$P,$F15,'Desenvolvimento diário'!$R:$R,"Sim") -> 0 | Q15: =SUMIFS('Desenvolvimento diário'!$H:$H,'Desenvolvimento diário'!$Q:$Q,$B15,'Desenvolvimento diário'!$P:$P,$F15,'Desenvolvimento diário'!$R:$R,"Não") -> 177481.41 | R15: =SUM(P15:Q15) -> 177481.41 | S15: =O15-R15 -> 0 | T15: =IFERROR(R15/O15,0) -> 1
A16: =A15 -> 1 | B16: =VLOOKUP($A16,Controle!$B$4:$F$68,2,FALSE) -> Diamantina 1 | C16: =VLOOKUP($A16,Controle!$B$4:$F$68,3,FALSE) -> MORI GERACAO II | D16: =VLOOKUP($A16,Controle!$B$4:$F$68,4,FALSE) -> Mori II | E16: =VLOOKUP($A16,Controle!$B$4:$F$68,5,FALSE) -> 3 | F16: Desenvolvimento de projeto - Coordenograma | G16: =VLOOKUP($A16,Controle!$B$4:$G$68,6,FALSE) -> Mori | H16: PROJETTI | I16: 6206.9 | J16: 0 | K16: 0 | L16: 0 | M16: 0 | N16: 0 | O16: =SUM(I16:N16) -> 6206.9 | P16: =SUMIFS('Desenvolvimento diário'!$H:$H,'Desenvolvimento diário'!$Q:$Q,$B16,'Desenvolvimento diário'!$P:$P,$F16,'Desenvolvimento diário'!$R:$R,"Sim") -> 0 | Q16: =SUMIFS('Desenvolvimento diário'!$H:$H,'Desenvolvimento diário'!$Q:$Q,$B16,'Desenvolvimento diário'!$P:$P,$F16,'Desenvolvimento diário'!$R:$R,"Não") -> 6206.9 | R16: =SUM(P16:Q16) -> 6206.9 | S16: =O16-R16 -> 0 | T16: =IFERROR(R16/O16,0) -> 1
A17: =A16 -> 1 | B17: =VLOOKUP($A17,Controle!$B$4:$F$68,2,FALSE) -> Diamantina 1 | C17: =VLOOKUP($A17,Controle!$B$4:$F$68,3,FALSE) -> MORI GERACAO II | D17: =VLOOKUP($A17,Controle!$B$4:$F$68,4,FALSE) -> Mori II | E17: =VLOOKUP($A17,Controle!$B$4:$F$68,5,FALSE) -> 3 | F17: Sistemas de Monitoramento - Supervisório | G17: =VLOOKUP($A17,Controle!$B$4:$G$68,6,FALSE) -> Mori | H17: ATI | I17: =136155.01-0.02 -> 136154.99 | K17: 0 | L17: 0 | M17: 0 | N17: 0 | O17: =SUM(I17:N17) -> 136154.99 | P17: =SUMIFS('Desenvolvimento diário'!$H:$H,'Desenvolvimento diário'!$Q:$Q,$B17,'Desenvolvimento diário'!$P:$P,$F17,'Desenvolvimento diário'!$R:$R,"Sim") -> 5821.02 | Q17: =SUMIFS('Desenvolvimento diário'!$H:$H,'Desenvolvimento diário'!$Q:$Q,$B17,'Desenvolvimento diário'!$P:$P,$F17,'Desenvolvimento diário'!$R:$R,"Não") -> 130333.97 | R17: =SUM(P17:Q17) -> 136154.99 | S17: =O17-R17 -> 0 | T17: =IFERROR(R17/O17,0) -> 1
A18: =A17 -> 1 | B18: =VLOOKUP($A18,Controle!$B$4:$F$68,2,FALSE) -> Diamantina 1 | C18: =VLOOKUP($A18,Controle!$B$4:$F$68,3,FALSE) -> MORI GERACAO II | D18: =VLOOKUP($A18,Controle!$B$4:$F$68,4,FALSE) -> Mori II | E18: =VLOOKUP($A18,Controle!$B$4:$F$68,5,FALSE) -> 3 | F18: Sistemas de Monitoramento - Estações Solarimétricas | G18: =VLOOKUP($A18,Controle!$B$4:$G$68,6,FALSE) -> Mori | H18: Hukseflux | I18: 48276.516 | J18: 0 | K18: 0 | L18: 0 | M18: 0 | N18: 0 | O18: =SUM(I18:N18) -> 48276.516 | P18: =SUMIFS('Desenvolvimento diário'!$H:$H,'Desenvolvimento diário'!$Q:$Q,$B18,'Desenvolvimento diário'!$P:$P,$F18,'Desenvolvimento diário'!$R:$R,"Sim") -> 0 | Q18: =SUMIFS('Desenvolvimento diário'!$H:$H,'Desenvolvimento diário'!$Q:$Q,$B18,'Desenvolvimento diário'!$P:$P,$F18,'Desenvolvimento diário'!$R:$R,"Não") -> 48276.516 | R18: =SUM(P18:Q18) -> 48276.516 | S18: =O18-R18 -> 0 | T18: =IFERROR(R18/O18,0) -> 1
A19: =A18 -> 1 | B19: =VLOOKUP($A19,Controle!$B$4:$F$68,2,FALSE) -> Diamantina 1 | C19: =VLOOKUP($A19,Controle!$B$4:$F$68,3,FALSE) -> MORI GERACAO II | D19: =VLOOKUP($A19,Controle!$B$4:$F$68,4,FALSE) -> Mori II | E19: =VLOOKUP($A19,Controle!$B$4:$F$68,5,FALSE) -> 3 | F19: Sistemas de Monitoramento - CFTV | G19: =VLOOKUP($A19,Controle!$B$4:$G$68,6,FALSE) -> Mori | H19: Maxvision | I19: 248414.57 | J19: 0 | K19: 10913.68 | L19: 0 | M19: 0 | N19: 0 | O19: =SUM(I19:N19) -> 259328.25 | P19: =SUMIFS('Desenvolvimento diário'!$H:$H,'Desenvolvimento diário'!$Q:$Q,$B19,'Desenvolvimento diário'!$P:$P,$F19,'Desenvolvimento diário'!$R:$R,"Sim") -> 0 | Q19: =SUMIFS('Desenvolvimento diário'!$H:$H,'Desenvolvimento diário'!$Q:$Q,$B19,'Desenvolvimento diário'!$P:$P,$F19,'Desenvolvimento diário'!$R:$R,"Não") -> 259328.25 | R19: =SUM(P19:Q19) -> 259328.25 | S19: =O19-R19 -> 0 | T19: =IFERROR(R19/O19,0) -> 1
A20: =A19 -> 1 | B20: =VLOOKUP($A20,Controle!$B$4:$F$68,2,FALSE) -> Diamantina 1 | C20: =VLOOKUP($A20,Controle!$B$4:$F$68,3,FALSE) -> MORI GERACAO II | D20: =VLOOKUP($A20,Controle!$B$4:$F$68,4,FALSE) -> Mori II | E20: =VLOOKUP($A20,Controle!$B$4:$F$68,5,FALSE) -> 3 | F20: Serviços Auxiliares - Drenagem | G20: =VLOOKUP($A20,Controle!$B$4:$G$68,6,FALSE) -> Mori | H20: CONSPLAN / ORCI / Engetela | I20: 839026.26 | J20: 293286.3 | K20: 188709 | L20: =82625+14190 -> 96815 | M20: 0 | N20: 0 | O20: =SUM(I20:N20) -> 1417836.6 | P20: =SUMIFS('Desenvolvimento diário'!$H:$H,'Desenvolvimento diário'!$Q:$Q,$B20,'Desenvolvimento diário'!$P:$P,$F20,'Desenvolvimento diário'!$R:$R,"Sim") -> 94354.5 | Q20: =SUMIFS('Desenvolvimento diário'!$H:$H,'Desenvolvimento diário'!$Q:$Q,$B20,'Desenvolvimento diário'!$P:$P,$F20,'Desenvolvimento diário'!$R:$R,"Não") -> 1323482.1 | R20: =SUM(P20:Q20) -> 1417836.6 | S20: =O20-R20 -> 0 | T20: =IFERROR(R20/O20,0) -> 1
A21: =A20 -> 1 | B21: =VLOOKUP($A21,Controle!$B$4:$F$68,2,FALSE) -> Diamantina 1 | C21: =VLOOKUP($A21,Controle!$B$4:$F$68,3,FALSE) -> MORI GERACAO II | D21: =VLOOKUP($A21,Controle!$B$4:$F$68,4,FALSE) -> Mori II | E21: =VLOOKUP($A21,Controle!$B$4:$F$68,5,FALSE) -> 3 | F21: Serviços Auxiliares - Terraplanagem | G21: =VLOOKUP($A21,Controle!$B$4:$G$68,6,FALSE) -> Mori | H21: MRO | I21: 1108130.6 | J21: 0 | K21: 0 | L21: 0 | M21: 0 | N21: 0 | O21: =SUM(I21:N21) -> 1108130.6 | P21: =SUMIFS('Desenvolvimento diário'!$H:$H,'Desenvolvimento diário'!$Q:$Q,$B21,'Desenvolvimento diário'!$P:$P,$F21,'Desenvolvimento diário'!$R:$R,"Sim") -> 0 | Q21: =SUMIFS('Desenvolvimento diário'!$H:$H,'Desenvolvimento diário'!$Q:$Q,$B21,'Desenvolvimento diário'!$P:$P,$F21,'Desenvolvimento diário'!$R:$R,"Não") -> 1108130.6 | R21: =SUM(P21:Q21) -> 1108130.6 | S21: =O21-R21 -> 0 | T21: =IFERROR(R21/O21,0) -> 1
A22: =A21 -> 1 | B22: =VLOOKUP($A22,Controle!$B$4:$F$68,2,FALSE) -> Diamantina 1 | C22: =VLOOKUP($A22,Controle!$B$4:$F$68,3,FALSE) -> MORI GERACAO II | D22: =VLOOKUP($A22,Controle!$B$4:$F$68,4,FALSE) -> Mori II | E22: =VLOOKUP($A22,Controle!$B$4:$F$68,5,FALSE) -> 3 | F22: Serviços Auxiliares - Supressão Vegetal | G22: =VLOOKUP($A22,Controle!$B$4:$G$68,6,FALSE) -> Mori | H22: Rima | I22: 50000 | J22: 3500 | K22: 30000 | L22: 0 | M22: 0 | N22: 0 | O22: =SUM(I22:N22) -> 83500 | P22: =SUMIFS('Desenvolvimento diário'!$H:$H,'Desenvolvimento diário'!$Q:$Q,$B22,'Desenvolvimento diário'!$P:$P,$F22,'Desenvolvimento diário'!$R:$R,"Sim") -> 0 | Q22: =SUMIFS('Desenvolvimento diário'!$H:$H,'Desenvolvimento diário'!$Q:$Q,$B22,'Desenvolvimento diário'!$P:$P,$F22,'Desenvolvimento diário'!$R:$R,"Não") -> 83500 | R22: =SUM(P22:Q22) -> 83500 | S22: =O22-R22 -> 0 | T22: =IFERROR(R22/O22,0) -> 1
A23: =A22 -> 1 | B23: =VLOOKUP($A23,Controle!$B$4:$F$68,2,FALSE) -> Diamantina 1 | C23: =VLOOKUP($A23,Controle!$B$4:$F$68,3,FALSE) -> MORI GERACAO II | D23: =VLOOKUP($A23,Controle!$B$4:$F$68,4,FALSE) -> Mori II | E23: =VLOOKUP($A23,Controle!$B$4:$F$68,5,FALSE) -> 3 | F23: RDR-Rede de Distribuição Rural | G23: =VLOOKUP($A23,Controle!$B$4:$G$68,6,FALSE) -> Mori | H23: 0 | I23: 0 | J23: 0 | K23: 0 | L23: 0 | M23: 0 | N23: 0 | O23: =SUM(I23:N23) -> 0 | P23: =SUMIFS('Desenvolvimento diário'!$H:$H,'Desenvolvimento diário'!$Q:$Q,$B23,'Desenvolvimento diário'!$P:$P,$F23,'Desenvolvimento diário'!$R:$R,"Sim") -> 0 | Q23: =SUMIFS('Desenvolvimento diário'!$H:$H,'Desenvolvimento diário'!$Q:$Q,$B23,'Desenvolvimento diário'!$P:$P,$F23,'Desenvolvimento diário'!$R:$R,"Não") -> 0 | R23: =SUM(P23:Q23) -> 0 | S23: =O23-R23 -> 0 | T23: =IFERROR(R23/O23,0) -> 0
A24: =A23 -> 1 | B24: =VLOOKUP($A24,Controle!$B$4:$F$68,2,FALSE) -> Diamantina 1 | C24: =VLOOKUP($A24,Controle!$B$4:$F$68,3,FALSE) -> MORI GERACAO II | D24: =VLOOKUP($A24,Controle!$B$4:$F$68,4,FALSE) -> Mori II | E24: =VLOOKUP($A24,Controle!$B$4:$F$68,5,FALSE) -> 3 | F24: Escopo COMERC | G24: =VLOOKUP($A24,Controle!$B$4:$G$68,6,FALSE) -> Mori | H24: 0 | I24: 552033.58 | J24: 59000 | K24: 0 | L24: 0 | M24: 0 | N24: 0 | O24: =SUM(I24:N24) -> 611033.58 | P24: =SUMIFS('Desenvolvimento diário'!$H:$H,'Desenvolvimento diário'!$Q:$Q,$B24,'Desenvolvimento diário'!$P:$P,$F24,'Desenvolvimento diário'!$R:$R,"Sim") -> 61688.6 | Q24: =SUMIFS('Desenvolvimento diário'!$H:$H,'Desenvolvimento diário'!$Q:$Q,$B24,'Desenvolvimento diário'!$P:$P,$F24,'Desenvolvimento diário'!$R:$R,"Não") -> 491343.76 | R24: =SUM(P24:Q24) -> 553032.36 | S24: =O24-R24 -> 58001.22 | T24: =IFERROR(R24/O24,0) -> 0.90507687 | U24: S | V24: Escopo Comerc
A25: =A24 -> 1 | B25: =VLOOKUP($A25,Controle!$B$4:$F$68,2,FALSE) -> Diamantina 1 | C25: =VLOOKUP($A25,Controle!$B$4:$F$68,3,FALSE) -> MORI GERACAO II | D25: =VLOOKUP($A25,Controle!$B$4:$F$68,4,FALSE) -> Mori II | E25: =VLOOKUP($A25,Controle!$B$4:$F$68,5,FALSE) -> 3 | F25: Escopo COMERC - Segurança | G25: =VLOOKUP($A25,Controle!$B$4:$G$68,6,FALSE) -> Mori | H25: 0 | I25: =R25 -> 231000 | J25: 0 | K25: 0 | L25: 0 | M25: 0 | N25: 0 | O25: =SUM(I25:N25) -> 231000 | P25: =SUMIFS('Desenvolvimento diário'!$H:$H,'Desenvolvimento diário'!$Q:$Q,$B25,'Desenvolvimento diário'!$P:$P,$F25,'Desenvolvimento diário'!$R:$R,"Sim") -> 0 | Q25: =SUMIFS('Desenvolvimento diário'!$H:$H,'Desenvolvimento diário'!$Q:$Q,$B25,'Desenvolvimento diário'!$P:$P,$F25,'Desenvolvimento diário'!$R:$R,"Não") -> 231000 | R25: =SUM(P25:Q25) -> 231000 | S25: =O25-R25 -> 0 | T25: =IFERROR(R25/O25,0) -> 1
A26: =A25 -> 1 | B26: =VLOOKUP($A26,Controle!$B$4:$F$68,2,FALSE) -> Diamantina 1 | C26: =VLOOKUP($A26,Controle!$B$4:$F$68,3,FALSE) -> MORI GERACAO II | D26: =VLOOKUP($A26,Controle!$B$4:$F$68,4,FALSE) -> Mori II | E26: =VLOOKUP($A26,Controle!$B$4:$F$68,5,FALSE) -> 3 | F26: Conexão MT - Obras Transferencia | G26: =VLOOKUP($A26,Controle!$B$4:$G$68,6,FALSE) -> Mori | H26: Engeluz | I26: 3677500 | J26: 1070080.4 | K26: 0 | L26: 0 | M26: 0 | N26: 0 | O26: =SUM(I26:N26) -> 4747580.4 | P26: =SUMIFS('Desenvolvimento diário'!$H:$H,'Desenvolvimento diário'!$Q:$Q,$B26,'Desenvolvimento diário'!$P:$P,$F26,'Desenvolvimento diário'!$R:$R,"Sim") -> 1711832.9 | Q26: =SUMIFS('Desenvolvimento diário'!$H:$H,'Desenvolvimento diário'!$Q:$Q,$B26,'Desenvolvimento diário'!$P:$P,$F26,'Desenvolvimento diário'!$R:$R,"Não") -> 3035747.5 | R26: =SUM(P26:Q26) -> 4747580.4 | S26: =O26-R26 -> 0 | T26: =IFERROR(R26/O26,0) -> 1
A27: =A26 -> 1 | B27: =VLOOKUP($A27,Controle!$B$4:$F$68,2,FALSE) -> Diamantina 1 | C27: =VLOOKUP($A27,Controle!$B$4:$F$68,3,FALSE) -> MORI GERACAO II | D27: =VLOOKUP($A27,Controle!$B$4:$F$68,4,FALSE) -> Mori II | E27: =VLOOKUP($A27,Controle!$B$4:$F$68,5,FALSE) -> 3 | F27: Bases de Contaniers | G27: =VLOOKUP($A27,Controle!$B$4:$G$68,6,FALSE) -> Mori | H27: 0 | I27: 0 | J27: 0 | K27: 0 | L27: 0 | M27: 0 | N27: 0 | O27: =SUM(I27:N27) -> 0 | P27: =SUMIFS('Desenvolvimento diário'!$H:$H,'Desenvolvimento diário'!$Q:$Q,$B27,'Desenvolvimento diário'!$P:$P,$F27,'Desenvolvimento diário'!$R:$R,"Sim") -> 0 | Q27: =SUMIFS('Desenvolvimento diário'!$H:$H,'Desenvolvimento diário'!$Q:$Q,$B27,'Desenvolvimento diário'!$P:$P,$F27,'Desenvolvimento diário'!$R:$R,"Não") -> 0 | R27: =SUM(P27:Q27) -> 0 | S27: =O27-R27 -> 0 | T27: =IFERROR(R27/O27,0) -> 0
A28: =A27 -> 1 | B28: =VLOOKUP($A28,Controle!$B$4:$F$68,2,FALSE) -> Diamantina 1 | C28: =VLOOKUP($A28,Controle!$B$4:$F$68,3,FALSE) -> MORI GERACAO II | D28: =VLOOKUP($A28,Controle!$B$4:$F$68,4,FALSE) -> Mori II | E28: =VLOOKUP($A28,Controle!$B$4:$F$68,5,FALSE) -> 3 | F28: Construção - Serviços de Construção - Ase Engenharia | G28: =VLOOKUP($A28,Controle!$B$4:$G$68,6,FALSE) -> Mori | H28: 0 | I28: 0 | J28: 0 | K28: 0 | L28: 0 | M28: 0 | N28: 0 | O28: =SUM(I28:N28) -> 0 | P28: =SUMIFS('Desenvolvimento diário'!$H:$H,'Desenvolvimento diário'!$Q:$Q,$B28,'Desenvolvimento diário'!$P:$P,$F28,'Desenvolvimento diário'!$R:$R,"Sim") -> 0 | Q28: =SUMIFS('Desenvolvimento diário'!$H:$H,'Desenvolvimento diário'!$Q:$Q,$B28,'Desenvolvimento diário'!$P:$P,$F28,'Desenvolvimento diário'!$R:$R,"Não") -> 0 | R28: =SUM(P28:Q28) -> 0 | S28: =O28-R28 -> 0 | T28: =IFERROR(R28/O28,0) -> 0
A29: =A28 -> 1 | B29: =VLOOKUP($A29,Controle!$B$4:$F$68,2,FALSE) -> Diamantina 1 | C29: =VLOOKUP($A29,Controle!$B$4:$F$68,3,FALSE) -> MORI GERACAO II | D29: =VLOOKUP($A29,Controle!$B$4:$F$68,4,FALSE) -> Mori II | E29: =VLOOKUP($A29,Controle!$B$4:$F$68,5,FALSE) -> 3 | F29: Full EPC - Contrato Sobressalentes | G29: =VLOOKUP($A29,Controle!$B$4:$G$68,6,FALSE) -> Mori | H29: 0 | I29: 0 | J29: 0 | K29: 0 | L29: 0 | M29: 0 | N29: 0 | O29: =SUM(I29:N29) -> 0 | P29: =SUMIFS('Desenvolvimento diário'!$H:$H,'Desenvolvimento diário'!$Q:$Q,$B29,'Desenvolvimento diário'!$P:$P,$F29,'Desenvolvimento diário'!$R:$R,"Sim") -> 0 | Q29: =SUMIFS('Desenvolvimento diário'!$H:$H,'Desenvolvimento diário'!$Q:$Q,$B29,'Desenvolvimento diário'!$P:$P,$F29,'Desenvolvimento diário'!$R:$R,"Não") -> 0 | R29: =SUM(P29:Q29) -> 0 | S29: =O29-R29 -> 0 | T29: =IFERROR(R29/O29,0) -> 0
A30: =A29 -> 1 | B30: =VLOOKUP($A30,Controle!$B$4:$F$68,2,FALSE) -> Diamantina 1 | C30: =VLOOKUP($A30,Controle!$B$4:$F$68,3,FALSE) -> MORI GERACAO II | D30: =VLOOKUP($A30,Controle!$B$4:$F$68,4,FALSE) -> Mori II | E30: =VLOOKUP($A30,Controle!$B$4:$F$68,5,FALSE) -> 3 | F30: Construção - Serviços de Construção - NOVA MORADA | G30: =VLOOKUP($A30,Controle!$B$4:$G$68,6,FALSE) -> Mori | H30: 0 | I30: 0 | J30: 0 | K30: 0 | L30: 0 | M30: 0 | N30: 0 | O30: =SUM(I30:N30) -> 0 | P30: =SUMIFS('Desenvolvimento diário'!$H:$H,'Desenvolvimento diário'!$Q:$Q,$B30,'Desenvolvimento diário'!$P:$P,$F30,'Desenvolvimento diário'!$R:$R,"Sim") -> 0 | Q30: =SUMIFS('Desenvolvimento diário'!$H:$H,'Desenvolvimento diário'!$Q:$Q,$B30,'Desenvolvimento diário'!$P:$P,$F30,'Desenvolvimento diário'!$R:$R,"Não") -> 0 | R30: =SUM(P30:Q30) -> 0 | S30: =O30-R30 -> 0 | T30: =IFERROR(R30/O30,0) -> 0
A31: =A30 -> 1 | B31: =VLOOKUP($A31,Controle!$B$4:$F$68,2,FALSE) -> Diamantina 1 | C31: =VLOOKUP($A31,Controle!$B$4:$F$68,3,FALSE) -> MORI GERACAO II | D31: =VLOOKUP($A31,Controle!$B$4:$F$68,4,FALSE) -> Mori II | E31: =VLOOKUP($A31,Controle!$B$4:$F$68,5,FALSE) -> 3 | F31: Equipamentos Curva A - Contrato Sobressalentes - SETTA | G31: =VLOOKUP($A31,Controle!$B$4:$G$68,6,FALSE) -> Mori | H31: 0 | I31: 0 | J31: 0 | K31: 0 | L31: 0 | M31: 0 | N31: 0 | O31: =SUM(I31:N31) -> 0 | P31: =SUMIFS('Desenvolvimento diário'!$H:$H,'Desenvolvimento diário'!$Q:$Q,$B31,'Desenvolvimento diário'!$P:$P,$F31,'Desenvolvimento diário'!$R:$R,"Sim") -> 0 | Q31: =SUMIFS('Desenvolvimento diário'!$H:$H,'Desenvolvimento diário'!$Q:$Q,$B31,'Desenvolvimento diário'!$P:$P,$F31,'Desenvolvimento diário'!$R:$R,"Não") -> 0 | R31: =SUM(P31:Q31) -> 0 | S31: =O31-R31 -> 0 | T31: =IFERROR(R31/O31,0) -> 0
A32: =A31 -> 1 | B32: =VLOOKUP($A32,Controle!$B$4:$F$68,2,FALSE) -> Diamantina 1 | C32: =VLOOKUP($A32,Controle!$B$4:$F$68,3,FALSE) -> MORI GERACAO II | D32: =VLOOKUP($A32,Controle!$B$4:$F$68,4,FALSE) -> Mori II | E32: =VLOOKUP($A32,Controle!$B$4:$F$68,5,FALSE) -> 3 | F32: Equipamentos Curva A - Contrato Sobressalentes - Arctech | G32: =VLOOKUP($A32,Controle!$B$4:$G$68,6,FALSE) -> Mori | H32: 0 | I32: 0 | J32: 0 | K32: 0 | L32: 0 | M32: 0 | N32: 0 | O32: =SUM(I32:N32) -> 0 | P32: =SUMIFS('Desenvolvimento diário'!$H:$H,'Desenvolvimento diário'!$Q:$Q,$B32,'Desenvolvimento diário'!$P:$P,$F32,'Desenvolvimento diário'!$R:$R,"Sim") -> 0 | Q32: =SUMIFS('Desenvolvimento diário'!$H:$H,'Desenvolvimento diário'!$Q:$Q,$B32,'Desenvolvimento diário'!$P:$P,$F32,'Desenvolvimento diário'!$R:$R,"Não") -> 0 | R32: =SUM(P32:Q32) -> 0 | S32: =O32-R32 -> 0 | T32: =IFERROR(R32/O32,0) -> 0
A33: =A30 -> 1 | B33: =VLOOKUP($A33,Controle!$B$4:$F$68,2,FALSE) -> Diamantina 1 | C33: =VLOOKUP($A33,Controle!$B$4:$F$68,3,FALSE) -> MORI GERACAO II | D33: =VLOOKUP($A33,Controle!$B$4:$F$68,4,FALSE) -> Mori II | E33: =VLOOKUP($A33,Controle!$B$4:$F$68,5,FALSE) -> 3 | F33: Equipamentos Curva A - Contrato Sobressalentes - Romagnole | G33: =VLOOKUP($A33,Controle!$B$4:$G$68,6,FALSE) -> Mori | H33: Onix | I33: 72399.64 | J33: 90503.03 | K33: 0 | L33: 0 | M33: 0 | N33: 0 | O33: =SUM(I33:N33) -> 162902.67 | P33: =SUMIFS('Desenvolvimento diário'!$H:$H,'Desenvolvimento diário'!$Q:$Q,$B33,'Desenvolvimento diário'!$P:$P,$F33,'Desenvolvimento diário'!$R:$R,"Sim") -> 0 | Q33: =SUMIFS('Desenvolvimento diário'!$H:$H,'Desenvolvimento diário'!$Q:$Q,$B33,'Desenvolvimento diário'!$P:$P,$F33,'Desenvolvimento diário'!$R:$R,"Não") -> 162902.67 | R33: =SUM(P33:Q33) -> 162902.67 | S33: =O33-R33 -> 0 | T33: =IFERROR(R33/O33,0) -> 1
A34: =A31 -> 1 | B34: =VLOOKUP($A34,Controle!$B$4:$F$68,2,FALSE) -> Diamantina 1 | C34: =VLOOKUP($A34,Controle!$B$4:$F$68,3,FALSE) -> MORI GERACAO II | D34: =VLOOKUP($A34,Controle!$B$4:$F$68,4,FALSE) -> Mori II | E34: =VLOOKUP($A34,Controle!$B$4:$F$68,5,FALSE) -> 3 | F34: GOS FLORESTAL - (PRAD - Recuperação Area Ambiental) | G34: =VLOOKUP($A34,Controle!$B$4:$G$68,6,FALSE) -> Mori | H34: Gos Florestal | I34: 426240 | K34: 0 | L34: 0 | M34: 0 | N34: 0 | O34: =SUM(I34:N34) -> 426240 | P34: =SUMIFS('Desenvolvimento diário'!$H:$H,'Desenvolvimento diário'!$Q:$Q,$B34,'Desenvolvimento diário'!$P:$P,$F34,'Desenvolvimento diário'!$R:$R,"Sim") -> 0 | Q34: =SUMIFS('Desenvolvimento diário'!$H:$H,'Desenvolvimento diário'!$Q:$Q,$B34,'Desenvolvimento diário'!$P:$P,$F34,'Desenvolvimento diário'!$R:$R,"Não") -> 426240 | R34: =SUM(P34:Q34) -> 426240 | S34: =O34-R34 -> 0 | T34: =IFERROR(R34/O34,0) -> 1 | U34: S | V34: GOS - Esse refere-se ao Contrato aprovado junto com acerto das Drenagens
A35: =A32 -> 1 | B35: =VLOOKUP($A35,Controle!$B$4:$F$68,2,FALSE) -> Diamantina 1 | C35: =VLOOKUP($A35,Controle!$B$4:$F$68,3,FALSE) -> MORI GERACAO II | D35: =VLOOKUP($A35,Controle!$B$4:$F$68,4,FALSE) -> Mori II | E35: =VLOOKUP($A35,Controle!$B$4:$F$68,5,FALSE) -> 3 | F35: Cercamento das bacias de contenção ciclo 2 | G35: =VLOOKUP($A35,Controle!$B$4:$G$68,6,FALSE) -> Mori | H35: A Definir | K35: 0 | L35: 0 | M35: 0 | N35: 0 | O35: =SUM(I35:N35) -> 0 | P35: =SUMIFS('Desenvolvimento diário'!$H:$H,'Desenvolvimento diário'!$Q:$Q,$B35,'Desenvolvimento diário'!$P:$P,$F35,'Desenvolvimento diário'!$R:$R,"Sim") -> 0 | Q35: =SUMIFS('Desenvolvimento diário'!$H:$H,'Desenvolvimento diário'!$Q:$Q,$B35,'Desenvolvimento diário'!$P:$P,$F35,'Desenvolvimento diário'!$R:$R,"Não") -> 0 | R35: =SUM(P35:Q35) -> 0 | S35: =O35-R35 -> 0 | T35: =IFERROR(R35/O35,0) -> 0 | U35: S | V35: Cercamento das bacias de contenção ciclo 2
A36: =A35 -> 1 | B36: =B35 -> Diamantina 1 | C36: =C35 -> MORI GERACAO II | D36: =D35 -> Mori II | E36: =E35 -> 3 | F36: Total | G36: =G35 -> Mori | I36: =SUBTOTAL(9,I2:I35) -> 0 | J36: =SUBTOTAL(9,J2:J35) -> 0 | K36: =SUBTOTAL(9,K2:K35) -> 0 | L36: =SUBTOTAL(9,L2:L35) -> 0 | M36: =SUBTOTAL(9,M2:M35) -> 0 | N36: =SUBTOTAL(9,N2:N35) -> 0 | O36: =SUBTOTAL(9,O2:O35) -> 0 | P36: =SUBTOTAL(9,P2:P35) -> 0 | ... S36: =SUBTOTAL(9,S2:S35) -> 0 | T36: =IFERROR(R36/O36,0) -> 0 | U36: =SUBTOTAL(9,U2:U35) -> 0
A37: =A2+1 -> 2 | B37: =VLOOKUP($A37,Controle!$B$4:$F$68,2,FALSE) -> Diamantina 2 | C37: =VLOOKUP($A37,Controle!$B$4:$F$68,3,FALSE) -> MORI GERACAO II | D37: =VLOOKUP($A37,Controle!$B$4:$F$68,4,FALSE) -> Mori II | E37: =VLOOKUP($A37,Controle!$B$4:$F$68,5,FALSE) -> 3 | F37: =F2 -> Conexão AT - Obras | G37: =VLOOKUP($A37,Controle!$B$4:$G$68,6,FALSE) -> Mori | H37: MBA | I37: 302420 | J37: 0 | K37: 0 | L37: 0 | M37: 0 | N37: 0 | O37: =SUM(I37:N37) -> 302420 | P37: =SUMIFS('Desenvolvimento diário'!$H:$H,'Desenvolvimento diário'!$Q:$Q,$B37,'Desenvolvimento diário'!$P:$P,$F37,'Desenvolvimento diário'!$R:$R,"Sim") -> 30000 | Q37: =SUMIFS('Desenvolvimento diário'!$H:$H,'Desenvolvimento diário'!$Q:$Q,$B37,'Desenvolvimento diário'!$P:$P,$F37,'Desenvolvimento diário'!$R:$R,"Não") -> 272420 | R37: =SUM(P37:Q37) -> 302420 | S37: =O37-R37 -> 0 | T37: =IFERROR(R37/O37,0) -> 1
A38: =A37 -> 2 | B38: =VLOOKUP($A38,Controle!$B$4:$F$68,2,FALSE) -> Diamantina 2 | C38: =VLOOKUP($A38,Controle!$B$4:$F$68,3,FALSE) -> MORI GERACAO II | D38: =VLOOKUP($A38,Controle!$B$4:$F$68,4,FALSE) -> Mori II | E38: =VLOOKUP($A38,Controle!$B$4:$F$68,5,FALSE) -> 3 | F38: =F3 -> Conexão MT - Obras | G38: =VLOOKUP($A38,Controle!$B$4:$G$68,6,FALSE) -> Mori | H38: MBA | I38: =I61*20% -> 733091.34 | J38: =51135+80355 -> 131490 | K38: 492542.22 | L38: 0 | M38: 0 | N38: 0 | O38: =SUM(I38:N38) -> 1357123.6 | P38: =SUMIFS('Desenvolvimento diário'!$H:$H,'Desenvolvimento diário'!$Q:$Q,$B38,'Desenvolvimento diário'!$P:$P,$F38,'Desenvolvimento diário'!$R:$R,"Sim") -> 137032.22 | Q38: =SUMIFS('Desenvolvimento diário'!$H:$H,'Desenvolvimento diário'!$Q:$Q,$B38,'Desenvolvimento diário'!$P:$P,$F38,'Desenvolvimento diário'!$R:$R,"Não") -> 1220091.3 | R38: =SUM(P38:Q38) -> 1357123.6 | S38: =O38-R38 -> 0 | T38: =IFERROR(R38/O38,0) -> 1
A39: =A38 -> 2 | B39: =VLOOKUP($A39,Controle!$B$4:$F$68,2,FALSE) -> Diamantina 2 | C39: =VLOOKUP($A39,Controle!$B$4:$F$68,3,FALSE) -> MORI GERACAO II | D39: =VLOOKUP($A39,Controle!$B$4:$F$68,4,FALSE) -> Mori II | E39: =VLOOKUP($A39,Controle!$B$4:$F$68,5,FALSE) -> 3 | F39: =F4 -> Construção - Serviços de Construção | G39: =VLOOKUP($A39,Controle!$B$4:$G$68,6,FALSE) -> Mori | H39: Implantar | I39: 2556450 | J39: 157000 | K39: 0 | L39: 0 | M39: 0 | N39: 0 | O39: =SUM(I39:N39) -> 2713450 | P39: =SUMIFS('Desenvolvimento diário'!$H:$H,'Desenvolvimento diário'!$Q:$Q,$B39,'Desenvolvimento diário'!$P:$P,$F39,'Desenvolvimento diário'!$R:$R,"Sim") -> 1642553.6 | Q39: =SUMIFS('Desenvolvimento diário'!$H:$H,'Desenvolvimento diário'!$Q:$Q,$B39,'Desenvolvimento diário'!$P:$P,$F39,'Desenvolvimento diário'!$R:$R,"Não") -> 1038444.8 | R39: =SUM(P39:Q39) -> 2680998.4 | S39: =O39-R39 -> 32451.59 | T39: =IFERROR(R39/O39,0) -> 0.98804047 | U39: N | V39: Em Processo Judicial
A40: =A39 -> 2 | B40: =VLOOKUP($A40,Controle!$B$4:$F$68,2,FALSE) -> Diamantina 2 | C40: =VLOOKUP($A40,Controle!$B$4:$F$68,3,FALSE) -> MORI GERACAO II | D40: =VLOOKUP($A40,Controle!$B$4:$F$68,4,FALSE) -> Mori II | E40: =VLOOKUP($A40,Controle!$B$4:$F$68,5,FALSE) -> 3 | F40: =F5 -> Construção - Serviços de Construção - Substituição | G40: =VLOOKUP($A40,Controle!$B$4:$G$68,6,FALSE) -> Mori | H40: 0 | I40: 0 | J40: 0 | K40: 0 | L40: 0 | M40: 0 | N40: 0 | O40: =SUM(I40:N40) -> 0 | P40: =SUMIFS('Desenvolvimento diário'!$H:$H,'Desenvolvimento diário'!$Q:$Q,$B40,'Desenvolvimento diário'!$P:$P,$F40,'Desenvolvimento diário'!$R:$R,"Sim") -> 0 | Q40: =SUMIFS('Desenvolvimento diário'!$H:$H,'Desenvolvimento diário'!$Q:$Q,$B40,'Desenvolvimento diário'!$P:$P,$F40,'Desenvolvimento diário'!$R:$R,"Não") -> 0 | R40: =SUM(P40:Q40) -> 0 | S40: =O40-R40 -> 0 | T40: =IFERROR(R40/O40,0) -> 0
A41: =A40 -> 2 | B41: =VLOOKUP($A41,Controle!$B$4:$F$68,2,FALSE) -> Diamantina 2 | C41: =VLOOKUP($A41,Controle!$B$4:$F$68,3,FALSE) -> MORI GERACAO II | D41: =VLOOKUP($A41,Controle!$B$4:$F$68,4,FALSE) -> Mori II | E41: =VLOOKUP($A41,Controle!$B$4:$F$68,5,FALSE) -> 3 | F41: =F6 -> Construção - RDA Interno | G41: =VLOOKUP($A41,Controle!$B$4:$G$68,6,FALSE) -> Mori | H41: Eletrocamp | I41: 700085 | J41: 6400 | K41: 7304.5454 | L41: 0 | M41: 0 | N41: 0 | O41: =SUM(I41:N41)+0.0046 -> 713789.55 | P41: =SUMIFS('Desenvolvimento diário'!$H:$H,'Desenvolvimento diário'!$Q:$Q,$B41,'Desenvolvimento diário'!$P:$P,$F41,'Desenvolvimento diário'!$R:$R,"Sim") -> 0 | Q41: =SUMIFS('Desenvolvimento diário'!$H:$H,'Desenvolvimento diário'!$Q:$Q,$B41,'Desenvolvimento diário'!$P:$P,$F41,'Desenvolvimento diário'!$R:$R,"Não") -> 713789.55 | R41: =SUM(P41:Q41) -> 713789.55 | S41: =O41-R41 -> 0 | T41: =IFERROR(R41/O41,0) -> 1
A42: =A41 -> 2 | B42: =VLOOKUP($A42,Controle!$B$4:$F$68,2,FALSE) -> Diamantina 2 | C42: =VLOOKUP($A42,Controle!$B$4:$F$68,3,FALSE) -> MORI GERACAO II | D42: =VLOOKUP($A42,Controle!$B$4:$F$68,4,FALSE) -> Mori II | E42: =VLOOKUP($A42,Controle!$B$4:$F$68,5,FALSE) -> 3 | F42: =F7 -> Full EPC - Contrato | G42: =VLOOKUP($A42,Controle!$B$4:$G$68,6,FALSE) -> Mori | H42: 0 | I42: 0 | J42: 0 | K42: 0 | L42: 0 | M42: 0 | N42: 0 | O42: =SUM(I42:N42) -> 0 | P42: =SUMIFS('Desenvolvimento diário'!$H:$H,'Desenvolvimento diário'!$Q:$Q,$B42,'Desenvolvimento diário'!$P:$P,$F42,'Desenvolvimento diário'!$R:$R,"Sim") -> 0 | Q42: =SUMIFS('Desenvolvimento diário'!$H:$H,'Desenvolvimento diário'!$Q:$Q,$B42,'Desenvolvimento diário'!$P:$P,$F42,'Desenvolvimento diário'!$R:$R,"Não") -> 0 | R42: =SUM(P42:Q42) -> 0 | S42: =O42-R42 -> 0 | T42: =IFERROR(R42/O42,0) -> 0
A43: =A42 -> 2 | B43: =VLOOKUP($A43,Controle!$B$4:$F$68,2,FALSE) -> Diamantina 2 | C43: =VLOOKUP($A43,Controle!$B$4:$F$68,3,FALSE) -> MORI GERACAO II | D43: =VLOOKUP($A43,Controle!$B$4:$F$68,4,FALSE) -> Mori II | E43: =VLOOKUP($A43,Controle!$B$4:$F$68,5,FALSE) -> 3 | F43: =F8 -> Equipamentos Curva A - Outros (Transformadores) | G43: =VLOOKUP($A43,Controle!$B$4:$G$68,6,FALSE) -> Mori | H43: 0 | I43: 0 | J43: 0 | K43: 0 | L43: 0 | M43: 0 | N43: 0 | O43: =SUM(I43:N43) -> 0 | P43: =SUMIFS('Desenvolvimento diário'!$H:$H,'Desenvolvimento diário'!$Q:$Q,$B43,'Desenvolvimento diário'!$P:$P,$F43,'Desenvolvimento diário'!$R:$R,"Sim") -> 0 | Q43: =SUMIFS('Desenvolvimento diário'!$H:$H,'Desenvolvimento diário'!$Q:$Q,$B43,'Desenvolvimento diário'!$P:$P,$F43,'Desenvolvimento diário'!$R:$R,"Não") -> 0 | R43: =SUM(P43:Q43) -> 0 | S43: =O43-R43 -> 0 | T43: =IFERROR(R43/O43,0) -> 0
A44: =A43 -> 2 | B44: =VLOOKUP($A44,Controle!$B$4:$F$68,2,FALSE) -> Diamantina 2 | C44: =VLOOKUP($A44,Controle!$B$4:$F$68,3,FALSE) -> MORI GERACAO II | D44: =VLOOKUP($A44,Controle!$B$4:$F$68,4,FALSE) -> Mori II | E44: =VLOOKUP($A44,Controle!$B$4:$F$68,5,FALSE) -> 3 | F44: =F9 -> Equipamentos Curva A - Outros (Cabine + Skid) | G44: =VLOOKUP($A44,Controle!$B$4:$G$68,6,FALSE) -> Mori | H44: 0 | I44: 0 | J44: 0 | K44: 0 | L44: 0 | M44: 0 | N44: 0 | O44: =SUM(I44:N44) -> 0 | P44: =SUMIFS('Desenvolvimento diário'!$H:$H,'Desenvolvimento diário'!$Q:$Q,$B44,'Desenvolvimento diário'!$P:$P,$F44,'Desenvolvimento diário'!$R:$R,"Sim") -> 0 | Q44: =SUMIFS('Desenvolvimento diário'!$H:$H,'Desenvolvimento diário'!$Q:$Q,$B44,'Desenvolvimento diário'!$P:$P,$F44,'Desenvolvimento diário'!$R:$R,"Não") -> 0 | R44: =SUM(P44:Q44) -> 0 | S44: =O44-R44 -> 0 | T44: =IFERROR(R44/O44,0) -> 0
A45: =A44 -> 2 | B45: =VLOOKUP($A45,Controle!$B$4:$F$68,2,FALSE) -> Diamantina 2 | C45: =VLOOKUP($A45,Controle!$B$4:$F$68,3,FALSE) -> MORI GERACAO II | D45: =VLOOKUP($A45,Controle!$B$4:$F$68,4,FALSE) -> Mori II | E45: =VLOOKUP($A45,Controle!$B$4:$F$68,5,FALSE) -> 3 | F45: =F10 -> Equipamentos Curva A - Outros (Cabine + Skid + Transformador) | G45: =VLOOKUP($A45,Controle!$B$4:$G$68,6,FALSE) -> Mori | H45: Romagnole | I45: 1199784.7 | J45: 0 | K45: 0 | L45: 0 | M45: 0 | N45: 0 | O45: =SUM(I45:N45) -> 1199784.7 | P45: =SUMIFS('Desenvolvimento diário'!$H:$H,'Desenvolvimento diário'!$Q:$Q,$B45,'Desenvolvimento diário'!$P:$P,$F45,'Desenvolvimento diário'!$R:$R,"Sim") -> 0 | Q45: =SUMIFS('Desenvolvimento diário'!$H:$H,'Desenvolvimento diário'!$Q:$Q,$B45,'Desenvolvimento diário'!$P:$P,$F45,'Desenvolvimento diário'!$R:$R,"Não") -> 1199784.7 | R45: =SUM(P45:Q45) -> 1199784.7 | S45: =O45-R45 -> 0 | T45: =IFERROR(R45/O45,0) -> 1
A46: =A45 -> 2 | B46: =VLOOKUP($A46,Controle!$B$4:$F$68,2,FALSE) -> Diamantina 2 | C46: =VLOOKUP($A46,Controle!$B$4:$F$68,3,FALSE) -> MORI GERACAO II | D46: =VLOOKUP($A46,Controle!$B$4:$F$68,4,FALSE) -> Mori II | E46: =VLOOKUP($A46,Controle!$B$4:$F$68,5,FALSE) -> 3 | F46: =F11 -> Desenvolvimento de projeto - Projetos - (Eng° Proprietario) | G46: =VLOOKUP($A46,Controle!$B$4:$G$68,6,FALSE) -> Mori | H46: LM Eng. | I46: 0 | J46: 0 | K46: 0 | L46: 0 | M46: 0 | N46: 0 | O46: =SUM(I46:N46) -> 0 | P46: =SUMIFS('Desenvolvimento diário'!$H:$H,'Desenvolvimento diário'!$Q:$Q,$B46,'Desenvolvimento diário'!$P:$P,$F46,'Desenvolvimento diário'!$R:$R,"Sim") -> 0 | Q46: =SUMIFS('Desenvolvimento diário'!$H:$H,'Desenvolvimento diário'!$Q:$Q,$B46,'Desenvolvimento diário'!$P:$P,$F46,'Desenvolvimento diário'!$R:$R,"Não") -> 0 | R46: =SUM(P46:Q46) -> 0 | S46: =O46-R46 -> 0 | T46: =IFERROR(R46/O46,0) -> 0
A47: =A46 -> 2 | B47: =VLOOKUP($A47,Controle!$B$4:$F$68,2,FALSE) -> Diamantina 2 | C47: =VLOOKUP($A47,Controle!$B$4:$F$68,3,FALSE) -> MORI GERACAO II | D47: =VLOOKUP($A47,Controle!$B$4:$F$68,4,FALSE) -> Mori II | E47: =VLOOKUP($A47,Controle!$B$4:$F$68,5,FALSE) -> 3 | F47: =F12 -> Desenvolvimento de projeto - Projetos - Executivos | G47: =VLOOKUP($A47,Controle!$B$4:$G$68,6,FALSE) -> Mori | H47: Enersolar | I47: Feito com a GLD | J47: 0 | K47: 0 | L47: 0 | M47: 0 | N47: 0 | O47: =SUM(I47:N47) -> 0 | P47: =SUMIFS('Desenvolvimento diário'!$H:$H,'Desenvolvimento diário'!$Q:$Q,$B47,'Desenvolvimento diário'!$P:$P,$F47,'Desenvolvimento diário'!$R:$R,"Sim") -> 0 | Q47: =SUMIFS('Desenvolvimento diário'!$H:$H,'Desenvolvimento diário'!$Q:$Q,$B47,'Desenvolvimento diário'!$P:$P,$F47,'Desenvolvimento diário'!$R:$R,"Não") -> 0 | R47: =SUM(P47:Q47) -> 0 | S47: =O47-R47 -> 0 | T47: =IFERROR(R47/O47,0) -> 0
A48: =A47 -> 2 | B48: =VLOOKUP($A48,Controle!$B$4:$F$68,2,FALSE) -> Diamantina 2 | C48: =VLOOKUP($A48,Controle!$B$4:$F$68,3,FALSE) -> MORI GERACAO II | D48: =VLOOKUP($A48,Controle!$B$4:$F$68,4,FALSE) -> Mori II | E48: =VLOOKUP($A48,Controle!$B$4:$F$68,5,FALSE) -> 3 | F48: =F13 -> Desenvolvimento de projeto - Projetos Básica | G48: =VLOOKUP($A48,Controle!$B$4:$G$68,6,FALSE) -> Mori | H48: 0 | I48: 0 | J48: 0 | K48: 0 | L48: 0 | M48: 0 | N48: 0 | O48: =SUM(I48:N48) -> 0 | P48: =SUMIFS('Desenvolvimento diário'!$H:$H,'Desenvolvimento diário'!$Q:$Q,$B48,'Desenvolvimento diário'!$P:$P,$F48,'Desenvolvimento diário'!$R:$R,"Sim") -> 0 | Q48: =SUMIFS('Desenvolvimento diário'!$H:$H,'Desenvolvimento diário'!$Q:$Q,$B48,'Desenvolvimento diário'!$P:$P,$F48,'Desenvolvimento diário'!$R:$R,"Não") -> 0 | R48: =SUM(P48:Q48) -> 0 | S48: =O48-R48 -> 0 | T48: =IFERROR(R48/O48,0) -> 0
A49: =A48 -> 2 | B49: =VLOOKUP($A49,Controle!$B$4:$F$68,2,FALSE) -> Diamantina 2 | C49: =VLOOKUP($A49,Controle!$B$4:$F$68,3,FALSE) -> MORI GERACAO II | D49: =VLOOKUP($A49,Controle!$B$4:$F$68,4,FALSE) -> Mori II | E49: =VLOOKUP($A49,Controle!$B$4:$F$68,5,FALSE) -> 3 | F49: =F14 -> Desenvolvimento de projeto - Projetos Detalhada | G49: =VLOOKUP($A49,Controle!$B$4:$G$68,6,FALSE) -> Mori | H49: GLD | I49: 93783 | J49: 34676.16 | K49: 0 | L49: 0 | M49: 0 | N49: 0 | O49: =SUM(I49:N49) -> 128459.16 | P49: =SUMIFS('Desenvolvimento diário'!$H:$H,'Desenvolvimento diário'!$Q:$Q,$B49,'Desenvolvimento diário'!$P:$P,$F49,'Desenvolvimento diário'!$R:$R,"Sim") -> 0 | Q49: =SUMIFS('Desenvolvimento diário'!$H:$H,'Desenvolvimento diário'!$Q:$Q,$B49,'Desenvolvimento diário'!$P:$P,$F49,'Desenvolvimento diário'!$R:$R,"Não") -> 128459.16 | R49: =SUM(P49:Q49) -> 128459.16 | S49: =O49-R49 -> 0 | T49: =IFERROR(R49/O49,0) -> 1
A50: =A49 -> 2 | B50: =VLOOKUP($A50,Controle!$B$4:$F$68,2,FALSE) -> Diamantina 2 | C50: =VLOOKUP($A50,Controle!$B$4:$F$68,3,FALSE) -> MORI GERACAO II | D50: =VLOOKUP($A50,Controle!$B$4:$F$68,4,FALSE) -> Mori II | E50: =VLOOKUP($A50,Controle!$B$4:$F$68,5,FALSE) -> 3 | F50: =F15 -> Desenvolvimento de projeto - Ambiental / Outros | G50: =VLOOKUP($A50,Controle!$B$4:$G$68,6,FALSE) -> Mori | H50: Varios | I50: =R50 -> 163687.34 | J50: 0 | K50: 0 | L50: 0 | M50: 0 | N50: 0 | O50: =SUM(I50:N50) -> 163687.34 | P50: =SUMIFS('Desenvolvimento diário'!$H:$H,'Desenvolvimento diário'!$Q:$Q,$B50,'Desenvolvimento diário'!$P:$P,$F50,'Desenvolvimento diário'!$R:$R,"Sim") -> 0 | Q50: =SUMIFS('Desenvolvimento diário'!$H:$H,'Desenvolvimento diário'!$Q:$Q,$B50,'Desenvolvimento diário'!$P:$P,$F50,'Desenvolvimento diário'!$R:$R,"Não") -> 163687.34 | R50: =SUM(P50:Q50) -> 163687.34 | S50: =O50-R50 -> 0 | T50: =IFERROR(R50/O50,0) -> 1
A51: =A50 -> 2 | B51: =VLOOKUP($A51,Controle!$B$4:$F$68,2,FALSE) -> Diamantina 2 | C51: =VLOOKUP($A51,Controle!$B$4:$F$68,3,FALSE) -> MORI GERACAO II | D51: =VLOOKUP($A51,Controle!$B$4:$F$68,4,FALSE) -> Mori II | E51: =VLOOKUP($A51,Controle!$B$4:$F$68,5,FALSE) -> 3 | F51: =F16 -> Desenvolvimento de projeto - Coordenograma | G51: =VLOOKUP($A51,Controle!$B$4:$G$68,6,FALSE) -> Mori | H51: PROJETTI | I51: 6206.9 | J51: 0 | K51: 0 | L51: 0 | M51: 0 | N51: 0 | O51: =SUM(I51:N51) -> 6206.9 | P51: =SUMIFS('Desenvolvimento diário'!$H:$H,'Desenvolvimento diário'!$Q:$Q,$B51,'Desenvolvimento diário'!$P:$P,$F51,'Desenvolvimento diário'!$R:$R,"Sim") -> 0 | Q51: =SUMIFS('Desenvolvimento diário'!$H:$H,'Desenvolvimento diário'!$Q:$Q,$B51,'Desenvolvimento diário'!$P:$P,$F51,'Desenvolvimento diário'!$R:$R,"Não") -> 6206.9 | R51: =SUM(P51:Q51) -> 6206.9 | S51: =O51-R51 -> 0 | T51: =IFERROR(R51/O51,0) -> 1
A52: =A51 -> 2 | B52: =VLOOKUP($A52,Controle!$B$4:$F$68,2,FALSE) -> Diamantina 2 | C52: =VLOOKUP($A52,Controle!$B$4:$F$68,3,FALSE) -> MORI GERACAO II | D52: =VLOOKUP($A52,Controle!$B$4:$F$68,4,FALSE) -> Mori II | E52: =VLOOKUP($A52,Controle!$B$4:$F$68,5,FALSE) -> 3 | F52: =F17 -> Sistemas de Monitoramento - Supervisório | G52: =VLOOKUP($A52,Controle!$B$4:$G$68,6,FALSE) -> Mori | H52: ATI | I52: 136155 | K52: 0 | L52: 0 | M52: 0 | N52: 0 | O52: =SUM(I52:N52) -> 136155 | P52: =SUMIFS('Desenvolvimento diário'!$H:$H,'Desenvolvimento diário'!$Q:$Q,$B52,'Desenvolvimento diário'!$P:$P,$F52,'Desenvolvimento diário'!$R:$R,"Sim") -> 5821.02 | Q52: =SUMIFS('Desenvolvimento diário'!$H:$H,'Desenvolvimento diário'!$Q:$Q,$B52,'Desenvolvimento diário'!$P:$P,$F52,'Desenvolvimento diário'!$R:$R,"Não") -> 130333.98 | R52: =SUM(P52:Q52) -> 136155 | S52: =O52-R52 -> 0 | T52: =IFERROR(R52/O52,0) -> 1
A53: =A52 -> 2 | B53: =VLOOKUP($A53,Controle!$B$4:$F$68,2,FALSE) -> Diamantina 2 | C53: =VLOOKUP($A53,Controle!$B$4:$F$68,3,FALSE) -> MORI GERACAO II | D53: =VLOOKUP($A53,Controle!$B$4:$F$68,4,FALSE) -> Mori II | E53: =VLOOKUP($A53,Controle!$B$4:$F$68,5,FALSE) -> 3 | F53: =F18 -> Sistemas de Monitoramento - Estações Solarimétricas | G53: =VLOOKUP($A53,Controle!$B$4:$G$68,6,FALSE) -> Mori | H53: Hukseflux | I53: 48276.516 | J53: 0 | K53: 0 | L53: 0 | M53: 0 | N53: 0 | O53: =SUM(I53:N53) -> 48276.516 | P53: =SUMIFS('Desenvolvimento diário'!$H:$H,'Desenvolvimento diário'!$Q:$Q,$B53,'Desenvolvimento diário'!$P:$P,$F53,'Desenvolvimento diário'!$R:$R,"Sim") -> 0 | Q53: =SUMIFS('Desenvolvimento diário'!$H:$H,'Desenvolvimento diário'!$Q:$Q,$B53,'Desenvolvimento diário'!$P:$P,$F53,'Desenvolvimento diário'!$R:$R,"Não") -> 48276.516 | R53: =SUM(P53:Q53) -> 48276.516 | S53: =O53-R53 -> 0 | T53: =IFERROR(R53/O53,0) -> 1
A54: =A53 -> 2 | B54: =VLOOKUP($A54,Controle!$B$4:$F$68,2,FALSE) -> Diamantina 2 | C54: =VLOOKUP($A54,Controle!$B$4:$F$68,3,FALSE) -> MORI GERACAO II | D54: =VLOOKUP($A54,Controle!$B$4:$F$68,4,FALSE) -> Mori II | E54: =VLOOKUP($A54,Controle!$B$4:$F$68,5,FALSE) -> 3 | F54: =F19 -> Sistemas de Monitoramento - CFTV | G54: =VLOOKUP($A54,Controle!$B$4:$G$68,6,FALSE) -> Mori | H54: Maxvision | I54: 261668.28 | J54: 0 | K54: 0 | L54: 0 | M54: 0 | N54: 0 | O54: =SUM(I54:N54) -> 261668.28 | P54: =SUMIFS('Desenvolvimento diário'!$H:$H,'Desenvolvimento diário'!$Q:$Q,$B54,'Desenvolvimento diário'!$P:$P,$F54,'Desenvolvimento diário'!$R:$R,"Sim") -> 0 | Q54: =SUMIFS('Desenvolvimento diário'!$H:$H,'Desenvolvimento diário'!$Q:$Q,$B54,'Desenvolvimento diário'!$P:$P,$F54,'Desenvolvimento diário'!$R:$R,"Não") -> 261668.28 | R54: =SUM(P54:Q54) -> 261668.28 | S54: =O54-R54 -> 0 | T54: =IFERROR(R54/O54,0) -> 1
A55: =A54 -> 2 | B55: =VLOOKUP($A55,Controle!$B$4:$F$68,2,FALSE) -> Diamantina 2 | C55: =VLOOKUP($A55,Controle!$B$4:$F$68,3,FALSE) -> MORI GERACAO II | D55: =VLOOKUP($A55,Controle!$B$4:$F$68,4,FALSE) -> Mori II | E55: =VLOOKUP($A55,Controle!$B$4:$F$68,5,FALSE) -> 3 | F55: =F20 -> Serviços Auxiliares - Drenagem | G55: =VLOOKUP($A55,Controle!$B$4:$G$68,6,FALSE) -> Mori | H55: ORCI / Engetela | I55: 686107.5 | J55: 164771.5 | K55: 14900 | L55: 1482339.8 | M55: 0 | N55: 0 | O55: =SUM(I55:N55) -> 2348118.8 | P55: =SUMIFS('Desenvolvimento diário'!$H:$H,'Desenvolvimento diário'!$Q:$Q,$B55,'Desenvolvimento diário'!$P:$P,$F55,'Desenvolvimento diário'!$R:$R,"Sim") -> 686107.5 | Q55: =SUMIFS('Desenvolvimento diário'!$H:$H,'Desenvolvimento diário'!$Q:$Q,$B55,'Desenvolvimento diário'!$P:$P,$F55,'Desenvolvimento diário'!$R:$R,"Não") -> 1604811.2 | R55: =SUM(P55:Q55) -> 2290918.8 | S55: =O55-R55 -> 57200 | T55: =IFERROR(R55/O55,0) -> 0.97564007 | U55: S | V55: Drenagem Orci Aprovada
A56: =A55 -> 2 | B56: =VLOOKUP($A56,Controle!$B$4:$F$68,2,FALSE) -> Diamantina 2 | C56: =VLOOKUP($A56,Controle!$B$4:$F$68,3,FALSE) -> MORI GERACAO II | D56: =VLOOKUP($A56,Controle!$B$4:$F$68,4,FALSE) -> Mori II | E56: =VLOOKUP($A56,Controle!$B$4:$F$68,5,FALSE) -> 3 | F56: =F21 -> Serviços Auxiliares - Terraplanagem | G56: =VLOOKUP($A56,Controle!$B$4:$G$68,6,FALSE) -> Mori | H56: ORCI | I56: 1205985.6 | K56: 0 | L56: 0 | M56: 0 | N56: 0 | O56: =SUM(I56:N56) -> 1205985.6 | P56: =SUMIFS('Desenvolvimento diário'!$H:$H,'Desenvolvimento diário'!$Q:$Q,$B56,'Desenvolvimento diário'!$P:$P,$F56,'Desenvolvimento diário'!$R:$R,"Sim") -> 780000 | Q56: =SUMIFS('Desenvolvimento diário'!$H:$H,'Desenvolvimento diário'!$Q:$Q,$B56,'Desenvolvimento diário'!$P:$P,$F56,'Desenvolvimento diário'!$R:$R,"Não")-(0.53) -> 425985.6 | R56: =SUM(P56:Q56) -> 1205985.6 | S56: =O56-R56 -> 0 | T56: =IFERROR(R56/O56,0) -> 1
A57: =A56 -> 2 | B57: =VLOOKUP($A57,Controle!$B$4:$F$68,2,FALSE) -> Diamantina 2 | C57: =VLOOKUP($A57,Controle!$B$4:$F$68,3,FALSE) -> MORI GERACAO II | D57: =VLOOKUP($A57,Controle!$B$4:$F$68,4,FALSE) -> Mori II | E57: =VLOOKUP($A57,Controle!$B$4:$F$68,5,FALSE) -> 3 | F57: =F22 -> Serviços Auxiliares - Supressão Vegetal | G57: =VLOOKUP($A57,Controle!$B$4:$G$68,6,FALSE) -> Mori | H57: Rima | I57: 50000 | J57: =23665.47-0.02 -> 23665.45 | K57: 0 | L57: 0 | M57: 0 | N57: 0 | O57: =SUM(I57:N57) -> 73665.45 | P57: =SUMIFS('Desenvolvimento diário'!$H:$H,'Desenvolvimento diário'!$Q:$Q,$B57,'Desenvolvimento diário'!$P:$P,$F57,'Desenvolvimento diário'!$R:$R,"Sim") -> 2366.54 | Q57: =SUMIFS('Desenvolvimento diário'!$H:$H,'Desenvolvimento diário'!$Q:$Q,$B57,'Desenvolvimento diário'!$P:$P,$F57,'Desenvolvimento diário'!$R:$R,"Não") -> 71298.91 | R57: =SUM(P57:Q57) -> 73665.45 | S57: =O57-R57 -> 0 | T57: =IFERROR(R57/O57,0) -> 1
A58: =A57 -> 2 | B58: =VLOOKUP($A58,Controle!$B$4:$F$68,2,FALSE) -> Diamantina 2 | C58: =VLOOKUP($A58,Controle!$B$4:$F$68,3,FALSE) -> MORI GERACAO II | D58: =VLOOKUP($A58,Controle!$B$4:$F$68,4,FALSE) -> Mori II | E58: =VLOOKUP($A58,Controle!$B$4:$F$68,5,FALSE) -> 3 | F58: =F23 -> RDR-Rede de Distribuição Rural | G58: =VLOOKUP($A58,Controle!$B$4:$G$68,6,FALSE) -> Mori | H58: 0 | I58: 0 | J58: 0 | K58: 0 | L58: 0 | M58: 0 | N58: 0 | O58: =SUM(I58:N58) -> 0 | P58: =SUMIFS('Desenvolvimento diário'!$H:$H,'Desenvolvimento diário'!$Q:$Q,$B58,'Desenvolvimento diário'!$P:$P,$F58,'Desenvolvimento diário'!$R:$R,"Sim") -> 0 | Q58: =SUMIFS('Desenvolvimento diário'!$H:$H,'Desenvolvimento diário'!$Q:$Q,$B58,'Desenvolvimento diário'!$P:$P,$F58,'Desenvolvimento diário'!$R:$R,"Não") -> 0 | R58: =SUM(P58:Q58) -> 0 | S58: =O58-R58 -> 0 | T58: =IFERROR(R58/O58,0) -> 0
A59: =A58 -> 2 | B59: =VLOOKUP($A59,Controle!$B$4:$F$68,2,FALSE) -> Diamantina 2 | C59: =VLOOKUP($A59,Controle!$B$4:$F$68,3,FALSE) -> MORI GERACAO II | D59: =VLOOKUP($A59,Controle!$B$4:$F$68,4,FALSE) -> Mori II | E59: =VLOOKUP($A59,Controle!$B$4:$F$68,5,FALSE) -> 3 | F59: =F24 -> Escopo COMERC | G59: =VLOOKUP($A59,Controle!$B$4:$G$68,6,FALSE) -> Mori | H59: 0 | I59: 495077.31 | J59: 46000 | L59: 0 | M59: 0 | N59: 0 | O59: =SUM(I59:N59) -> 541077.31 | P59: =SUMIFS('Desenvolvimento diário'!$H:$H,'Desenvolvimento diário'!$Q:$Q,$B59,'Desenvolvimento diário'!$P:$P,$F59,'Desenvolvimento diário'!$R:$R,"Sim") -> 1459 | Q59: =SUMIFS('Desenvolvimento diário'!$H:$H,'Desenvolvimento diário'!$Q:$Q,$B59,'Desenvolvimento diário'!$P:$P,$F59,'Desenvolvimento diário'!$R:$R,"Não") -> 494617.09 | R59: =SUM(P59:Q59) -> 496076.09 | S59: =O59-R59 -> 45001.22 | T59: =IFERROR(R59/O59,0) -> 0.91683033 | U59: S | V59: Escopo Comerc
A60: =A59 -> 2 | B60: =VLOOKUP($A60,Controle!$B$4:$F$68,2,FALSE) -> Diamantina 2 | C60: =VLOOKUP($A60,Controle!$B$4:$F$68,3,FALSE) -> MORI GERACAO II | D60: =VLOOKUP($A60,Controle!$B$4:$F$68,4,FALSE) -> Mori II | E60: =VLOOKUP($A60,Controle!$B$4:$F$68,5,FALSE) -> 3 | F60: =F25 -> Escopo COMERC - Segurança | G60: =VLOOKUP($A60,Controle!$B$4:$G$68,6,FALSE) -> Mori | H60: 0 | I60: =R60 -> 135780 | J60: 0 | K60: 0 | L60: 0 | M60: 0 | N60: 0 | O60: =SUM(I60:N60) -> 135780 | P60: =SUMIFS('Desenvolvimento diário'!$H:$H,'Desenvolvimento diário'!$Q:$Q,$B60,'Desenvolvimento diário'!$P:$P,$F60,'Desenvolvimento diário'!$R:$R,"Sim") -> 0 | Q60: =SUMIFS('Desenvolvimento diário'!$H:$H,'Desenvolvimento diário'!$Q:$Q,$B60,'Desenvolvimento diário'!$P:$P,$F60,'Desenvolvimento diário'!$R:$R,"Não") -> 135780 | R60: =SUM(P60:Q60) -> 135780 | S60: =O60-R60 -> 0 | T60: =IFERROR(R60/O60,0) -> 1
A61: =A60 -> 2 | B61: =VLOOKUP($A61,Controle!$B$4:$F$68,2,FALSE) -> Diamantina 2 | C61: =VLOOKUP($A61,Controle!$B$4:$F$68,3,FALSE) -> MORI GERACAO II | D61: =VLOOKUP($A61,Controle!$B$4:$F$68,4,FALSE) -> Mori II | E61: =VLOOKUP($A61,Controle!$B$4:$F$68,5,FALSE) -> 3 | F61: =F26 -> Conexão MT - Obras Transferencia | G61: =VLOOKUP($A61,Controle!$B$4:$G$68,6,FALSE) -> Mori | H61: Engeluz | I61: 3665456.7 | J61: 0 | K61: 0 | L61: 0 | M61: 0 | N61: 0 | O61: =SUM(I61:N61) -> 3665456.7 | P61: =SUMIFS('Desenvolvimento diário'!$H:$H,'Desenvolvimento diário'!$Q:$Q,$B61,'Desenvolvimento diário'!$P:$P,$F61,'Desenvolvimento diário'!$R:$R,"Sim") -> 1743736.1 | Q61: =SUMIFS('Desenvolvimento diário'!$H:$H,'Desenvolvimento diário'!$Q:$Q,$B61,'Desenvolvimento diário'!$P:$P,$F61,'Desenvolvimento diário'!$R:$R,"Não") -> 1921720.6 | R61: =SUM(P61:Q61) -> 3665456.7 | S61: =O61-R61 -> 0 | T61: =IFERROR(R61/O61,0) -> 1
A62: =A61 -> 2 | B62: =VLOOKUP($A62,Controle!$B$4:$F$68,2,FALSE) -> Diamantina 2 | C62: =VLOOKUP($A62,Controle!$B$4:$F$68,3,FALSE) -> MORI GERACAO II | D62: =VLOOKUP($A62,Controle!$B$4:$F$68,4,FALSE) -> Mori II | E62: =VLOOKUP($A62,Controle!$B$4:$F$68,5,FALSE) -> 3 | F62: =F27 -> Bases de Contaniers | G62: =VLOOKUP($A62,Controle!$B$4:$G$68,6,FALSE) -> Mori | H62: 0 | I62: 0 | J62: 0 | K62: 0 | L62: 0 | M62: 0 | N62: 0 | O62: =SUM(I62:N62) -> 0 | P62: =SUMIFS('Desenvolvimento diário'!$H:$H,'Desenvolvimento diário'!$Q:$Q,$B62,'Desenvolvimento diário'!$P:$P,$F62,'Desenvolvimento diário'!$R:$R,"Sim") -> 0 | Q62: =SUMIFS('Desenvolvimento diário'!$H:$H,'Desenvolvimento diário'!$Q:$Q,$B62,'Desenvolvimento diário'!$P:$P,$F62,'Desenvolvimento diário'!$R:$R,"Não") -> 0 | R62: =SUM(P62:Q62) -> 0 | S62: =O62-R62 -> 0 | T62: =IFERROR(R62/O62,0) -> 0
A63: =A62 -> 2 | B63: =VLOOKUP($A63,Controle!$B$4:$F$68,2,FALSE) -> Diamantina 2 | C63: =VLOOKUP($A63,Controle!$B$4:$F$68,3,FALSE) -> MORI GERACAO II | D63: =VLOOKUP($A63,Controle!$B$4:$F$68,4,FALSE) -> Mori II | E63: =VLOOKUP($A63,Controle!$B$4:$F$68,5,FALSE) -> 3 | F63: =F28 -> Construção - Serviços de Construção - Ase Engenharia | G63: =VLOOKUP($A63,Controle!$B$4:$G$68,6,FALSE) -> Mori | H63: 0 | I63: 0 | J63: 0 | K63: 0 | L63: 0 | M63: 0 | N63: 0 | O63: =SUM(I63:N63) -> 0 | P63: =SUMIFS('Desenvolvimento diário'!$H:$H,'Desenvolvimento diário'!$Q:$Q,$B63,'Desenvolvimento diário'!$P:$P,$F63,'Desenvolvimento diário'!$R:$R,"Sim") -> 0 | Q63: =SUMIFS('Desenvolvimento diário'!$H:$H,'Desenvolvimento diário'!$Q:$Q,$B63,'Desenvolvimento diário'!$P:$P,$F63,'Desenvolvimento diário'!$R:$R,"Não") -> 0 | R63: =SUM(P63:Q63) -> 0 | S63: =O63-R63 -> 0 | T63: =IFERROR(R63/O63,0) -> 0
A64: =A63 -> 2 | B64: =VLOOKUP($A64,Controle!$B$4:$F$68,2,FALSE) -> Diamantina 2 | C64: =VLOOKUP($A64,Controle!$B$4:$F$68,3,FALSE) -> MORI GERACAO II | D64: =VLOOKUP($A64,Controle!$B$4:$F$68,4,FALSE) -> Mori II | E64: =VLOOKUP($A64,Controle!$B$4:$F$68,5,FALSE) -> 3 | F64: =F29 -> Full EPC - Contrato Sobressalentes | G64: =VLOOKUP($A64,Controle!$B$4:$G$68,6,FALSE) -> Mori | H64: 0 | I64: 0 | J64: 0 | K64: 0 | L64: 0 | M64: 0 | N64: 0 | O64: =SUM(I64:N64) -> 0 | P64: =SUMIFS('Desenvolvimento diário'!$H:$H,'Desenvolvimento diário'!$Q:$Q,$B64,'Desenvolvimento diário'!$P:$P,$F64,'Desenvolvimento diário'!$R:$R,"Sim") -> 0 | Q64: =SUMIFS('Desenvolvimento diário'!$H:$H,'Desenvolvimento diário'!$Q:$Q,$B64,'Desenvolvimento diário'!$P:$P,$F64,'Desenvolvimento diário'!$R:$R,"Não") -> 0 | R64: =SUM(P64:Q64) -> 0 | S64: =O64-R64 -> 0 | T64: =IFERROR(R64/O64,0) -> 0
A65: =A64 -> 2 | B65: =VLOOKUP($A65,Controle!$B$4:$F$68,2,FALSE) -> Diamantina 2 | C65: =VLOOKUP($A65,Controle!$B$4:$F$68,3,FALSE) -> MORI GERACAO II | D65: =VLOOKUP($A65,Controle!$B$4:$F$68,4,FALSE) -> Mori II | E65: =VLOOKUP($A65,Controle!$B$4:$F$68,5,FALSE) -> 3 | F65: =F30 -> Construção - Serviços de Construção - NOVA MORADA | G65: =VLOOKUP($A65,Controle!$B$4:$G$68,6,FALSE) -> Mori | H65: 0 | I65: 0 | J65: 0 | K65: 0 | L65: 0 | M65: 0 | N65: 0 | O65: =SUM(I65:N65) -> 0 | P65: =SUMIFS('Desenvolvimento diário'!$H:$H,'Desenvolvimento diário'!$Q:$Q,$B65,'Desenvolvimento diário'!$P:$P,$F65,'Desenvolvimento diário'!$R:$R,"Sim") -> 0 | Q65: =SUMIFS('Desenvolvimento diário'!$H:$H,'Desenvolvimento diário'!$Q:$Q,$B65,'Desenvolvimento diário'!$P:$P,$F65,'Desenvolvimento diário'!$R:$R,"Não") -> 0 | R65: =SUM(P65:Q65) -> 0 | S65: =O65-R65 -> 0 | T65: =IFERROR(R65/O65,0) -> 0
A66: =A65 -> 2 | B66: =VLOOKUP($A66,Controle!$B$4:$F$68,2,FALSE) -> Diamantina 2 | C66: =VLOOKUP($A66,Controle!$B$4:$F$68,3,FALSE) -> MORI GERACAO II | D66: =VLOOKUP($A66,Controle!$B$4:$F$68,4,FALSE) -> Mori II | E66: =VLOOKUP($A66,Controle!$B$4:$F$68,5,FALSE) -> 3 | F66: =F31 -> Equipamentos Curva A - Contrato Sobressalentes - SETTA | G66: =VLOOKUP($A66,Controle!$B$4:$G$68,6,FALSE) -> Mori | H66: 0 | I66: 0 | J66: 0 | K66: 0 | L66: 0 | M66: 0 | N66: 0 | O66: =SUM(I66:N66) -> 0 | P66: =SUMIFS('Desenvolvimento diário'!$H:$H,'Desenvolvimento diário'!$Q:$Q,$B66,'Desenvolvimento diário'!$P:$P,$F66,'Desenvolvimento diário'!$R:$R,"Sim") -> 0 | Q66: =SUMIFS('Desenvolvimento diário'!$H:$H,'Desenvolvimento diário'!$Q:$Q,$B66,'Desenvolvimento diário'!$P:$P,$F66,'Desenvolvimento diário'!$R:$R,"Não") -> 0 | R66: =SUM(P66:Q66) -> 0 | S66: =O66-R66 -> 0 | T66: =IFERROR(R66/O66,0) -> 0
A67: =A66 -> 2 | B67: =VLOOKUP($A67,Controle!$B$4:$F$68,2,FALSE) -> Diamantina 2 | C67: =VLOOKUP($A67,Controle!$B$4:$F$68,3,FALSE) -> MORI GERACAO II | D67: =VLOOKUP($A67,Controle!$B$4:$F$68,4,FALSE) -> Mori II | E67: =VLOOKUP($A67,Controle!$B$4:$F$68,5,FALSE) -> 3 | F67: =F32 -> Equipamentos Curva A - Contrato Sobressalentes - Arctech | G67: =VLOOKUP($A67,Controle!$B$4:$G$68,6,FALSE) -> Mori | H67: 0 | I67: 0 | J67: 0 | K67: 0 | L67: 0 | M67: 0 | N67: 0 | O67: =SUM(I67:N67) -> 0 | P67: =SUMIFS('Desenvolvimento diário'!$H:$H,'Desenvolvimento diário'!$Q:$Q,$B67,'Desenvolvimento diário'!$P:$P,$F67,'Desenvolvimento diário'!$R:$R,"Sim") -> 0 | Q67: =SUMIFS('Desenvolvimento diário'!$H:$H,'Desenvolvimento diário'!$Q:$Q,$B67,'Desenvolvimento diário'!$P:$P,$F67,'Desenvolvimento diário'!$R:$R,"Não") -> 0 | R67: =SUM(P67:Q67) -> 0 | S67: =O67-R67 -> 0 | T67: =IFERROR(R67/O67,0) -> 0
A68: =A67 -> 2 | B68: =VLOOKUP($A68,Controle!$B$4:$F$68,2,FALSE) -> Diamantina 2 | C68: =VLOOKUP($A68,Controle!$B$4:$F$68,3,FALSE) -> MORI GERACAO II | D68: =VLOOKUP($A68,Controle!$B$4:$F$68,4,FALSE) -> Mori II | E68: =VLOOKUP($A68,Controle!$B$4:$F$68,5,FALSE) -> 3 | F68: =F33 -> Equipamentos Curva A - Contrato Sobressalentes - Romagnole | G68: =VLOOKUP($A68,Controle!$B$4:$G$68,6,FALSE) -> Mori | H68: 0 | I68: 0 | J68: 0 | K68: 0 | L68: 0 | M68: 0 | N68: 0 | O68: =SUM(I68:N68) -> 0 | P68: =SUMIFS('Desenvolvimento diário'!$H:$H,'Desenvolvimento diário'!$Q:$Q,$B68,'Desenvolvimento diário'!$P:$P,$F68,'Desenvolvimento diário'!$R:$R,"Sim") -> 0 | Q68: =SUMIFS('Desenvolvimento diário'!$H:$H,'Desenvolvimento diário'!$Q:$Q,$B68,'Desenvolvimento diário'!$P:$P,$F68,'Desenvolvimento diário'!$R:$R,"Não") -> 0 | R68: =SUM(P68:Q68) -> 0 | S68: =O68-R68 -> 0 | T68: =IFERROR(R68/O68,0) -> 0
A69: =A66 -> 2 | B69: =VLOOKUP($A69,Controle!$B$4:$F$68,2,FALSE) -> Diamantina 2 | C69: =VLOOKUP($A69,Controle!$B$4:$F$68,3,FALSE) -> MORI GERACAO II | D69: =VLOOKUP($A69,Controle!$B$4:$F$68,4,FALSE) -> Mori II | E69: =VLOOKUP($A69,Controle!$B$4:$F$68,5,FALSE) -> 3 | F69: =F34 -> GOS FLORESTAL - (PRAD - Recuperação Area Ambiental) | G69: =VLOOKUP($A69,Controle!$B$4:$G$68,6,FALSE) -> Mori | H69: Gos Florestal | I69: 339840 | K69: 0 | L69: 0 | M69: 0 | N69: 0 | O69: =SUM(I69:N69) -> 339840 | P69: =SUMIFS('Desenvolvimento diário'!$H:$H,'Desenvolvimento diário'!$Q:$Q,$B69,'Desenvolvimento diário'!$P:$P,$F69,'Desenvolvimento diário'!$R:$R,"Sim") -> 0 | Q69: =SUMIFS('Desenvolvimento diário'!$H:$H,'Desenvolvimento diário'!$Q:$Q,$B69,'Desenvolvimento diário'!$P:$P,$F69,'Desenvolvimento diário'!$R:$R,"Não") -> 339840 | R69: =SUM(P69:Q69) -> 339840 | S69: =O69-R69 -> 0 | T69: =IFERROR(R69/O69,0) -> 1 | U69: S | V69: GOS - Esse refere-se ao Contrato aprovado junto com acerto das Drenagens
A70: =A67 -> 2 | B70: =VLOOKUP($A70,Controle!$B$4:$F$68,2,FALSE) -> Diamantina 2 | C70: =VLOOKUP($A70,Controle!$B$4:$F$68,3,FALSE) -> MORI GERACAO II | D70: =VLOOKUP($A70,Controle!$B$4:$F$68,4,FALSE) -> Mori II | E70: =VLOOKUP($A70,Controle!$B$4:$F$68,5,FALSE) -> 3 | F70: =F35 -> Cercamento das bacias de contenção ciclo 2 | G70: =VLOOKUP($A70,Controle!$B$4:$G$68,6,FALSE) -> Mori | H70: A Definir | K70: 0 | L70: 0 | M70: 0 | N70: 0 | O70: =SUM(I70:N70) -> 0 | P70: =SUMIFS('Desenvolvimento diário'!$H:$H,'Desenvolvimento diário'!$Q:$Q,$B70,'Desenvolvimento diário'!$P:$P,$F70,'Desenvolvimento diário'!$R:$R,"Sim") -> 0 | Q70: =SUMIFS('Desenvolvimento diário'!$H:$H,'Desenvolvimento diário'!$Q:$Q,$B70,'Desenvolvimento diário'!$P:$P,$F70,'Desenvolvimento diário'!$R:$R,"Não") -> 0 | R70: =SUM(P70:Q70) -> 0 | S70: =O70-R70 -> 0 | T70: =IFERROR(R70/O70,0) -> 0 | U70: S | V70: Cercamento das bacias de contenção ciclo 2
A71: =A68 -> 2 | B71: =B68 -> Diamantina 2 | C71: =C68 -> MORI GERACAO II | D71: =D68 -> Mori II | E71: =E68 -> 3 | F71: Total | G71: =G68 -> Mori | I71: =SUBTOTAL(9,I37:I70) -> 686107.5 | J71: =SUBTOTAL(9,J37:J70) -> 164771.5 | K71: =SUBTOTAL(9,K37:K70) -> 14900 | L71: =SUBTOTAL(9,L37:L70) -> 1482339.8 | M71: =SUBTOTAL(9,M37:M70) -> 0 | N71: =SUBTOTAL(9,N37:N70) -> 0 | O71: =SUBTOTAL(9,O37:O70) -> 2348118.8 | P71: =SUBTOTAL(9,P37:P70) -> 686107.5 | ... S71: =SUBTOTAL(9,S37:S70) -> 57200 | T71: =IFERROR(R71/O71,0) -> 0.97564007 | U71: =SUBTOTAL(9,U37:U70) -> 0
A72: =A37+1 -> 3 | B72: =VLOOKUP($A72,Controle!$B$4:$F$68,2,FALSE) -> Frei Inocêncio 1 | C72: =VLOOKUP($A72,Controle!$B$4:$F$68,3,FALSE) -> MORI GERACAO II | D72: =VLOOKUP($A72,Controle!$B$4:$F$68,4,FALSE) -> Mori II | E72: =VLOOKUP($A72,Controle!$B$4:$F$68,5,FALSE) -> Weg | F72: =F37 -> Conexão AT - Obras | G72: =VLOOKUP($A72,Controle!$B$4:$G$68,6,FALSE) -> Mori | H72: MBA | I72: 460000 | J72: 0 | K72: 0 | L72: 0 | M72: 0 | N72: 0 | O72: =SUM(I72:N72) -> 460000 | P72: =SUMIFS('Desenvolvimento diário'!$H:$H,'Desenvolvimento diário'!$Q:$Q,$B72,'Desenvolvimento diário'!$P:$P,$F72,'Desenvolvimento diário'!$R:$R,"Sim") -> 86000 | Q72: =SUMIFS('Desenvolvimento diário'!$H:$H,'Desenvolvimento diário'!$Q:$Q,$B72,'Desenvolvimento diário'!$P:$P,$F72,'Desenvolvimento diário'!$R:$R,"Não") -> 374000 | R72: =SUM(P72:Q72) -> 460000 | S72: =O72-R72 -> 0 | T72: =IFERROR(R72/O72,0) -> 1
A73: =A72 -> 3 | B73: =VLOOKUP($A73,Controle!$B$4:$F$68,2,FALSE) -> Frei Inocêncio 1 | C73: =VLOOKUP($A73,Controle!$B$4:$F$68,3,FALSE) -> MORI GERACAO II | D73: =VLOOKUP($A73,Controle!$B$4:$F$68,4,FALSE) -> Mori II | E73: =VLOOKUP($A73,Controle!$B$4:$F$68,5,FALSE) -> Weg | F73: =F38 -> Conexão MT - Obras | G73: =VLOOKUP($A73,Controle!$B$4:$G$68,6,FALSE) -> Mori | H73: MBA | I73: 1425000 | J73: 412000 | K73: 709786 | L73: 0 | M73: 0 | N73: 0 | O73: =SUM(I73:N73) -> 2546786 | P73: =SUMIFS('Desenvolvimento diário'!$H:$H,'Desenvolvimento diário'!$Q:$Q,$B73,'Desenvolvimento diário'!$P:$P,$F73,'Desenvolvimento diário'!$R:$R,"Sim") -> 915361.03 | Q73: =SUMIFS('Desenvolvimento diário'!$H:$H,'Desenvolvimento diário'!$Q:$Q,$B73,'Desenvolvimento diário'!$P:$P,$F73,'Desenvolvimento diário'!$R:$R,"Não") -> 1631425 | R73: =SUM(P73:Q73) -> 2546786 | S73: =O73-R73 -> 0 | T73: =IFERROR(R73/O73,0) -> 1
A74: =A73 -> 3 | B74: =VLOOKUP($A74,Controle!$B$4:$F$68,2,FALSE) -> Frei Inocêncio 1 | C74: =VLOOKUP($A74,Controle!$B$4:$F$68,3,FALSE) -> MORI GERACAO II | D74: =VLOOKUP($A74,Controle!$B$4:$F$68,4,FALSE) -> Mori II | E74: =VLOOKUP($A74,Controle!$B$4:$F$68,5,FALSE) -> Weg | F74: =F39 -> Construção - Serviços de Construção | G74: =VLOOKUP($A74,Controle!$B$4:$G$68,6,FALSE) -> Mori | H74: 0 | I74: 0 | J74: 0 | K74: 0 | L74: 0 | M74: 0 | N74: 0 | O74: =SUM(I74:N74) -> 0 | P74: =SUMIFS('Desenvolvimento diário'!$H:$H,'Desenvolvimento diário'!$Q:$Q,$B74,'Desenvolvimento diário'!$P:$P,$F74,'Desenvolvimento diário'!$R:$R,"Sim") -> 0 | Q74: =SUMIFS('Desenvolvimento diário'!$H:$H,'Desenvolvimento diário'!$Q:$Q,$B74,'Desenvolvimento diário'!$P:$P,$F74,'Desenvolvimento diário'!$R:$R,"Não") -> 0 | R74: =SUM(P74:Q74) -> 0 | S74: =O74-R74 -> 0 | T74: =IFERROR(R74/O74,0) -> 0
A75: =A74 -> 3 | B75: =VLOOKUP($A75,Controle!$B$4:$F$68,2,FALSE) -> Frei Inocêncio 1 | C75: =VLOOKUP($A75,Controle!$B$4:$F$68,3,FALSE) -> MORI GERACAO II | D75: =VLOOKUP($A75,Controle!$B$4:$F$68,4,FALSE) -> Mori II | E75: =VLOOKUP($A75,Controle!$B$4:$F$68,5,FALSE) -> Weg | F75: =F40 -> Construção - Serviços de Construção - Substituição | G75: =VLOOKUP($A75,Controle!$B$4:$G$68,6,FALSE) -> Mori | H75: 0 | I75: 0 | J75: 0 | K75: 0 | L75: 0 | M75: 0 | N75: 0 | O75: =SUM(I75:N75) -> 0 | P75: =SUMIFS('Desenvolvimento diário'!$H:$H,'Desenvolvimento diário'!$Q:$Q,$B75,'Desenvolvimento diário'!$P:$P,$F75,'Desenvolvimento diário'!$R:$R,"Sim") -> 0 | Q75: =SUMIFS('Desenvolvimento diário'!$H:$H,'Desenvolvimento diário'!$Q:$Q,$B75,'Desenvolvimento diário'!$P:$P,$F75,'Desenvolvimento diário'!$R:$R,"Não") -> 0 | R75: =SUM(P75:Q75) -> 0 | S75: =O75-R75 -> 0 | T75: =IFERROR(R75/O75,0) -> 0
A76: =A75 -> 3 | B76: =VLOOKUP($A76,Controle!$B$4:$F$68,2,FALSE) -> Frei Inocêncio 1 | C76: =VLOOKUP($A76,Controle!$B$4:$F$68,3,FALSE) -> MORI GERACAO II | D76: =VLOOKUP($A76,Controle!$B$4:$F$68,4,FALSE) -> Mori II | E76: =VLOOKUP($A76,Controle!$B$4:$F$68,5,FALSE) -> Weg | F76: =F41 -> Construção - RDA Interno | G76: =VLOOKUP($A76,Controle!$B$4:$G$68,6,FALSE) -> Mori | H76: 0 | I76: 0 | J76: 0 | K76: 0 | L76: 0 | M76: 0 | N76: 0 | O76: =SUM(I76:N76) -> 0 | P76: =SUMIFS('Desenvolvimento diário'!$H:$H,'Desenvolvimento diário'!$Q:$Q,$B76,'Desenvolvimento diário'!$P:$P,$F76,'Desenvolvimento diário'!$R:$R,"Sim") -> 0 | Q76: =SUMIFS('Desenvolvimento diário'!$H:$H,'Desenvolvimento diário'!$Q:$Q,$B76,'Desenvolvimento diário'!$P:$P,$F76,'Desenvolvimento diário'!$R:$R,"Não") -> 0 | R76: =SUM(P76:Q76) -> 0 | S76: =O76-R76 -> 0 | T76: =IFERROR(R76/O76,0) -> 0
A77: =A76 -> 3 | B77: =VLOOKUP($A77,Controle!$B$4:$F$68,2,FALSE) -> Frei Inocêncio 1 | C77: =VLOOKUP($A77,Controle!$B$4:$F$68,3,FALSE) -> MORI GERACAO II | D77: =VLOOKUP($A77,Controle!$B$4:$F$68,4,FALSE) -> Mori II | E77: =VLOOKUP($A77,Controle!$B$4:$F$68,5,FALSE) -> Weg | F77: =F42 -> Full EPC - Contrato | G77: =VLOOKUP($A77,Controle!$B$4:$G$68,6,FALSE) -> Mori | H77: Weg | I77: =11753510.62-0.049 -> 11753511 | K77: 0 | L77: 0 | M77: 0 | N77: 0 | O77: =SUM(I77:N77) -> 11753511 | P77: =SUMIFS('Desenvolvimento diário'!$H:$H,'Desenvolvimento diário'!$Q:$Q,$B77,'Desenvolvimento diário'!$P:$P,$F77,'Desenvolvimento diário'!$R:$R,"Sim") -> 0 | Q77: =SUMIFS('Desenvolvimento diário'!$H:$H,'Desenvolvimento diário'!$Q:$Q,$B77,'Desenvolvimento diário'!$P:$P,$F77,'Desenvolvimento diário'!$R:$R,"Não") -> 11753511 | R77: =SUM(P77:Q77) -> 11753511 | S77: =O77-R77 -> 0 | T77: =IFERROR(R77/O77,0) -> 1
A78: =A77 -> 3 | B78: =VLOOKUP($A78,Controle!$B$4:$F$68,2,FALSE) -> Frei Inocêncio 1 | C78: =VLOOKUP($A78,Controle!$B$4:$F$68,3,FALSE) -> MORI GERACAO II | D78: =VLOOKUP($A78,Controle!$B$4:$F$68,4,FALSE) -> Mori II | E78: =VLOOKUP($A78,Controle!$B$4:$F$68,5,FALSE) -> Weg | F78: =F43 -> Equipamentos Curva A - Outros (Transformadores) | G78: =VLOOKUP($A78,Controle!$B$4:$G$68,6,FALSE) -> Mori | H78: 0 | I78: 0 | J78: 0 | K78: 0 | L78: 0 | M78: 0 | N78: 0 | O78: =SUM(I78:N78) -> 0 | P78: =SUMIFS('Desenvolvimento diário'!$H:$H,'Desenvolvimento diário'!$Q:$Q,$B78,'Desenvolvimento diário'!$P:$P,$F78,'Desenvolvimento diário'!$R:$R,"Sim") -> 0 | Q78: =SUMIFS('Desenvolvimento diário'!$H:$H,'Desenvolvimento diário'!$Q:$Q,$B78,'Desenvolvimento diário'!$P:$P,$F78,'Desenvolvimento diário'!$R:$R,"Não") -> 0 | R78: =SUM(P78:Q78) -> 0 | S78: =O78-R78 -> 0 | T78: =IFERROR(R78/O78,0) -> 0
A79: =A78 -> 3 | B79: =VLOOKUP($A79,Controle!$B$4:$F$68,2,FALSE) -> Frei Inocêncio 1 | C79: =VLOOKUP($A79,Controle!$B$4:$F$68,3,FALSE) -> MORI GERACAO II | D79: =VLOOKUP($A79,Controle!$B$4:$F$68,4,FALSE) -> Mori II | E79: =VLOOKUP($A79,Controle!$B$4:$F$68,5,FALSE) -> Weg | F79: =F44 -> Equipamentos Curva A - Outros (Cabine + Skid) | G79: =VLOOKUP($A79,Controle!$B$4:$G$68,6,FALSE) -> Mori | H79: 0 | I79: 0 | J79: 0 | K79: 0 | L79: 0 | M79: 0 | N79: 0 | O79: =SUM(I79:N79) -> 0 | P79: =SUMIFS('Desenvolvimento diário'!$H:$H,'Desenvolvimento diário'!$Q:$Q,$B79,'Desenvolvimento diário'!$P:$P,$F79,'Desenvolvimento diário'!$R:$R,"Sim") -> 0 | Q79: =SUMIFS('Desenvolvimento diário'!$H:$H,'Desenvolvimento diário'!$Q:$Q,$B79,'Desenvolvimento diário'!$P:$P,$F79,'Desenvolvimento diário'!$R:$R,"Não") -> 0 | R79: =SUM(P79:Q79) -> 0 | S79: =O79-R79 -> 0 | T79: =IFERROR(R79/O79,0) -> 0
A80: =A79 -> 3 | B80: =VLOOKUP($A80,Controle!$B$4:$F$68,2,FALSE) -> Frei Inocêncio 1 | C80: =VLOOKUP($A80,Controle!$B$4:$F$68,3,FALSE) -> MORI GERACAO II | D80: =VLOOKUP($A80,Controle!$B$4:$F$68,4,FALSE) -> Mori II | E80: =VLOOKUP($A80,Controle!$B$4:$F$68,5,FALSE) -> Weg | F80: =F45 -> Equipamentos Curva A - Outros (Cabine + Skid + Transformador) | G80: =VLOOKUP($A80,Controle!$B$4:$G$68,6,FALSE) -> Mori | H80: Romagnole | I80: 223422.32 | J80: 0 | K80: 0 | L80: 0 | M80: 0 | N80: 0 | O80: =SUM(I80:N80) -> 223422.32 | P80: =SUMIFS('Desenvolvimento diário'!$H:$H,'Desenvolvimento diário'!$Q:$Q,$B80,'Desenvolvimento diário'!$P:$P,$F80,'Desenvolvimento diário'!$R:$R,"Sim") -> 0 | Q80: =SUMIFS('Desenvolvimento diário'!$H:$H,'Desenvolvimento diário'!$Q:$Q,$B80,'Desenvolvimento diário'!$P:$P,$F80,'Desenvolvimento diário'!$R:$R,"Não") -> 223422.32 | R80: =SUM(P80:Q80) -> 223422.32 | S80: =O80-R80 -> 0 | T80: =IFERROR(R80/O80,0) -> 1
A81: =A80 -> 3 | B81: =VLOOKUP($A81,Controle!$B$4:$F$68,2,FALSE) -> Frei Inocêncio 1 | C81: =VLOOKUP($A81,Controle!$B$4:$F$68,3,FALSE) -> MORI GERACAO II | D81: =VLOOKUP($A81,Controle!$B$4:$F$68,4,FALSE) -> Mori II | E81: =VLOOKUP($A81,Controle!$B$4:$F$68,5,FALSE) -> Weg | F81: =F46 -> Desenvolvimento de projeto - Projetos - (Eng° Proprietario) | G81: =VLOOKUP($A81,Controle!$B$4:$G$68,6,FALSE) -> Mori | H81: Afaplan | I81: =R81 -> 151743.28 | J81: 0 | K81: 0 | L81: 0 | M81: 0 | N81: 0 | O81: =SUM(I81:N81) -> 151743.28 | P81: =SUMIFS('Desenvolvimento diário'!$H:$H,'Desenvolvimento diário'!$Q:$Q,$B81,'Desenvolvimento diário'!$P:$P,$F81,'Desenvolvimento diário'!$R:$R,"Sim") -> 0 | Q81: =SUMIFS('Desenvolvimento diário'!$H:$H,'Desenvolvimento diário'!$Q:$Q,$B81,'Desenvolvimento diário'!$P:$P,$F81,'Desenvolvimento diário'!$R:$R,"Não") -> 151743.28 | R81: =SUM(P81:Q81) -> 151743.28 | S81: =O81-R81 -> 0 | T81: =IFERROR(R81/O81,0) -> 1
A82: =A81 -> 3 | B82: =VLOOKUP($A82,Controle!$B$4:$F$68,2,FALSE) -> Frei Inocêncio 1 | C82: =VLOOKUP($A82,Controle!$B$4:$F$68,3,FALSE) -> MORI GERACAO II | D82: =VLOOKUP($A82,Controle!$B$4:$F$68,4,FALSE) -> Mori II | E82: =VLOOKUP($A82,Controle!$B$4:$F$68,5,FALSE) -> Weg | F82: =F47 -> Desenvolvimento de projeto - Projetos - Executivos | G82: =VLOOKUP($A82,Controle!$B$4:$G$68,6,FALSE) -> Mori | H82: 0 | I82: 0 | J82: 0 | K82: 0 | L82: 0 | M82: 0 | N82: 0 | O82: =SUM(I82:N82) -> 0 | P82: =SUMIFS('Desenvolvimento diário'!$H:$H,'Desenvolvimento diário'!$Q:$Q,$B82,'Desenvolvimento diário'!$P:$P,$F82,'Desenvolvimento diário'!$R:$R,"Sim") -> 0 | Q82: =SUMIFS('Desenvolvimento diário'!$H:$H,'Desenvolvimento diário'!$Q:$Q,$B82,'Desenvolvimento diário'!$P:$P,$F82,'Desenvolvimento diário'!$R:$R,"Não") -> 0 | R82: =SUM(P82:Q82) -> 0 | S82: =O82-R82 -> 0 | T82: =IFERROR(R82/O82,0) -> 0
A83: =A82 -> 3 | B83: =VLOOKUP($A83,Controle!$B$4:$F$68,2,FALSE) -> Frei Inocêncio 1 | C83: =VLOOKUP($A83,Controle!$B$4:$F$68,3,FALSE) -> MORI GERACAO II | D83: =VLOOKUP($A83,Controle!$B$4:$F$68,4,FALSE) -> Mori II | E83: =VLOOKUP($A83,Controle!$B$4:$F$68,5,FALSE) -> Weg | F83: =F48 -> Desenvolvimento de projeto - Projetos Básica | G83: =VLOOKUP($A83,Controle!$B$4:$G$68,6,FALSE) -> Mori | H83: 0 | I83: 0 | J83: 0 | K83: 0 | L83: 0 | M83: 0 | N83: 0 | O83: =SUM(I83:N83) -> 0 | P83: =SUMIFS('Desenvolvimento diário'!$H:$H,'Desenvolvimento diário'!$Q:$Q,$B83,'Desenvolvimento diário'!$P:$P,$F83,'Desenvolvimento diário'!$R:$R,"Sim") -> 0 | Q83: =SUMIFS('Desenvolvimento diário'!$H:$H,'Desenvolvimento diário'!$Q:$Q,$B83,'Desenvolvimento diário'!$P:$P,$F83,'Desenvolvimento diário'!$R:$R,"Não") -> 0 | R83: =SUM(P83:Q83) -> 0 | S83: =O83-R83 -> 0 | T83: =IFERROR(R83/O83,0) -> 0
A84: =A83 -> 3 | B84: =VLOOKUP($A84,Controle!$B$4:$F$68,2,FALSE) -> Frei Inocêncio 1 | C84: =VLOOKUP($A84,Controle!$B$4:$F$68,3,FALSE) -> MORI GERACAO II | D84: =VLOOKUP($A84,Controle!$B$4:$F$68,4,FALSE) -> Mori II | E84: =VLOOKUP($A84,Controle!$B$4:$F$68,5,FALSE) -> Weg | F84: =F49 -> Desenvolvimento de projeto - Projetos Detalhada | G84: =VLOOKUP($A84,Controle!$B$4:$G$68,6,FALSE) -> Mori | H84: 0 | I84: 0 | J84: 0 | K84: 0 | L84: 0 | M84: 0 | N84: 0 | O84: =SUM(I84:N84) -> 0 | P84: =SUMIFS('Desenvolvimento diário'!$H:$H,'Desenvolvimento diário'!$Q:$Q,$B84,'Desenvolvimento diário'!$P:$P,$F84,'Desenvolvimento diário'!$R:$R,"Sim") -> 0 | Q84: =SUMIFS('Desenvolvimento diário'!$H:$H,'Desenvolvimento diário'!$Q:$Q,$B84,'Desenvolvimento diário'!$P:$P,$F84,'Desenvolvimento diário'!$R:$R,"Não") -> 0 | R84: =SUM(P84:Q84) -> 0 | S84: =O84-R84 -> 0 | T84: =IFERROR(R84/O84,0) -> 0
A85: =A84 -> 3 | B85: =VLOOKUP($A85,Controle!$B$4:$F$68,2,FALSE) -> Frei Inocêncio 1 | C85: =VLOOKUP($A85,Controle!$B$4:$F$68,3,FALSE) -> MORI GERACAO II | D85: =VLOOKUP($A85,Controle!$B$4:$F$68,4,FALSE) -> Mori II | E85: =VLOOKUP($A85,Controle!$B$4:$F$68,5,FALSE) -> Weg | F85: =F50 -> Desenvolvimento de projeto - Ambiental / Outros | G85: =VLOOKUP($A85,Controle!$B$4:$G$68,6,FALSE) -> Mori | H85: Varios | I85: =R85 -> 210312.58 | J85: 0 | K85: 0 | L85: 0 | M85: 0 | N85: 0 | O85: =SUM(I85:N85) -> 210312.58 | P85: =SUMIFS('Desenvolvimento diário'!$H:$H,'Desenvolvimento diário'!$Q:$Q,$B85,'Desenvolvimento diário'!$P:$P,$F85,'Desenvolvimento diário'!$R:$R,"Sim") -> 0 | Q85: =SUMIFS('Desenvolvimento diário'!$H:$H,'Desenvolvimento diário'!$Q:$Q,$B85,'Desenvolvimento diário'!$P:$P,$F85,'Desenvolvimento diário'!$R:$R,"Não") -> 210312.58 | R85: =SUM(P85:Q85) -> 210312.58 | S85: =O85-R85 -> 0 | T85: =IFERROR(R85/O85,0) -> 1
A86: =A85 -> 3 | B86: =VLOOKUP($A86,Controle!$B$4:$F$68,2,FALSE) -> Frei Inocêncio 1 | C86: =VLOOKUP($A86,Controle!$B$4:$F$68,3,FALSE) -> MORI GERACAO II | D86: =VLOOKUP($A86,Controle!$B$4:$F$68,4,FALSE) -> Mori II | E86: =VLOOKUP($A86,Controle!$B$4:$F$68,5,FALSE) -> Weg | F86: =F51 -> Desenvolvimento de projeto - Coordenograma | G86: =VLOOKUP($A86,Controle!$B$4:$G$68,6,FALSE) -> Mori | H86: PROJETTI | I86: 6206.9 | J86: 2281.25 | K86: 0 | L86: 0 | M86: 0 | N86: 0 | O86: =SUM(I86:N86) -> 8488.15 | P86: =SUMIFS('Desenvolvimento diário'!$H:$H,'Desenvolvimento diário'!$Q:$Q,$B86,'Desenvolvimento diário'!$P:$P,$F86,'Desenvolvimento diário'!$R:$R,"Sim") -> 0 | Q86: =SUMIFS('Desenvolvimento diário'!$H:$H,'Desenvolvimento diário'!$Q:$Q,$B86,'Desenvolvimento diário'!$P:$P,$F86,'Desenvolvimento diário'!$R:$R,"Não") -> 8488.15 | R86: =SUM(P86:Q86) -> 8488.15 | S86: =O86-R86 -> 0 | T86: =IFERROR(R86/O86,0) -> 1
A87: =A86 -> 3 | B87: =VLOOKUP($A87,Controle!$B$4:$F$68,2,FALSE) -> Frei Inocêncio 1 | C87: =VLOOKUP($A87,Controle!$B$4:$F$68,3,FALSE) -> MORI GERACAO II | D87: =VLOOKUP($A87,Controle!$B$4:$F$68,4,FALSE) -> Mori II | E87: =VLOOKUP($A87,Controle!$B$4:$F$68,5,FALSE) -> Weg | F87: =F52 -> Sistemas de Monitoramento - Supervisório | G87: =VLOOKUP($A87,Controle!$B$4:$G$68,6,FALSE) -> Mori | H87: ATI | I87: 126513.54 | K87: 0 | L87: 0 | M87: 0 | N87: 0 | O87: =SUM(I87:N87) -> 126513.54 | P87: =SUMIFS('Desenvolvimento diário'!$H:$H,'Desenvolvimento diário'!$Q:$Q,$B87,'Desenvolvimento diário'!$P:$P,$F87,'Desenvolvimento diário'!$R:$R,"Sim") -> 14032 | Q87: =SUMIFS('Desenvolvimento diário'!$H:$H,'Desenvolvimento diário'!$Q:$Q,$B87,'Desenvolvimento diário'!$P:$P,$F87,'Desenvolvimento diário'!$R:$R,"Não") -> 112481.54 | R87: =SUM(P87:Q87) -> 126513.54 | S87: =O87-R87 -> 0 | T87: =IFERROR(R87/O87,0) -> 1
A88: =A87 -> 3 | B88: =VLOOKUP($A88,Controle!$B$4:$F$68,2,FALSE) -> Frei Inocêncio 1 | C88: =VLOOKUP($A88,Controle!$B$4:$F$68,3,FALSE) -> MORI GERACAO II | D88: =VLOOKUP($A88,Controle!$B$4:$F$68,4,FALSE) -> Mori II | E88: =VLOOKUP($A88,Controle!$B$4:$F$68,5,FALSE) -> Weg | F88: =F53 -> Sistemas de Monitoramento - Estações Solarimétricas | G88: =VLOOKUP($A88,Controle!$B$4:$G$68,6,FALSE) -> Mori | H88: 0 | I88: 0 | J88: 0 | K88: 0 | L88: 0 | M88: 0 | N88: 0 | O88: =SUM(I88:N88) -> 0 | P88: =SUMIFS('Desenvolvimento diário'!$H:$H,'Desenvolvimento diário'!$Q:$Q,$B88,'Desenvolvimento diário'!$P:$P,$F88,'Desenvolvimento diário'!$R:$R,"Sim") -> 0 | Q88: =SUMIFS('Desenvolvimento diário'!$H:$H,'Desenvolvimento diário'!$Q:$Q,$B88,'Desenvolvimento diário'!$P:$P,$F88,'Desenvolvimento diário'!$R:$R,"Não") -> 0 | R88: =SUM(P88:Q88) -> 0 | S88: =O88-R88 -> 0 | T88: =IFERROR(R88/O88,0) -> 0
A89: =A88 -> 3 | B89: =VLOOKUP($A89,Controle!$B$4:$F$68,2,FALSE) -> Frei Inocêncio 1 | C89: =VLOOKUP($A89,Controle!$B$4:$F$68,3,FALSE) -> MORI GERACAO II | D89: =VLOOKUP($A89,Controle!$B$4:$F$68,4,FALSE) -> Mori II | E89: =VLOOKUP($A89,Controle!$B$4:$F$68,5,FALSE) -> Weg | F89: =F54 -> Sistemas de Monitoramento - CFTV | G89: =VLOOKUP($A89,Controle!$B$4:$G$68,6,FALSE) -> Mori | H89: Maxvision | I89: 289840.9 | J89: 0 | K89: 9336.84 | L89: 0 | M89: 0 | N89: 0 | O89: =SUM(I89:N89) -> 299177.74 | P89: =SUMIFS('Desenvolvimento diário'!$H:$H,'Desenvolvimento diário'!$Q:$Q,$B89,'Desenvolvimento diário'!$P:$P,$F89,'Desenvolvimento diário'!$R:$R,"Sim") -> 12905.67 | Q89: =SUMIFS('Desenvolvimento diário'!$H:$H,'Desenvolvimento diário'!$Q:$Q,$B89,'Desenvolvimento diário'!$P:$P,$F89,'Desenvolvimento diário'!$R:$R,"Não") -> 286272.07 | R89: =SUM(P89:Q89) -> 299177.74 | S89: =O89-R89 -> 0 | T89: =IFERROR(R89/O89,0) -> 1
A90: =A89 -> 3 | B90: =VLOOKUP($A90,Controle!$B$4:$F$68,2,FALSE) -> Frei Inocêncio 1 | C90: =VLOOKUP($A90,Controle!$B$4:$F$68,3,FALSE) -> MORI GERACAO II | D90: =VLOOKUP($A90,Controle!$B$4:$F$68,4,FALSE) -> Mori II | E90: =VLOOKUP($A90,Controle!$B$4:$F$68,5,FALSE) -> Weg | F90: =F55 -> Serviços Auxiliares - Drenagem | G90: =VLOOKUP($A90,Controle!$B$4:$G$68,6,FALSE) -> Mori | H90: MRO | I90: 472621.43 | J90: 0 | K90: 0 | L90: 0 | M90: 0 | N90: 0 | O90: =SUM(I90:N90) -> 472621.43 | P90: =SUMIFS('Desenvolvimento diário'!$H:$H,'Desenvolvimento diário'!$Q:$Q,$B90,'Desenvolvimento diário'!$P:$P,$F90,'Desenvolvimento diário'!$R:$R,"Sim") -> 0 | Q90: =SUMIFS('Desenvolvimento diário'!$H:$H,'Desenvolvimento diário'!$Q:$Q,$B90,'Desenvolvimento diário'!$P:$P,$F90,'Desenvolvimento diário'!$R:$R,"Não") -> 472621.43 | R90: =SUM(P90:Q90) -> 472621.43 | S90: =O90-R90 -> 0 | T90: =IFERROR(R90/O90,0) -> 1
A91: =A90 -> 3 | B91: =VLOOKUP($A91,Controle!$B$4:$F$68,2,FALSE) -> Frei Inocêncio 1 | C91: =VLOOKUP($A91,Controle!$B$4:$F$68,3,FALSE) -> MORI GERACAO II | D91: =VLOOKUP($A91,Controle!$B$4:$F$68,4,FALSE) -> Mori II | E91: =VLOOKUP($A91,Controle!$B$4:$F$68,5,FALSE) -> Weg | F91: =F56 -> Serviços Auxiliares - Terraplanagem | G91: =VLOOKUP($A91,Controle!$B$4:$G$68,6,FALSE) -> Mori | H91: MRO | I91: =497631.51+(0.003) -> 497631.51 | J91: 0 | K91: 0 | L91: 0 | M91: 0 | N91: 0 | O91: =SUM(I91:N91) -> 497631.51 | P91: =SUMIFS('Desenvolvimento diário'!$H:$H,'Desenvolvimento diário'!$Q:$Q,$B91,'Desenvolvimento diário'!$P:$P,$F91,'Desenvolvimento diário'!$R:$R,"Sim") -> 0 | Q91: =SUMIFS('Desenvolvimento diário'!$H:$H,'Desenvolvimento diário'!$Q:$Q,$B91,'Desenvolvimento diário'!$P:$P,$F91,'Desenvolvimento diário'!$R:$R,"Não") -> 497631.51 | R91: =SUM(P91:Q91) -> 497631.51 | S91: =O91-R91 -> 0 | T91: =IFERROR(R91/O91,0) -> 1
A92: =A91 -> 3 | B92: =VLOOKUP($A92,Controle!$B$4:$F$68,2,FALSE) -> Frei Inocêncio 1 | C92: =VLOOKUP($A92,Controle!$B$4:$F$68,3,FALSE) -> MORI GERACAO II | D92: =VLOOKUP($A92,Controle!$B$4:$F$68,4,FALSE) -> Mori II | E92: =VLOOKUP($A92,Controle!$B$4:$F$68,5,FALSE) -> Weg | F92: =F57 -> Serviços Auxiliares - Supressão Vegetal | G92: =VLOOKUP($A92,Controle!$B$4:$G$68,6,FALSE) -> Mori | H92: 0 | I92: 0 | J92: 0 | K92: 0 | L92: 0 | M92: 0 | N92: 0 | O92: =SUM(I92:N92) -> 0 | P92: =SUMIFS('Desenvolvimento diário'!$H:$H,'Desenvolvimento diário'!$Q:$Q,$B92,'Desenvolvimento diário'!$P:$P,$F92,'Desenvolvimento diário'!$R:$R,"Sim") -> 0 | Q92: =SUMIFS('Desenvolvimento diário'!$H:$H,'Desenvolvimento diário'!$Q:$Q,$B92,'Desenvolvimento diário'!$P:$P,$F92,'Desenvolvimento diário'!$R:$R,"Não") -> 0 | R92: =SUM(P92:Q92) -> 0 | S92: =O92-R92 -> 0 | T92: =IFERROR(R92/O92,0) -> 0
A93: =A92 -> 3 | B93: =VLOOKUP($A93,Controle!$B$4:$F$68,2,FALSE) -> Frei Inocêncio 1 | C93: =VLOOKUP($A93,Controle!$B$4:$F$68,3,FALSE) -> MORI GERACAO II | D93: =VLOOKUP($A93,Controle!$B$4:$F$68,4,FALSE) -> Mori II | E93: =VLOOKUP($A93,Controle!$B$4:$F$68,5,FALSE) -> Weg | F93: =F58 -> RDR-Rede de Distribuição Rural | G93: =VLOOKUP($A93,Controle!$B$4:$G$68,6,FALSE) -> Mori | H93: 0 | I93: 0 | J93: 0 | K93: 0 | L93: 0 | M93: 0 | N93: 0 | O93: =SUM(I93:N93) -> 0 | P93: =SUMIFS('Desenvolvimento diário'!$H:$H,'Desenvolvimento diário'!$Q:$Q,$B93,'Desenvolvimento diário'!$P:$P,$F93,'Desenvolvimento diário'!$R:$R,"Sim") -> 0 | Q93: =SUMIFS('Desenvolvimento diário'!$H:$H,'Desenvolvimento diário'!$Q:$Q,$B93,'Desenvolvimento diário'!$P:$P,$F93,'Desenvolvimento diário'!$R:$R,"Não") -> 0 | R93: =SUM(P93:Q93) -> 0 | S93: =O93-R93 -> 0 | T93: =IFERROR(R93/O93,0) -> 0
A94: =A93 -> 3 | B94: =VLOOKUP($A94,Controle!$B$4:$F$68,2,FALSE) -> Frei Inocêncio 1 | C94: =VLOOKUP($A94,Controle!$B$4:$F$68,3,FALSE) -> MORI GERACAO II | D94: =VLOOKUP($A94,Controle!$B$4:$F$68,4,FALSE) -> Mori II | E94: =VLOOKUP($A94,Controle!$B$4:$F$68,5,FALSE) -> Weg | F94: =F59 -> Escopo COMERC | G94: =VLOOKUP($A94,Controle!$B$4:$G$68,6,FALSE) -> Mori | H94: 0 | I94: 145160 | J94: 13000 | L94: 0 | M94: 0 | N94: 0 | O94: =SUM(I94:N94) -> 158160 | P94: =SUMIFS('Desenvolvimento diário'!$H:$H,'Desenvolvimento diário'!$Q:$Q,$B94,'Desenvolvimento diário'!$P:$P,$F94,'Desenvolvimento diário'!$R:$R,"Sim") -> 118860 | Q94: =SUMIFS('Desenvolvimento diário'!$H:$H,'Desenvolvimento diário'!$Q:$Q,$B94,'Desenvolvimento diário'!$P:$P,$F94,'Desenvolvimento diário'!$R:$R,"Não") -> 26300 | R94: =SUM(P94:Q94) -> 145160 | S94: =O94-R94 -> 13000 | T94: =IFERROR(R94/O94,0) -> 0.91780475 | U94: S | V94: Escopo Comerc
A95: =A94 -> 3 | B95: =VLOOKUP($A95,Controle!$B$4:$F$68,2,FALSE) -> Frei Inocêncio 1 | C95: =VLOOKUP($A95,Controle!$B$4:$F$68,3,FALSE) -> MORI GERACAO II | D95: =VLOOKUP($A95,Controle!$B$4:$F$68,4,FALSE) -> Mori II | E95: =VLOOKUP($A95,Controle!$B$4:$F$68,5,FALSE) -> Weg | F95: =F60 -> Escopo COMERC - Segurança | G95: =VLOOKUP($A95,Controle!$B$4:$G$68,6,FALSE) -> Mori | H95: 0 | I95: =R95 -> 173663.79 | J95: 0 | K95: 0 | L95: 0 | M95: 0 | N95: 0 | O95: =SUM(I95:N95) -> 173663.79 | P95: =SUMIFS('Desenvolvimento diário'!$H:$H,'Desenvolvimento diário'!$Q:$Q,$B95,'Desenvolvimento diário'!$P:$P,$F95,'Desenvolvimento diário'!$R:$R,"Sim") -> 0 | Q95: =SUMIFS('Desenvolvimento diário'!$H:$H,'Desenvolvimento diário'!$Q:$Q,$B95,'Desenvolvimento diário'!$P:$P,$F95,'Desenvolvimento diário'!$R:$R,"Não") -> 173663.79 | R95: =SUM(P95:Q95) -> 173663.79 | S95: =O95-R95 -> 0 | T95: =IFERROR(R95/O95,0) -> 1
A96: =A95 -> 3 | B96: =VLOOKUP($A96,Controle!$B$4:$F$68,2,FALSE) -> Frei Inocêncio 1 | C96: =VLOOKUP($A96,Controle!$B$4:$F$68,3,FALSE) -> MORI GERACAO II | D96: =VLOOKUP($A96,Controle!$B$4:$F$68,4,FALSE) -> Mori II | E96: =VLOOKUP($A96,Controle!$B$4:$F$68,5,FALSE) -> Weg | F96: =F61 -> Conexão MT - Obras Transferencia | G96: =VLOOKUP($A96,Controle!$B$4:$G$68,6,FALSE) -> Mori | H96: 0 | I96: 0 | J96: 0 | K96: 0 | L96: 0 | M96: 0 | N96: 0 | O96: =SUM(I96:N96) -> 0 | P96: =SUMIFS('Desenvolvimento diário'!$H:$H,'Desenvolvimento diário'!$Q:$Q,$B96,'Desenvolvimento diário'!$P:$P,$F96,'Desenvolvimento diário'!$R:$R,"Sim") -> 0 | Q96: =SUMIFS('Desenvolvimento diário'!$H:$H,'Desenvolvimento diário'!$Q:$Q,$B96,'Desenvolvimento diário'!$P:$P,$F96,'Desenvolvimento diário'!$R:$R,"Não") -> 0 | R96: =SUM(P96:Q96) -> 0 | S96: =O96-R96 -> 0 | T96: =IFERROR(R96/O96,0) -> 0
A97: =A96 -> 3 | B97: =VLOOKUP($A97,Controle!$B$4:$F$68,2,FALSE) -> Frei Inocêncio 1 | C97: =VLOOKUP($A97,Controle!$B$4:$F$68,3,FALSE) -> MORI GERACAO II | D97: =VLOOKUP($A97,Controle!$B$4:$F$68,4,FALSE) -> Mori II | E97: =VLOOKUP($A97,Controle!$B$4:$F$68,5,FALSE) -> Weg | F97: =F62 -> Bases de Contaniers | G97: =VLOOKUP($A97,Controle!$B$4:$G$68,6,FALSE) -> Mori | H97: GR ENGENHARIA | I97: 99192.67 | J97: 0 | K97: 0 | L97: 0 | M97: 0 | N97: 0 | O97: =SUM(I97:N97)+0.11 -> 99192.78 | P97: =SUMIFS('Desenvolvimento diário'!$H:$H,'Desenvolvimento diário'!$Q:$Q,$B97,'Desenvolvimento diário'!$P:$P,$F97,'Desenvolvimento diário'!$R:$R,"Sim") -> 0 | Q97: =SUMIFS('Desenvolvimento diário'!$H:$H,'Desenvolvimento diário'!$Q:$Q,$B97,'Desenvolvimento diário'!$P:$P,$F97,'Desenvolvimento diário'!$R:$R,"Não") -> 99192.78 | R97: =SUM(P97:Q97) -> 99192.78 | S97: =O97-R97 -> 0 | T97: =IFERROR(R97/O97,0) -> 1
A98: =A97 -> 3 | B98: =VLOOKUP($A98,Controle!$B$4:$F$68,2,FALSE) -> Frei Inocêncio 1 | C98: =VLOOKUP($A98,Controle!$B$4:$F$68,3,FALSE) -> MORI GERACAO II | D98: =VLOOKUP($A98,Controle!$B$4:$F$68,4,FALSE) -> Mori II | E98: =VLOOKUP($A98,Controle!$B$4:$F$68,5,FALSE) -> Weg | F98: =F63 -> Construção - Serviços de Construção - Ase Engenharia | G98: =VLOOKUP($A98,Controle!$B$4:$G$68,6,FALSE) -> Mori | H98: 0 | I98: 0 | J98: 0 | K98: 0 | L98: 0 | M98: 0 | N98: 0 | O98: =SUM(I98:N98) -> 0 | P98: =SUMIFS('Desenvolvimento diário'!$H:$H,'Desenvolvimento diário'!$Q:$Q,$B98,'Desenvolvimento diário'!$P:$P,$F98,'Desenvolvimento diário'!$R:$R,"Sim") -> 0 | Q98: =SUMIFS('Desenvolvimento diário'!$H:$H,'Desenvolvimento diário'!$Q:$Q,$B98,'Desenvolvimento diário'!$P:$P,$F98,'Desenvolvimento diário'!$R:$R,"Não") -> 0 | R98: =SUM(P98:Q98) -> 0 | S98: =O98-R98 -> 0 | T98: =IFERROR(R98/O98,0) -> 0
A99: =A98 -> 3 | B99: =VLOOKUP($A99,Controle!$B$4:$F$68,2,FALSE) -> Frei Inocêncio 1 | C99: =VLOOKUP($A99,Controle!$B$4:$F$68,3,FALSE) -> MORI GERACAO II | D99: =VLOOKUP($A99,Controle!$B$4:$F$68,4,FALSE) -> Mori II | E99: =VLOOKUP($A99,Controle!$B$4:$F$68,5,FALSE) -> Weg | F99: =F64 -> Full EPC - Contrato Sobressalentes | G99: =VLOOKUP($A99,Controle!$B$4:$G$68,6,FALSE) -> Mori | H99: Weg | I99: =199511.98-0.01 -> 199511.97 | J99: 0 | K99: 0 | L99: 0 | M99: 0 | N99: 0 | O99: =SUM(I99:N99)+0.01 -> 199511.98 | P99: =SUMIFS('Desenvolvimento diário'!$H:$H,'Desenvolvimento diário'!$Q:$Q,$B99,'Desenvolvimento diário'!$P:$P,$F99,'Desenvolvimento diário'!$R:$R,"Sim") -> 0 | Q99: =SUMIFS('Desenvolvimento diário'!$H:$H,'Desenvolvimento diário'!$Q:$Q,$B99,'Desenvolvimento diário'!$P:$P,$F99,'Desenvolvimento diário'!$R:$R,"Não") -> 199511.98 | R99: =SUM(P99:Q99) -> 199511.98 | S99: =O99-R99 -> 0 | T99: =IFERROR(R99/O99,0) -> 1
A100: =A99 -> 3 | B100: =VLOOKUP($A100,Controle!$B$4:$F$68,2,FALSE) -> Frei Inocêncio 1 | C100: =VLOOKUP($A100,Controle!$B$4:$F$68,3,FALSE) -> MORI GERACAO II | D100: =VLOOKUP($A100,Controle!$B$4:$F$68,4,FALSE) -> Mori II | E100: =VLOOKUP($A100,Controle!$B$4:$F$68,5,FALSE) -> Weg | F100: =F65 -> Construção - Serviços de Construção - NOVA MORADA | G100: =VLOOKUP($A100,Controle!$B$4:$G$68,6,FALSE) -> Mori | H100: 0 | I100: 0 | J100: 0 | K100: 0 | L100: 0 | M100: 0 | N100: 0 | O100: =SUM(I100:N100) -> 0 | P100: =SUMIFS('Desenvolvimento diário'!$H:$H,'Desenvolvimento diário'!$Q:$Q,$B100,'Desenvolvimento diário'!$P:$P,$F100,'Desenvolvimento diário'!$R:$R,"Sim") -> 0 | Q100: =SUMIFS('Desenvolvimento diário'!$H:$H,'Desenvolvimento diário'!$Q:$Q,$B100,'Desenvolvimento diário'!$P:$P,$F100,'Desenvolvimento diário'!$R:$R,"Não") -> 0 | R100: =SUM(P100:Q100) -> 0 | S100: =O100-R100 -> 0 | T100: =IFERROR(R100/O100,0) -> 0
...

Sheet Desenvolvimento diário
B1: # | C1: FILIAL | D1: Número do pedido | E1: Tipo | F1: Descrição | G1: Descrição adicional | H1: Valor | I1: Vencimento | J1: REF ENG | K1: Outros | O1: Fornecedor | P1: Natureza Nova | Q1: Unidade da Usina | R1: FD
B2: 1970 | C2: A701-ARES 2 PARTICIPACOES S.A | D2: * | E2: Fat. Direto (MBA-AT) | F2: Projetos AT - PROEL (Diamantina 1) | G2: * | H2: 56000 | I2: 44425 | J2: [CCC02328-03] | M2: Diamantina 1_Obras AT_FT | N2: Obras de AT | O2: MBA | P2: Conexão AT - Obras | Q2: Diamantina 1 | R2: Sim
B3: 2050 | C3: A701-ARES 2 PARTICIPACOES S.A | D3: * | E3: Outros - Serviços à UFV | F3: JX AMBIENTAL - Procedimento Administrativo - DAIA de implantação de UFV - 50% iniciais - (Diamantina 1) | G3: * | H3: 10496.25 | I3: 44438 | J3: [CCC02461-01] | M3: Diamantina 1 _Outros | N3: Serviço/Taxas Ambientais | O3: JX AMBIENTAL | P3: Desenvolvimento de projeto - Ambiental / Outros | Q3: Diamantina 1 | R3: Não
B4: 2068 | C4: A701-ARES 2 PARTICIPACOES S.A | D4: * | E4: Outros - Serviços à UFV | F4: JX AMBIENTAL - Procedimento Administrativo - DAIA de implantação de rede rural - 50% iniciais - (Diamantina 1) | G4: * | H4: 11551.75 | I4: 44438 | J4: [CCC02461-01] | M4: Diamantina 1 _Outros | N4: Serviço/Taxas Ambientais | O4: JX AMBIENTAL | P4: Desenvolvimento de projeto - Ambiental / Outros | Q4: Diamantina 1 | R4: Não
B5: 2236 | C5: A701-ARES 2 PARTICIPACOES S.A | D5: * | E5: Outros - Serviços à UFV | F5: JX AMBIENTAL - Taxa de Analise (Diamantina 1) | G5: * | H5: 528.5 | I5: 44466 | J5: [CCC02534-01] | M5: Diamantina 1 _Outros | N5: Serviço/Taxas Ambientais | O5: JX AMBIENTAL | P5: Desenvolvimento de projeto - Ambiental / Outros | Q5: Diamantina 1 | R5: Não
B6: 2237 | C6: A701-ARES 2 PARTICIPACOES S.A | D6: * | E6: Outros - Serviços à UFV | F6: JX AMBIENTAL - Taxa de Lenha (Diamantina 1) | G6: * | H6: 23.34 | I6: 44466 | J6: [CCC02534-02] | M6: Diamantina 1 _Outros | N6: Serviço/Taxas Ambientais | O6: JX AMBIENTAL | P6: Desenvolvimento de projeto - Ambiental / Outros | Q6: Diamantina 1 | R6: Não
B7: 2238 | C7: A701-ARES 2 PARTICIPACOES S.A | D7: * | E7: Outros - Serviços à UFV | F7: JX AMBIENTAL - Taxa de Madeira (Diamantina 1) | G7: * | H7: 285.15 | I7: 44466 | J7: [CCC02534-03] | M7: Diamantina 1 _Outros | N7: Serviço/Taxas Ambientais | O7: JX AMBIENTAL | P7: Desenvolvimento de projeto - Ambiental / Outros | Q7: Diamantina 1 | R7: Não
B8: 2106 | C8: A701-ARES 2 PARTICIPACOES S.A | D8: * | E8: Outros - Serviços à UFV | F8: JX AMBIENTAL - Procedimento Administrativo - DAIA de implantação de UFV - 40% intermediários - (Diamantina 1) | G8: * | H8: 8397 | I8: 44455 | J8: [CCC02488-02] | M8: Diamantina 1 _Outros | N8: Serviço/Taxas Ambientais | O8: JX AMBIENTAL | P8: Desenvolvimento de projeto - Ambiental / Outros | Q8: Diamantina 1 | R8: Não
B9: 2305 | C9: A701-ARES 2 PARTICIPACOES S.A | E9: Fat. Direto (MBA-AT) | F9: Projetos AT - PROEL (Diamantina 1) | H9: 26000 | I9: 44481 | J9: [CCC02545] | M9: Diamantina 1_Obras AT_FT | N9: Obras de AT | O9: MBA | P9: Conexão AT - Obras | Q9: Diamantina 1 | R9: Sim
B10: 2351 | C10: A701-ARES 2 PARTICIPACOES S.A | E10: Medição (MBA-AT) | F10: CONT. PROJETOS - Medição final de serviços (Diamantina 1) | H10: 41000 | I10: 44489 | J10: [CCC02581] | M10: Diamantina 1 _Obras AT_MD | N10: Obras de AT | O10: MBA | P10: Conexão AT - Obras | Q10: Diamantina 1 | R10: Não
B11: 2353 | C11: A701-ARES 2 PARTICIPACOES S.A | D11: * | E11: Outros - Serviços à UFV | F11: JX AMBIENTAL - Procedimento Administrativo - DAIA de implantação de UFV - 10% finais (Diamantina 1) | G11: * | H11: 2099.25 | I11: 44494 | J11: [CCC02575] | M11: Diamantina 1 _Outros | N11: Serviço/Taxas Ambientais | P11: Desenvolvimento de projeto - Ambiental / Outros | Q11: Diamantina 1 | R11: Não
B12: 2501 | C12: A-SOLATIO | D12: 0001 | E12: Medição (REMO-MT) | F12: Medição 0 - Adiantamento (VARGINHA 5 ) | G12: Pagamento orindo da Solatio para Usinas Solares | H12: 940.94 | I12: 44656 | J12: [CCC03152] | K12: [URGENTE] Controle de pagamentos AT e MT ter 05/04/2022 13:25 | O12: REMO | P12: Conexão MT - Obras | Q12: Varginha 5 | R12: Não
B13: 2502 | C13: A-SOLATIO | D13: 0002 | E13: Medição (REMO-MT) | F13: Medição 0 - Adiantamento (CAMPO BELO 4) | G13: Pagamento orindo da Solatio para Usinas Solares | H13: 104660.83 | I13: 44656 | J13: [CCC03152] | K13: [URGENTE] Controle de pagamentos AT e MT ter 05/04/2022 13:25 | O13: REMO | P13: Conexão MT - Obras | Q13: Campo Belo 4 | R13: Não
B14: 2503 | C14: A-SOLATIO | D14: 0003 | E14: Medição (REMO-MT) | F14: Medição 0 - Adiantamento (BAMBUI 1.1) | G14: Pagamento orindo da Solatio para Usinas Solares | H14: 568805.17 | I14: 44656 | J14: [CCC03152] | K14: [URGENTE] Controle de pagamentos AT e MT ter 05/04/2022 13:25 | O14: REMO | P14: Conexão MT - Obras | Q14: Bambuí 1.1 | R14: Não
B15: 2370 | C15: A701-ARES 2 PARTICIPACOES S.A | D15: 000048 | E15: Medição (MBA-AT) | F15: Medição 0 - Adiantamento (Diamantina 1) | H15: 67400 | I15: 44531 | J15: [CCC02610-01] | M15: Diamantina 1 _Obras AT_MD | N15: Obras de AT | O15: MBA | P15: Conexão AT - Obras | Q15: Diamantina 1 | R15: Não
B16: 2453 | C16: 0101-MORI HOLDING SA | D16: 001205 | E16: Outros - Serviços para Projetos | F16: Consultoria em servidão (Diamantina 1) GEOVANY | G16: Pagamento de consultoria em obtenção de documentos de servidão em suporte à implantação de UFV e sua rede MT. | H16: 10000 | I16: 44517 | J16: [CCC02649] | M16: Diamantina 1 _Outros | N16: Serviço/Taxas Ambientais | P16: Desenvolvimento de projeto - Ambiental / Outros | Q16: Diamantina 1 | R16: Não
B17: 2479 | C17: A201-MORI GERACAO II ENERGIA SOLAR S.A | D17: 000066 | E17: Outros - Serviços à UFV | F17: Projetos de fundações e drenagem - HALLITE (Diamantina 1) Analise terraplanagem | G17: Pagamento de serviço contratado, desenvolvendo análise e projeto de terraplanagem na UFV apontada (Diamantina 1) | H17: 6600 | I17: 44540 | J17: [CCC02569-02] | M17: Diamantina 1 _Outros | N17: Serviço/Taxas Ambientais | P17: Desenvolvimento de projeto - Ambiental / Outros | Q17: Diamantina 1 | R17: Não
B18: 2646 | C18: A701-ARES 2 PARTICIPACOES S.A | E18: Outros - Serviços à UFV | F18: JX AMBIENTAL - Procedimento Administrativo - DAIA de implantação de rede rural - 40% intermediários - (Diamantina 1) | G18: Segunda parcela de serviço de consultoria contratado cumprimento de legislação ambiental. | H18: 9241.4 | I18: 44546 | J18: [CCC02743-06] | M18: Diamantina 1 _Outros | N18: Serviço/Taxas Ambientais | P18: Desenvolvimento de projeto - Ambiental / Outros | Q18: Diamantina 1 | R18: Não
B19: 2841 | C19: A701-ARES 2 PARTICIPACOES S.A | E19: Outros - Serviços à UFV | F19: JX AMBIENTAL - Taxa de Analise - Rede (Diamantina 1) | H19: 620.14 | I19: 44604 | J19: [CCC02693-01] | M19: Diamantina 1 _Outros | N19: Serviço/Taxas Ambientais | P19: Desenvolvimento de projeto - Ambiental / Outros | Q19: Diamantina 1 | R19: Não
B20: 2842 | C20: A701-ARES 2 PARTICIPACOES S.A | E20: Outros - Serviços à UFV | F20: JX AMBIENTAL - Taxa de Lenha - Rede - Complementar (Diamantina 1) | H20: 57.05 | I20: 44604 | J20: [CCC02693-02] | M20: Diamantina 1 _Outros | N20: Serviço/Taxas Ambientais | P20: Desenvolvimento de projeto - Ambiental / Outros | Q20: Diamantina 1 | R20: Não
B21: 2843 | C21: A701-ARES 2 PARTICIPACOES S.A | E21: Outros - Serviços à UFV | F21: JX AMBIENTAL - Taxa de Madeira - Rede - Complementar (Diamantina 1) | H21: 31.39 | I21: 44604 | J21: [CCC02693-03] | M21: Diamantina 1 _Outros | N21: Serviço/Taxas Ambientais | P21: Desenvolvimento de projeto - Ambiental / Outros | Q21: Diamantina 1 | R21: Não
B22: 2852 | C22: A201-MORI GERACAO II ENERGIA SOLAR S.A | D22: 000133 | E22: Outros - Serviços à UFV | F22: Revisão de coordenadas de terreno - Soluç. Agrimensura (Diamantina 1) | G22: Serviço contatado para revisar coordenadas de projetos em desenvolvimento, com revalidação e certificação de dados e documentação. | H22: 4235.3 | I22: * | J22: [CCC02851-01] | M22: Diamantina 1 _Outros | N22: Serviço/Taxas Ambientais | P22: Desenvolvimento de projeto - Ambiental / Outros | Q22: Diamantina 1 | R22: Não
B23: 2920 | C23: A701-ARES 2 PARTICIPACOES S.A | E23: Outros - Serviços à UFV | F23: JX AMBIENTAL - Taxa de Analise APP - Rede (Diamantina 1) | G23: Taxa necessária à avaliação de intervenção ambiental na Rede de distribuição para a UFV. | H23: 596.29 | I23: 44582 | J23: [CCC02873] | M23: Diamantina 1 _Outros | N23: Serviço/Taxas Ambientais | P23: Desenvolvimento de projeto - Ambiental / Outros | Q23: Diamantina 1 | R23: Não
B24: 2960 | C24: A201-MORI GERACAO II ENERGIA SOLAR S.A | D24: SCOMP-000001 | E24: Outros - Compras para a UFV | F24: Reatores de aterramento ADELCO (Diamantina 1) | G24: Modelos 13,8kv - Pot:375kW Xreator: 50,8Ω (RNA 134750-7); Pot:1000kW Xreator: 25,4Ω (RNA 67376-13); Pot:1000kW Xreator: 25,4Ω (RNA 67376-13) | H24: 0 | I24: * | J24: [CCC02908] | N24: Controle da Lais | P24: Controle da Lais | Q24: Diamantina 1 | R24: Não
B25: 3089 | C25: A701-ARES 2 PARTICIPACOES S.A | E25: Outros - Serviços à UFV | F25: JX AMBIENTAL - Procedimento Administrativo - DAIA de implantação de rede rural - 10% finais - (Diamantina 1) | H25: 2310.35 | I25: 44608 | J25: [CCC02919-03] | M25: Diamantina 1 _Outros | N25: Serviço/Taxas Ambientais | P25: Desenvolvimento de projeto - Ambiental / Outros | Q25: Diamantina 1 | R25: Não
B26: 3031 | C26: A201-MORI GERACAO II ENERGIA SOLAR S.A | D26: 000189 | E26: Outros - Serviços à UFV | F26: JX AMBIENTAL - PTRF - Rede - 01de03 (Diamantina 1) | G26: Pagamento inicial do serviço de consultoria ambiental para p PTRF em suporte à implantação da rede da UFV. | H26: 8875 | I26: 44602 | J26: [CCC02901] | M26: Diamantina 1 _Outros | N26: Serviço/Taxas Ambientais | P26: Desenvolvimento de projeto - Ambiental / Outros | Q26: Diamantina 1 | R26: Não
B27: 3087 | C27: A201-MORI GERACAO II ENERGIA SOLAR S.A | D27: 000187 | E27: Outros - Serviços à UFV | F27: JX AMBIENTAL - PTRF - Rede - 02de03 (Diamantina 1) | G27: Pagamento intermediário do serviço de consultoria ambiental para p PTRF em suporte à implantação da rede da UFV. | H27: 7100 | I27: 44608 | J27: [CCC02919-01] | M27: Diamantina 1 _Outros | N27: Serviço/Taxas Ambientais | P27: Desenvolvimento de projeto - Ambiental / Outros | Q27: Diamantina 1 | R27: Não
B28: 3088 | C28: A201-MORI GERACAO II ENERGIA SOLAR S.A | D28: 000188 | E28: Outros - Serviços à UFV | F28: JX AMBIENTAL - PTRF - Rede - 03de03 (Diamantina 1) | G28: Pagamento final do serviço de consultoria ambiental para o PTRF em suporte à implantação da rede da UFV. | H28: 1775 | I28: 44608 | J28: [CCC02919-02] | M28: Diamantina 1 _Outros | N28: Serviço/Taxas Ambientais | P28: Desenvolvimento de projeto - Ambiental / Outros | Q28: Diamantina 1 | R28: Não
B29: 3118 | C29: A201-MORI GERACAO II ENERGIA SOLAR S.A | D29: 000205 | E29: Fat. Direto (MBA-MT) | F29: Desenvolvimento de Projeto MT (Diamantina 1) | G29: Compra feita em Faturamento Direto, em contrato de obras MT externas à UFV. | H29: 18172.23 | I29: 44608 | J29: [CCC02962-01] | K29: Cobrado no Distrato MBA | M29: Diamantina 1 _Obras MT_FD | N29: Obras de MT | O29: MBA | P29: Conexão MT - Obras | Q29: Diamantina 1 | R29: Sim
B30: 3114 | C30: A201-MORI GERACAO II ENERGIA SOLAR S.A | D30: 000201 | E30: Medição (MBA-MT) | F30: Medição 0 - Adiantamento contratual (Diamantina 1) | G30: Medição inicial, suportando adiantamento contratual para obras no contrato MT EXTERNOS à UFV. | H30: 460000 | I30: 44610 | J30: [CCC02925-01] | K30: Cobrado no Distrato MBA | M30: Diamantina 1 _Obras MT_MD | N30: Obras de MT | O30: MBA | P30: Conexão MT - Obras | Q30: Diamantina 1 | R30: Não
B31: 4636 | C31: A201-MORI GERACAO II ENERGIA SOLAR S.A | D31: 000305 | E31: Medição (MBA-AT) | F31: Medição 01 (Diamantina 1) | G31: Medição de serviços, suportando desenvolvimento de serviços em obras no contrato AT. | H31: 101100 | I31: 44676 | J31: [CCC03178-05] | M31: Diamantina 1 _Obras AT_MD | N31: Obras de AT | O31: MBA | P31: Conexão AT - Obras | Q31: Diamantina 1 | R31: Não
B32: 4734 | C32: A201-MORI GERACAO II ENERGIA SOLAR S.A | D32: 000293 | E32: Outros - Compras para a UFV | F32: Archtech - Testes de PullOuT_Biotec - Adiantamento (Diamantina 1) | H32: 3389.12 | I32: 44678 | J32: [CCC03145-47] | M32: Diamantina 1 _Outros | N32: Serviço/Taxas Ambientais | P32: Desenvolvimento de projeto - Ambiental / Outros | Q32: Diamantina 1 | R32: Não
B33: 4734 | C33: A201-MORI GERACAO II ENERGIA SOLAR S.A | D33: 000357 | E33: Outros - Compras para a UFV | F33: Archtech - Testes de PullOuT_Biotec - Finalização (Diamantina 1) | G33: Faturamento Direto de serviço de pullout, em testes de solo para dimenskonamento de estruturas | H33: 30502.1 | I33: 44701 | J33: [CCC03265-47] | M33: Diamantina 1 _Outros | N33: Serviço/Taxas Ambientais | P33: Desenvolvimento de projeto - Ambiental / Outros | Q33: Diamantina 1 | R33: Não
B34: 4946 | C34: A201-MORI GERACAO II ENERGIA SOLAR S.A | D34: 000362 | E34: Outros - Serviços à UFV | F34: Serviço de SPT - BIOTEC (Diamantina 1) - 40% iniciais - Campanha 6 | G34: Pagamento de serviço de sondagem de solo, executado em campo em preparação para implantação de UFV. | H34: 2465.06 | I34: 44706 | J34: [CCC03281-09] | M34: Diamantina 1 _Outros | N34: Serviço/Taxas Ambientais | P34: Desenvolvimento de projeto - Ambiental / Outros | Q34: Diamantina 1 | R34: Não
B35: 5107 | C35: A201-MORI GERACAO II ENERGIA SOLAR S.A | D35: 000376 | E35: Outros - Serviços à UFV | F35: Serviço de SPT - BIOTEC (Diamantina 1) - 60% finais - Campanha 6 | G35: Pagamento de serviço de sondagem de solo, executado em campo em preparação para implantação de UFV. | H35: 3697.58 | I35: 44732 | J35: [CCC03295-04] | M35: Diamantina 1 _Outros | N35: Serviço/Taxas Ambientais | P35: Desenvolvimento de projeto - Ambiental / Outros | Q35: Diamantina 1 | R35: Não
B36: 6150 | C36: A201-MORI GERACAO II ENERGIA SOLAR S.A | D36: 000405 | E36: Fat. Direto (ATI) | F36: SUPERVISORIO - Ciclo 2 - Gateways e remota (Diamantina 1) NF 1706 | G36: Compra inicial de equipamentos para implementação de sistema supervisório na UFV. Compra com NF de venda futura. | H36: 27761.33 | I36: 44736 | J36: [CCC03287-01] | M36: Diamantina 1 _SGD | N36: SGD - Supervisorio Geração Distribuida | O36: ATI | P36: Sistemas de Monitoramento - Supervisório | Q36: Diamantina 1 | R36: Não
B37: 6166 | C37: A201-MORI GERACAO II ENERGIA SOLAR S.A | D37: 000412 | E37: Fat. Direto (ATI) | F37: SUPERVISORIO - Ciclo 2 - Baterias, desktops, switch e acessórios (Diamantina 1) NF 1722 | G37: Compra inicial de equipamentos para implementação de sistema supervisório na UFV. Compra com NF de venda futura. | H37: 39819.52 | I37: 44736 | J37: [CCC03287-17] | M37: Diamantina 1 _SGD | N37: SGD - Supervisorio Geração Distribuida | O37: ATI | P37: Sistemas de Monitoramento - Supervisório | Q37: Diamantina 1 | R37: Não
B38: 6281 | C38: A701-ARES 2 PARTICIPACOES S.A | E38: Outros - Serviços à UFV | F38: JX AMBIENTAL - Taxa de Rep. Florestal - Complementar (Diamantina 1) | G38: Taxa necessária à avaliação de intervenção ambiental para a UFV. | H38: 276.87 | I38: 44739 | J38: [CCC02957] | M38: Diamantina 1 _Outros | N38: Serviço/Taxas Ambientais | P38: Desenvolvimento de projeto - Ambiental / Outros | Q38: Diamantina 1 | R38: Não
B39: 5268 | C39: A201-MORI GERACAO II ENERGIA SOLAR S.A | D39: 000437 | E39: Outros - Serviços à UFV | F39: Eng. Executiva GLD - Entrega 01 - P01_05 (Diamantina 1) | G39: Pagamento inicial suportando contrato de desenvolvimento de projetos executivos, na entrega de Projetos de Sistemas de Drenagem | H39: 3500 | I39: 44753 | J39: [CCC03314-01] | M39: Diamantina 1 _Engenharia Executiva - Basica | N39: Engenharia Executiva - Basica | O39: GLD | P39: Desenvolvimento de projeto - Projetos Detalhada | Q39: Diamantina 1 | R39: Não
B40: 5273 | C40: A201-MORI GERACAO II ENERGIA SOLAR S.A | D40: 000441 | E40: Outros - Serviços à UFV | F40: Eng. Executiva GLD - Entrega 02 - P01_03 (Diamantina 1) | G40: Pagamento inicial suportando contrato de desenvolvimento de projetos executivos, na entrega de Projetos de Sistemas de Drenagem | H40: 5878.3 | I40: 44753 | J40: [CCC03314-06] | M40: Diamantina 1 _Engenharia Executiva - Basica | N40: Engenharia Executiva - Basica | O40: GLD | P40: Desenvolvimento de projeto - Projetos Detalhada | Q40: Diamantina 1 | R40: Não
B41: 6033 | C41: A701-ARES 2 PARTICIPACOES S.A | E41: Outros - Serviços à UFV | F41: JX AMBIENTAL - Taxa de Extrator de lenha - UFV (Diamantina 1) | G41: Taxa necessária à avaliação de intervenção ambiental para a UFV. | H41: 166.96 | I41: 44762 | J41: [CCC03363-01] | M41: Diamantina 1 _Outros | N41: Serviço/Taxas Ambientais | P41: Desenvolvimento de projeto - Ambiental / Outros | Q41: Diamantina 1 | R41: Não
B42: 6034 | C42: A701-ARES 2 PARTICIPACOES S.A | D42: 000008 | E42: Outros - Serviços à UFV | F42: JX AMBIENTAL - Taxa de Extrator de Madeira - UFV (Diamantina 1) | G42: Taxa necessária à avaliação de intervenção ambiental para a UFV. | H42: 166.96 | I42: 44762 | J42: [CCC03363-02] | M42: Diamantina 1 _Outros | N42: Serviço/Taxas Ambientais | P42: Desenvolvimento de projeto - Ambiental / Outros | Q42: Diamantina 1 | R42: Não
B43: 6081 | C43: A201-MORI GERACAO II ENERGIA SOLAR S.A | D43: 000483 | E43: Medição (EPC) | F43: CANCELAR - Construção e Montagem IMPLANTAR - Adiantamento contratual (Diamantina 1) | G43: Pagamento de adiantamento contratual de 15% do total de contrato EPC de construção da UFV | H43: 0 | I43: * | J43: [CCC03380-01] | M43: Diamantina 1 _EPC_MD | N43: EPC - CLUSTER 1/2/3/4 | P43: Construção - Serviços de Construção | Q43: Diamantina 1 | R43: Não
B44: 6081 | C44: A201-MORI GERACAO II ENERGIA SOLAR S.A | D44: 000485 | E44: Medição (EPC) | F44: Construção e Montagem IMPLANTAR - Adiantamento contratual (Diamantina 1) | G44: Pagamento de adiantamento contratual de 15% do total de contrato EPC de construção da UFV | H44: 0 | I44: 44769 | J44: [CCC03380-01] | K44: DUPLO PEDIDO 000557 A201 | M44: Diamantina 1 _EPC_MD | N44: EPC - CLUSTER 1/2/3/4 | O44: * | P44: Não Controlado | Q44: Diamantina 1 | R44: Não
B45: 6001 | C45: A201-MORI GERACAO II ENERGIA SOLAR S.A | D45: 000461 | E45: Fat. Direto (MBA-MT) | F45: Religadores (Diamantina 1) NF372 | G45: Serviço necessário à disponibilização do software adquirido para gestão de documentação técnica da Engenharia. | H45: 118860 | I45: 44762 | J45: [CCC03327-01] | K45: Cobrado no Contrato da Engeluz | M45: Diamantina 1 _Obras MT_FD | N45: Obras de MT | O45: MBA | P45: Conexão MT - Obras Transferencia | Q45: Diamantina 1 | R45: Sim
B46: 6125 | C46: A201-MORI GERACAO II ENERGIA SOLAR S.A | D46: 000550 | E46: Fat. Direto (MBA-MT) | F46: Transformador Monofásico - Adiantamento (Diamantina 1) | G46: Compra feita em Faturamento Direto, em contrato de obras MT externas à UFV. | H46: =6461.02/2 -> 3230.51 | I46: 44795 | J46: [CCC03396-01] | K46: Cobrado na Engeluz | M46: Diamantina 1 _Obras MT_FD | N46: Obras de MT | O46: MBA | P46: Conexão MT - Obras Transferencia | Q46: Diamantina 1 | R46: Sim
B47: 6404 | C47: A201-MORI GERACAO II ENERGIA SOLAR S.A | D47: 000581 | E47: Outros - Compras para a UFV | F47: Estação solarimétrica – Hukseflux Diamantina 1 * NF 7022 PC 003177 | G47: Compra de equipamento adicional de monitoração de condições atmosféricas, adiantamento 30 % . | H47: 13959.486 | I47: 44802 | J47: [CCC03542] | M47: Diamantina 1 _Estação solarimétrica | N47: Estação solarimétrica | P47: Sistemas de Monitoramento - Estações Solarimétricas | Q47: Diamantina 1 | R47: Não
B48: 6550 | C48: A701-ARES 2 PARTICIPACOES S.A | D48: 000049 | E48: Outros - Serviços à UFV | F48: DAE - Dispença de Licenciamento ambiental UFV ( DIAMANTINA 1 ) N 1900017760527 LENHA PAGA EM PC 000007 | G48: Taxa necessária à avaliação de intervenção ambiental para a UFV. | H48: 166.96 | I48: 44816 | J48: [CCC03629] | M48: Diamantina 1 _Outros | N48: Serviço/Taxas Ambientais | P48: Desenvolvimento de projeto - Ambiental / Outros | Q48: Diamantina 1 | R48: Não
B49: 6551 | C49: A701-ARES 2 PARTICIPACOES S.A | D49: 000050 | E49: Outros - Serviços à UFV | F49: DAE - Dispença de Licenciamento ambiental UFV ( DIAMANTINA 1 ) N 1900017760608 MADEIRA | G49: Taxa necessária à avaliação de intervenção ambiental para a UFV. | H49: 166.96 | I49: 44816 | J49: [CCC03629] | M49: Diamantina 1 _Outros | N49: Serviço/Taxas Ambientais | P49: Desenvolvimento de projeto - Ambiental / Outros | Q49: Diamantina 1 | R49: Não
B50: 6258 | C50: A201-MORI GERACAO II ENERGIA SOLAR S.A | D50: 000557 | E50: Medição (EPC) | F50: SERVIÇO DE MAO DE OBRA E EQUIPAMENTOS / FERRAMENTAL ( DIAMANTINA 1) NF 659 | G50: Pagamento referente a 1° medição mão de obra e equipamentos | H50: 383467.5 | I50: 44785 | J50: [CCC03380-01] | M50: Diamantina 1 _EPC_MD | N50: EPC - CLUSTER 1/2/3/4 | O50: IMPLANTAR | P50: Construção - Serviços de Construção | Q50: Diamantina 1 | R50: Não
B51: 7478 | C51: A201-MORI GERACAO II ENERGIA SOLAR S.A | D51: 000938 | E51: Outros - Serviços à UFV | F51: Atividades para liberação de execução de POT nas UFVs ( DIAMANTINA 1) NF 429 | G51: Pagamento referente a 50 % do serviço de engenharia, necessário a construção da UFVs. | H51: 5334.67 | I51: 44879 | J51: [CCC04054] | M51: Diamantina 1 _Outros | N51: Serviço/Taxas Ambientais | P51: Desenvolvimento de projeto - Ambiental / Outros | Q51: Diamantina 1 | R51: Não
B52: 7478 | C52: A201-MORI GERACAO II ENERGIA SOLAR S.A | D52: 000938 | E52: Outros - Serviços à UFV | F52: Atividades para liberação de execução de POT nas UFVs ( DIAMANTINA 1) NF 429 | G52: Pagamento referente a 50 % do serviço de engenharia, necessário a construção da UFVs. | H52: 5334.67 | I52: 44879 | J52: [CCC04054] | M52: Diamantina 1 _Outros | N52: Serviço/Taxas Ambientais | P52: Desenvolvimento de projeto - Ambiental / Outros | Q52: Diamantina 1 | R52: Não
B53: 6836 | C53: A201-MORI GERACAO II ENERGIA SOLAR S.A | D53: 000715 | E53: Outros - Serviços à UFV | F53: Desenvolvimento de projetos GLD (DIAMANTINA 1) NF 226 | G53: Pagamento referente a elaboracao de planos diretores, estudos de viabilidade necessário para a construção da UFv . | H53: 17500 | I53: 44832 | J53: [CCC03840] | M53: Diamantina 1 _Engenharia Executiva - Basica | N53: Engenharia Executiva - Basica | O53: GLD | P53: Desenvolvimento de projeto - Projetos Detalhada | Q53: Diamantina 1 | R53: Não
B54: 8073 | C54: A210-MORI GERACAO II - UFV DIAMANTINA 1 | D54: 0001145 | E54: Outros - Serviços à UFV | F54: PRESTAÇÃO DE SERVIÇOS UFVs ( DIAMANTINA 1 ) NF 960 VB AMBIENTAL | G54: Pagamento referente a Análise documental e elaboração de laudos de cubagem visando à instalação das Usinas Contratantes no estado de Minas Gerais . | H54: 1000 | I54: 44911 | J54: [CCC04173] | M54: Diamantina 1 _Outros | N54: Serviço/Taxas Ambientais | P54: Desenvolvimento de projeto - Ambiental / Outros | Q54: Diamantina 1 | R54: Não
B55: 7592 | C55: A201-MORI GERACAO II ENERGIA SOLAR S.A | D55: 001036 | E55: Outros - Serviços à UFV | F55: DAE - Dispença de Licenciamento ambiental UFV (DIAMANTINA 01 ) NF 906 | G55: Taxa necessária à avaliação de intervenção ambiental para a UFV. | H55: 1150 | I55: 44895 | J55: [CCC04108] | M55: Diamantina 1 _Outros | N55: Serviço/Taxas Ambientais | P55: Desenvolvimento de projeto - Ambiental / Outros | Q55: Diamantina 1 | R55: Não
B56: 8340 | C56: A401-MORI MINAS NEWCO IV ENERGIA SOLAR S.A | D56: 000976 | E56: Fat.Direito EPC ( GLD ) | F56: PRESTÇÃO DE SERVIÇOS UFVS ( CAMPO BELO 5 ) NF 297 | G56: Pagamento EM FATURAMENTO DIRETO, PRESTAÇÃO DE SERVIÇO DE VIGILANCIA DESARMADA , necessário à construção da UFV em contrato EPC . | H56: 20000 | I56: 44923 | J56: [CCC04223] | M56: Diamantina 1 _EPC_FD | N56: EPC - CLUSTER 1/2/3/4 | O56: GLD | P56: Construção - Serviços de Construção | Q56: Campo Belo 5 | R56: Sim
B57: 2051 | C57: A701-ARES 2 PARTICIPACOES S.A | D57: * | E57: Outros - Serviços à UFV | F57: JX AMBIENTAL - Procedimento Administrativo - DAIA de implantação de UFV - 50% iniciais - (Diamantina 2) | G57: * | H57: 10496.25 | I57: 44438 | J57: [CCC02461-01] | M57: Diamantina 2 _Outros | N57: Serviço/Taxas Ambientais | O57: JX AMBIENTAL | P57: Desenvolvimento de projeto - Ambiental / Outros | Q57: Diamantina 2 | R57: Não
B58: 2069 | C58: A701-ARES 2 PARTICIPACOES S.A | D58: * | E58: Outros - Serviços à UFV | F58: JX AMBIENTAL - Procedimento Administrativo - DAIA de implantação de rede rural - 50% iniciais - (Diamantina 2) | G58: * | H58: 11551.75 | I58: 44438 | J58: [CCC02461-01] | M58: Diamantina 2 _Outros | N58: Serviço/Taxas Ambientais | O58: JX AMBIENTAL | P58: Desenvolvimento de projeto - Ambiental / Outros | Q58: Diamantina 2 | R58: Não
B59: 2148 | C59: A201-MORI GERACAO II ENERGIA SOLAR S.A | D59: 000014 | E59: Outros - Serviços à UFV | F59: Execução de testes SPT - 10% iniciais - (Diamantina 2) | H59: 1750.59 | I59: 44455 | J59: [CCC02492-04] | M59: Diamantina 2 _Outros | N59: Serviço/Taxas Ambientais | P59: Desenvolvimento de projeto - Ambiental / Outros | Q59: Diamantina 2 | R59: Não
B60: 2239 | C60: A701-ARES 2 PARTICIPACOES S.A | D60: * | E60: Outros - Serviços à UFV | F60: JX AMBIENTAL - Taxa de Analise (Diamantina 2) | G60: * | H60: 532.44 | I60: 44466 | J60: [CCC02534-04] | M60: Diamantina 2 _Outros | N60: Serviço/Taxas Ambientais | O60: JX AMBIENTAL | P60: Desenvolvimento de projeto - Ambiental / Outros | Q60: Diamantina 2 | R60: Não
B61: 2240 | C61: A701-ARES 2 PARTICIPACOES S.A | D61: * | E61: Outros - Serviços à UFV | F61: JX AMBIENTAL - Taxa de Lenha (Diamantina 2) | G61: * | H61: 0.05 | I61: 44466 | J61: [CCC02534-05] | M61: Diamantina 2 _Outros | N61: Serviço/Taxas Ambientais | O61: JX AMBIENTAL | P61: Desenvolvimento de projeto - Ambiental / Outros | Q61: Diamantina 2 | R61: Não
B62: 2241 | C62: A701-ARES 2 PARTICIPACOES S.A | D62: * | E62: Outros - Serviços à UFV | F62: JX AMBIENTAL - Taxa de Madeira (Diamantina 2) | G62: * | H62: 56.56 | I62: 44466 | J62: [CCC02534-06] | M62: Diamantina 2 _Outros | N62: Serviço/Taxas Ambientais | O62: JX AMBIENTAL | P62: Desenvolvimento de projeto - Ambiental / Outros | Q62: Diamantina 2 | R62: Não
B63: 2242 | C63: A701-ARES 2 PARTICIPACOES S.A | D63: * | E63: Outros - Serviços à UFV | F63: JX AMBIENTAL - Taxa de Rep. Florestal (Diamantina 2) | G63: * | H63: 36.51 | I63: 44466 | J63: [CCC02534-07] | M63: Diamantina 2 _Outros | N63: Serviço/Taxas Ambientais | O63: JX AMBIENTAL | P63: Desenvolvimento de projeto - Ambiental / Outros | Q63: Diamantina 2 | R63: Não
B64: 2107 | C64: A701-ARES 2 PARTICIPACOES S.A | E64: Outros - Serviços à UFV | F64: JX AMBIENTAL - Procedimento Administrativo - DAIA de implantação de UFV - 40% intermediários - (Diamantina 2) | H64: 8397 | I64: 44455 | J64: [CCC02488-02] | M64: Diamantina 2 _Outros | N64: Serviço/Taxas Ambientais | O64: JX AMBIENTAL | P64: Desenvolvimento de projeto - Ambiental / Outros | Q64: Diamantina 2 | R64: Não
B65: 2284 | C65: A201-MORI GERACAO II ENERGIA SOLAR S.A | D65: 000026 | E65: Outros - Serviços à UFV | F65: Execução de testes SPT - Pagamento final (Diamantina 2) | H65: 5220 | I65: * | J65: [CCC02540] | M65: Diamantina 2 _Outros | N65: Serviço/Taxas Ambientais | P65: Desenvolvimento de projeto - Ambiental / Outros | Q65: Diamantina 2 | R65: Não
B66: 2305 | C66: A701-ARES 2 PARTICIPACOES S.A | E66: Fat. Direto (MBA-AT) | F66: Projetos AT - PROEL (Diamantina 2) | H66: 30000 | I66: 44481 | J66: [CCC02545] | K66: Diamantina 2 - CAPEX - Serviço AT - CCAP-C2_000008 | M66: Diamantina 2_Obras AT_FT | N66: Obras de AT | O66: MBA | P66: Conexão AT - Obras | Q66: Diamantina 2 | R66: Sim
B67: 2351 | C67: A701-ARES 2 PARTICIPACOES S.A | E67: Medição (MBA-AT) | F67: CONT. PROJETOS - Medição final de serviços (Diamantina 2) | H67: 15000 | I67: 44489 | J67: [CCC02581] | K67: Diamantina 2 - CAPEX - Serviço AT - CCAP-C2_000008 | M67: Diamantina 2_Obras AT_MD | N67: Obras de AT | O67: MBA | P67: Conexão AT - Obras | Q67: Diamantina 2 | R67: Não
B68: 2346 | C68: 0101-MORI HOLDING SA | D68: 001153 | E68: Outros - Serviços para Projetos | F68: Consultoria em servidão (Diamantina 2) GEOVANY | H68: 10000 | I68: 44489 | J68: [CCC02579] | M68: Diamantina 2 _Outros | N68: Serviço/Taxas Ambientais | P68: Desenvolvimento de projeto - Ambiental / Outros | Q68: Diamantina 2 | R68: Não
B69: 2362 | C69: A701-ARES 2 PARTICIPACOES S.A | E69: Outros - Serviços à UFV | F69: JX AMBIENTAL - Procedimento Administrativo - DAIA de implantação de UFV - 10% finais (Diamantina 2) | H69: 2099.25 | I69: 44498 | J69: [CCC02593] | M69: Diamantina 2 _Outros | N69: Serviço/Taxas Ambientais | O69: JX AMBIENTAL | P69: Desenvolvimento de projeto - Ambiental / Outros | Q69: Diamantina 2 | R69: Não
B70: 2371 | C70: A701-ARES 2 PARTICIPACOES S.A | D70: 000049 | E70: Medição (MBA-AT) | F70: Medição 0 - Adiantamento (Diamantina 2) | H70: 83000 | I70: 44531 | J70: [CCC02610-02] | K70: Diamantina 2 - CAPEX - Serviço AT - CCAP-C2_000008 | M70: Diamantina 2_Obras AT_MD | N70: Obras de AT | O70: MBA | P70: Conexão AT - Obras | Q70: Diamantina 2 | R70: Não
B71: 2611 | C71: A701-ARES 2 PARTICIPACOES S.A | E71: Outros - Serviços à UFV | F71: JX AMBIENTAL - Taxa de Analise (Diamantina 2) | G71: Taxa necessária à avaliação de intervenção ambiental para a UFV. | H71: 532.44 | I71: 44538 | J71: [CCC02746-01] | M71: Diamantina 2 _Outros | N71: Serviço/Taxas Ambientais | O71: JX AMBIENTAL | P71: Desenvolvimento de projeto - Ambiental / Outros | Q71: Diamantina 2 | R71: Não
B72: 2612 | C72: A701-ARES 2 PARTICIPACOES S.A | E72: Outros - Serviços à UFV | F72: JX AMBIENTAL - Taxa Florestal - Lenha (Diamantina 2) | G72: Taxa necessária à avaliação de intervenção ambiental para a UFV. | H72: 0.05 | I72: 44538 | J72: [CCC02746-02] | M72: Diamantina 2 _Outros | N72: Serviço/Taxas Ambientais | O72: JX AMBIENTAL | P72: Desenvolvimento de projeto - Ambiental / Outros | Q72: Diamantina 2 | R72: Não
B73: 2647 | C73: A701-ARES 2 PARTICIPACOES S.A | E73: Outros - Serviços à UFV | F73: JX AMBIENTAL - Procedimento Administrativo - DAIA de implantação de rede rural - 40% intermediários - (Diamantina 2) | G73: Segunda parcela de serviço de consultoria contratado cumprimento de legislação ambiental. | H73: 9241.4 | I73: 44546 | J73: [CCC02743-07] | M73: Diamantina 2 _Outros | N73: Serviço/Taxas Ambientais | O73: JX AMBIENTAL | P73: Desenvolvimento de projeto - Ambiental / Outros | Q73: Diamantina 2 | R73: Não
B74: 2844 | C74: A701-ARES 2 PARTICIPACOES S.A | E74: Outros - Serviços à UFV | F74: JX AMBIENTAL - Taxa de Analise - Rede - (Diamantina 2) | H74: 605.83 | I74: 44604 | J74: [CCC02693-04] | M74: Diamantina 2 _Outros | N74: Serviço/Taxas Ambientais | O74: JX AMBIENTAL | P74: Desenvolvimento de projeto - Ambiental / Outros | Q74: Diamantina 2 | R74: Não
B75: 2845 | C75: A701-ARES 2 PARTICIPACOES S.A | E75: Outros - Serviços à UFV | F75: JX AMBIENTAL - Taxa de Lenha - Rede - Complementar (Diamantina 2) | H75: 36.24 | I75: 44604 | J75: [CCC02693-05] | M75: Diamantina 2 _Outros | N75: Serviço/Taxas Ambientais | O75: JX AMBIENTAL | P75: Desenvolvimento de projeto - Ambiental / Outros | Q75: Diamantina 2 | R75: Não
B76: 2846 | C76: A701-ARES 2 PARTICIPACOES S.A | E76: Outros - Serviços à UFV | F76: JX AMBIENTAL - Taxa de Madeira - Rede - Complementar (Diamantina 2) | H76: 59.39 | I76: 44604 | J76: [CCC02693-06] | M76: Diamantina 2 _Outros | N76: Serviço/Taxas Ambientais | O76: JX AMBIENTAL | P76: Desenvolvimento de projeto - Ambiental / Outros | Q76: Diamantina 2 | R76: Não
B77: 2870 | C77: A701-ARES 2 PARTICIPACOES S.A | E77: Outros - Serviços à UFV | F77: JX AMBIENTAL - Taxa de Analise - UFV - (Diamantina 2) | G77: Taxa necessária à avaliação de intervenção ambiental para a UFV. | H77: 106.78 | I77: 44580 | J77: [CCC02856-01] | M77: Diamantina 2 _Outros | N77: Serviço/Taxas Ambientais | O77: JX AMBIENTAL | P77: Desenvolvimento de projeto - Ambiental / Outros | Q77: Diamantina 2 | R77: Não
B78: 2871 | C78: A701-ARES 2 PARTICIPACOES S.A | E78: Outros - Serviços à UFV | F78: JX AMBIENTAL - Taxa de Lenha - UFV - Complementar (Diamantina 2) | G78: Taxa necessária à avaliação de intervenção ambiental para a UFV. | H78: 0.06 | I78: 44580 | J78: [CCC02856-02] | M78: Diamantina 2 _Outros | N78: Serviço/Taxas Ambientais | O78: JX AMBIENTAL | P78: Desenvolvimento de projeto - Ambiental / Outros | Q78: Diamantina 2 | R78: Não
B79: 2872 | C79: A701-ARES 2 PARTICIPACOES S.A | E79: Outros - Serviços à UFV | F79: JX AMBIENTAL - Taxa de Madeira - UFV - Complementar (Diamantina 2) | G79: Taxa necessária à avaliação de intervenção ambiental para a UFV. | H79: 11.85 | I79: 44580 | J79: [CCC02856-03] | M79: Diamantina 2 _Outros | N79: Serviço/Taxas Ambientais | O79: JX AMBIENTAL | P79: Desenvolvimento de projeto - Ambiental / Outros | Q79: Diamantina 2 | R79: Não
B80: 2886 | C80: A701-ARES 2 PARTICIPACOES S.A | E80: Outros - Serviços à UFV | F80: JX AMBIENTAL - Taxa de Analise - (Diamantina 2) | G80: Taxa necessária à avaliação de intervenção ambiental para a UFV. | H80: 639.22 | I80: 44580 | J80: [CCC02857] | M80: Diamantina 2 _Outros | N80: Serviço/Taxas Ambientais | O80: JX AMBIENTAL | P80: Desenvolvimento de projeto - Ambiental / Outros | Q80: Diamantina 2 | R80: Não
B81: 2853 | C81: A201-MORI GERACAO II ENERGIA SOLAR S.A | D81: 000134 | E81: Outros - Serviços à UFV | F81: Revisão de coordenadas de terreno - Soluç. Agrimensura (Diamantina 2) | G81: Serviço contatado para revisar coordenadas de projetos em desenvolvimento, com revalidação e certificação de dados e documentação. | H81: 4235.3 | I81: * | J81: [CCC02851-02] | M81: Diamantina 2 _Outros | N81: Serviço/Taxas Ambientais | P81: Desenvolvimento de projeto - Ambiental / Outros | Q81: Diamantina 2 | R81: Não
B82: 2961 | C82: A201-MORI GERACAO II ENERGIA SOLAR S.A | D82: SCOMP-000002 | E82: Outros - Compras para a UFV | F82: Reatores de aterramento ADELCO (Diamantina 2) | G82: Modelos 13,8kv - Pot:375kW Xreator: 50,8Ω (RNA 134750-7); Pot:1000kW Xreator: 25,4Ω (RNA 67376-13); Pot:1000kW Xreator: 25,4Ω (RNA 67376-13) | H82: 0 | I82: * | J82: [CCC02908] | M82: Diamantina 2 | N82: Controle da Lais | P82: Controle da Lais | Q82: Diamantina 2 | R82: Não
B83: 3090 | C83: A701-ARES 2 PARTICIPACOES S.A | E83: Outros - Serviços à UFV | F83: JX AMBIENTAL - Procedimento Administrativo - DAIA de implantação de rede rural - 10% finais - (Diamantina 2) | H83: 2310.35 | I83: 44608 | J83: [CCC02919-04] | M83: Diamantina 2 _Outros | N83: Serviço/Taxas Ambientais | O83: JX AMBIENTAL | P83: Desenvolvimento de projeto - Ambiental / Outros | Q83: Diamantina 2 | R83: Não
B84: 3119 | C84: A201-MORI GERACAO II ENERGIA SOLAR S.A | D84: 000206 | E84: Fat. Direto (MBA-MT) | F84: Desenvolvimento de Projeto MT (Diamantina 2) | G84: Compra feita em Faturamento Direto, em contrato de obras MT externas à UFV. | H84: 18172.22 | I84: 44608 | J84: [CCC02962-02] | K84: Diamantina 2 - CAPEX - Serviço MT - CCAP-C2_000019 Descontado Contrato MBA | M84: Diamantina 2 _Obras MT_FD | N84: Obras de MT | O84: MBA | P84: Conexão MT - Obras | Q84: Diamantina 2 | R84: Sim
B85: 4179 | C85: A201-MORI GERACAO II ENERGIA SOLAR S.A | D85: 000239 | E85: Medição (MBA-MT) | F85: Medição 01 (Diamantina 2) | G85: Medição de serviços contratados para execução de projeto de rede MT, externos à UFV. | H85: 487000 | I85: 44648 | J85: [CCC03090-01] | K85: Diamantina 2 - CAPEX - Serviço MT - CCAP-C2_000019 (Valor a ser Restituido) | M85: Diamantina 2 _Obras MT_MD | N85: Obras de MT | O85: MBA | P85: Conexão MT - Obras | Q85: Diamantina 2 | R85: Não
B86: 4637 | C86: A201-MORI GERACAO II ENERGIA SOLAR S.A | D86: 000304 | E86: Medição (MBA-AT) | F86: Medição 01 (Diamantina 2) | G86: Medição de serviços, suportando desenvolvimento de serviços em obras no contrato AT. | H86: 124500 | I86: 44676 | J86: [CCC03178-06] | K86: Diamantina 2 - CAPEX - Serviço AT - CCAP-C2_000008 | M86: Diamantina 2_Obras AT_MD | N86: Obras de AT | O86: MBA | P86: Conexão AT - Obras | Q86: Diamantina 2 | R86: Não
B87: 4735 | C87: A201-MORI GERACAO II ENERGIA SOLAR S.A | D87: 000294 | E87: Outros - Compras para a UFV | F87: Archtech - Testes de PullOuT_Biotec - Adiantamento (Diamantina 2) | H87: 3389.12 | I87: 44678 | J87: [CCC03145-48] | M87: Diamantina 2 _Outros | N87: Serviço/Taxas Ambientais | P87: Desenvolvimento de projeto - Ambiental / Outros | Q87: Diamantina 2 | R87: Não
B88: 4735 | C88: A201-MORI GERACAO II ENERGIA SOLAR S.A | D88: 000358 | E88: Outros - Compras para a UFV | F88: Archtech - Testes de PullOuT_Biotec - Finalização (Diamantina 2) | G88: Faturamento Direto de serviço de pullout, em testes de solo para dimenskonamento de estruturas | H88: 30502.1 | I88: 44701 | J88: [CCC03265-48] | M88: Diamantina 2 _Outros | N88: Serviço/Taxas Ambientais | P88: Desenvolvimento de projeto - Ambiental / Outros | Q88: Diamantina 2 | R88: Não
B89: 2 | C89: A201-MORI GERACAO II ENERGIA SOLAR S.A | D89: 000406 | E89: Fat. Direto (ATI) | F89: SUPERVISORIO - Ciclo 2 - Gateways e remota (Diamantina 2) NF 1708 | G89: Compra inicial de equipamentos para implementação de sistema supervisório na UFV. Compra com NF de venda futura. | H89: 27761.33 | I89: 44736 | J89: [CCC03287-03] | M89: Diamantina 2 _SGD | N89: SGD - Supervisorio Geração Distribuida | O89: ATI | P89: Sistemas de Monitoramento - Supervisório | Q89: Diamantina 2 | R89: Não
B90: 1 | C90: A201-MORI GERACAO II ENERGIA SOLAR S.A | D90: 000418 | E90: Fat. Direto (ATI) | F90: SUPERVISORIO - Ciclo 2 - Baterias, desktops, switch e acessórios (Diamantina 2) NF 1723 | G90: Compra inicial de equipamentos para implementação de sistema supervisório na UFV. Compra com NF de venda futura. | H90: 39819.52 | I90: 44736 | J90: [CCC03287-18] | M90: Diamantina 2 _SGD | N90: SGD - Supervisorio Geração Distribuida | O90: ATI | P90: Sistemas de Monitoramento - Supervisório | Q90: Diamantina 2 | R90: Não
B91: 5276 | C91: A201-MORI GERACAO II ENERGIA SOLAR S.A | D91: 000438 | E91: Outros - Serviços à UFV | F91: Eng. Executiva GLD - Entrega 01 - P01_05 (Diamantina 2) | G91: Pagamento inicial suportando contrato de desenvolvimento de projetos executivos, na entrega de Projetos de Sistemas de Drenagem | H91: 3500 | I91: 44753 | J91: [CCC03314-09] | M91: Diamantina 2_Engenharia Executiva - Detalhada | N91: Engenharia Executiva - Detalhada | O91: GLD | P91: Desenvolvimento de projeto - Projetos Detalhada | Q91: Diamantina 2 | R91: Não
B92: 5281 | C92: A201-MORI GERACAO II ENERGIA SOLAR S.A | D92: 000442 | E92: Outros - Serviços à UFV | F92: Eng. Executiva GLD - Entrega 02 - P01_03 (Diamantina 2) | G92: Pagamento inicial suportando contrato de desenvolvimento de projetos executivos, na entrega de Projetos de Sistemas de Drenagem | H92: 5878.3 | I92: 44753 | J92: [CCC03314-14] | M92: Diamantina 2_Engenharia Executiva - Detalhada | N92: Engenharia Executiva - Detalhada | O92: GLD | P92: Desenvolvimento de projeto - Projetos Detalhada | Q92: Diamantina 2 | R92: Não
B93: 6082 | C93: A201-MORI GERACAO II ENERGIA SOLAR S.A | D93: 000486 | E93: Medição (EPC) | F93: Construção e Montagem IMPLANTAR - Adiantamento contratual (Diamantina 2) | G93: Pagamento de adiantamento contratual de 15% do total de contrato EPC de construção da UFV | H93: 383467.5 | I93: 44769 | J93: [CCC03380-02] | K93: CANCELADO DUPLO A201 000523 LINHA 6259 | M93: Diamantina 2_EPC_MD | N93: EPC - CLUSTER 1/2/3/4 | O93: * | P93: Não Controlado | Q93: Diamantina 2 | R93: Não
B94: 6126 | C94: A201-MORI GERACAO II ENERGIA SOLAR S.A | D94: 000551 | E94: Fat. Direto (MBA-MT) | F94: Transformador Monofásico - Adiantamento (Diamantina 2) | G94: Compra feita em Faturamento Direto, em contrato de obras MT externas à UFV. | H94: =6461.02/2 -> 3230.51 | I94: 44795 | J94: [CCC03396-02] | M94: Diamantina 2 _Obras MT_FD | N94: Obras de MT | O94: MBA | P94: Conexão MT - Obras Transferencia | Q94: Diamantina 2 | R94: Sim
B95: 6405 | C95: A201-MORI GERACAO II ENERGIA SOLAR S.A | D95: 000582 | E95: Outros - Compras para a UFV | F95: Estação solarimétrica – Hukseflux Diamantina 2 NF 7023 PC 003178 | G95: Compra de equipamento adicional de monitoração de condições atmosféricas, adiantamento 30 % . | H95: 13959.486 | I95: 44802 | J95: [CCC03542] | M95: Diamantina 2 _Estação solarimétrica | N95: Estação solarimétrica | P95: Sistemas de Monitoramento - Estações Solarimétricas | Q95: Diamantina 2 | R95: Não
B96: 6259 | C96: A201-MORI GERACAO II ENERGIA SOLAR S.A | D96: 000523 | E96: Medição (EPC) | F96: SERVIÇO DE MAO DE OBRA E EQUIPAMENTOS / FERRAMENTAL ( DIAMANTINA 2) NF 658 | G96: Pagamento referente a 1° medição mão de obra e equipamentos ( Não foi medição, isto se trata-se de adiantamento) | H96: 383467.5 | I96: 44785 | J96: [CCC03380-02] | M96: Diamantina 2_EPC_MD | N96: EPC - CLUSTER 1/2/3/4 | O96: IMPLANTAR | P96: Construção - Serviços de Construção | Q96: Diamantina 2 | R96: Não
B97: 6800 | C97: A201-MORI GERACAO II ENERGIA SOLAR S.A | D97: 000705 | E97: Outros - Serviços à UFV | F97: SERVIÇOS FUNDIÁRIOS PTRF - (Diamantina 2 ) NF 125 | G97: Pagamento referente ao serviço de consultoria contratado cumprimento de legislação ambiental. | H97: 10000 | I97: 44830 | J97: [CCC03821] | M97: Diamantina 2 _Outros | N97: Serviço/Taxas Ambientais | P97: Desenvolvimento de projeto - Ambiental / Outros | Q97: Diamantina 2 | R97: Não
B98: 7479 | C98: A201-MORI GERACAO II ENERGIA SOLAR S.A | D98: 000939 | E98: Outros - Serviços à UFV | F98: Atividades para liberação de execução de POT nas UFVs ( DIAMANTINA 2) NF 430 | G98: Pagamento referente a 50 % do serviço de engenharia, necessário a construção da UFVs. | H98: 5334.67 | I98: 44879 | J98: [CCC04054] | M98: Diamantina 2 _Outros | N98: Serviço/Taxas Ambientais | P98: Desenvolvimento de projeto - Ambiental / Outros | Q98: Diamantina 2 | R98: Não
B99: 6837 | C99: A201-MORI GERACAO II ENERGIA SOLAR S.A | D99: 000716 | E99: Outros - Serviços à UFV | F99: Desenvolvimento de projetos GLD (DIAMANTINA 2) NF 227 | G99: Pagamento referente a elaboracao de planos diretores, estudos de viabilidade necessário para a construção da UFv . | H99: 17500 | I99: 44832 | J99: [CCC03840] | M99: Diamantina 2 _Engenharia Executiva - Basica | N99: Engenharia Executiva - Basica | O99: GLD | P99: Desenvolvimento de projeto - Projetos Detalhada | Q99: Diamantina 2 | R99: Não
B100: 7593 | C100: A201-MORI GERACAO II ENERGIA SOLAR S.A | D100: 001037 | E100: Outros - Serviços à UFV | F100: DAE - Dispença de Licenciamento ambiental UFV (DIAMANTINA 02 ) NF 907 | G100: Taxa necessária à avaliação de intervenção ambiental para a UFV. | H100: 1150 | I100: 44895 | J100: [CCC04108] | M100: Diamantina 2 _Outros | N100: Serviço/Taxas Ambientais | P100: Desenvolvimento de projeto - Ambiental / Outros | Q100: Diamantina 2 | R100: Não
...

Sheet Alterações_Detalhes por Usina
B2: Alterações : 29/08/2024
B3: Data | C3: UFV | D3: Tipo | E3: Valor | F3: Observações
B4: 45371 | C4: Diamantina 1 | D4: Serviços Auxiliares - Drenagem | E4: 150000 | F4: 0
B5: 45383 | C5: São Sebastião 4 | D5: Serviços Auxiliares - Drenagem | E5: 755406.23 | F5: Alterado valor que estava em estimado (Era estimado em 800.000). Aguardando contrato
B6: 45356 | C6: Varias | D6: Full EPC - Contrato | E6: 2906636.1 | F6: Adicionado aditivo de contrato sobressalentes da Weg varias usinas. R$2.906.636,06
B7: 45356 | C7: Varias | D7: Bases de Contaniers | E7: 297578 | F7: Adicionado contrato base de contaiers da GR ENGENHARIA Frei Ino, Indaiabira 1 e 2
B8: 45356 | C8: Varias | D8: Bases de Contaniers | E8: 459002 | F8: Adicionado contrato base de contaiers da AP Engecon Campo Belo 3 & 4 e São Sebastião 1 & 3
B9: 45356 | C9: Varias | D9: Bases de Contaniers | E9: 459600 | F9: Adicionado contrato base de contaiers da MIPE Bambui e Cassia
B10: 45356 | C10: Varias | D10: Bases de Contaniers | E10: 1477000.5 | F10: Adicionado contrato base de contaiers da R&M Solar Varias
B11: 45385 | C11: Patrocinio 2 | D11: Construção - Serviços de Construção | E11: 581550.83 | F11: Tirado de Escopo Comerc e adicionado a Construção - Serviços de Construção
B12: 45385 | C12: Patrocinio 3 | D12: Construção - Serviços de Construção | E12: 578449.47 | F12: Tirado de Escopo Comerc e adicionado a Construção - Serviços de Construção
B13: 45385 | C13: Santo Antônio do Amparo 1 | D13: Serviços Auxiliares - Drenagem | E13: 89345.02 | F13: Aditivo regularição da Drenagem
B14: 45386 | C14: Paracatu 4 | D14: Serviços Auxiliares - Drenagem | E14: 83261.88 | F14: Aditivo de Paracatu 4 adversidades apresentadas em projeto.
B15: 45390 | C15: São Sebastião 4 | D15: Serviços Auxiliares - Supressão Vegetal | E15: 0 | F15: Contrato para acerto escopo fornecimento da Rima sem custo
B16: 45391 | C16: Diamantina 2 | D16: Serviços Auxiliares - Drenagem | E16: 164771.5 | F16: Complemento contrato Drenagem.
... B27: 45398 | C27: Muzambinho 1 | D27: Serviços Auxiliares - Supressão Vegetal | E27: 21500 | F27: Aditivo 2, prestação de serviços na UFV Muzabinho.
B28: 45434 | C28: Campo Belo 1 | D28: Serviços Auxiliares - Drenagem | E28: 94504.9 | F28: 0
B29: 45434 | C29: Campo Belo 2 | D29: Serviços Auxiliares - Drenagem | E29: 55921 | F29: 0
B30: 45434 | C30: Campo Belo 5 | D30: Conexão MT - Obras | E30: 42000 | F30: Linha Viva Campo Belo 5
B31: 45437 | C31: Diamantina 1 | D31: Serviços Auxiliares - Drenagem | E31: 188709 | F31: Orci - UnitárioTotalCOMPLEMENTO DRENAGEM - DIAMANTINA I
B32: 45778 | C32: Pains 3 | D32: Serviços Auxiliares - Drenagem | E32: 22800 | F32: Drenagem UFV Pains 03 - Canaleta meia Cana
B33: 45778 | C33: São Sebastião 6 | D33: Serviços Auxiliares - Drenagem | E33: 227075.59 | F33: Serviço referente drenagem de solo UFV São Sebastião
B34: 45414 | C34: Campo Belo 2 | D34: Conexão MT - Obras | E34: 154000 | F34: Linha Viva Campo Belo 2
B35: 45419 | C35: Três Corações 3 | D35: Conexão MT - Obras | E35: 15000 | F35: Realocação dos postes 13, 14 e 15 atender embargo do proprietário.
B36: 45420 | C36: Patrocinio 2 | D36: Bases de Contaniers | E36: 86616.4 | F36: Execução de infra subterrânea para sistema de CFTV.
B37: 45420 | C37: Patrocinio 3 | D37: Bases de Contaniers | E37: 90543.4 | F37: Execução de infra subterrânea para sistema de CFTV.
B38: 45420 | C38: EDN | D38: Full EPC - Contrato | E38: 1059739.9 | F38: Sobressalentes do contrato Weg
B39: 45420 | C39: Jaboticatubas | D39: Serviços Auxiliares - Drenagem | E39: 400000 | F39: Contrato de complemento feito com a Orci.
B40: 45432 | C40: Paracatu 4 | D40: Serviços Auxiliares - Terraplanagem | E40: 297803.7 | F40: Aumento Escavação, carga e transporte.
B41: 45448 | C41: Muzambinho 1 | D41: Conexão MT - Obras Transferencia | E41: 302750 | F41: Previsão Estimado aditivos Obras MT
... B51: 45453 | C51: Campo Belo 2 | D51: Serviços Auxiliares - Terraplanagem | E51: 290585.06 | F51: São referentes a limpeza de bacias, além da manutenção da drenagem
B52: 45493 | C52: Muzambinho 1 / Ouro Fino /3 Corações | D52: Construção - Serviços de Construção - NOVA MORADA | E52: ​250.600,26 | F52: Construção Offices Abandonados EPC GLD
B53: 45533 | C53: Diamantina 1 | D53: Drenagem | E53: 65000 | F53: Correção Erosões | G53: Escopo COMERC | H53: Estimado Engenharia
B54: 45533 | C54: Diamantina 1 | D54: Construção - Serviços de Construção | E54: 10000 | F54: Insumos energização | G54: Escopo COMERC | H54: 1830.62
B55: 45533 | C55: Diamantina 1 | D55: Construção - Serviços de Construção | E55: 10000 | F55: Instalação TPs e TCs | G55: Feito | H55: 9980
B56: 45533 | C56: Diamantina 1 | D56: Construção - Serviços de Construção | E56: 94815 | F56: Cercamento Bacia de Contenção - Engetela | G56: Escopo COMERC | H56: Estimado Engenharia
B57: 45533 | C57: Diamantina 2 | D57: Construção - Serviços de Construção | E57: 12900 | F57: Cercamento Bacia de Contenção - Engetela | G57: Escopo COMERC | H57: Estimado Engenharia
B58: 45533 | C58: Diamantina 2 | D58: Construção - Serviços de Construção | E58: 20000 | F58: Limpeza geral da usina | G58: Escopo COMERC | H58: Estimado Engenharia
B59: 45533 | C59: Diamantina 2 | D59: Construção - Serviços de Construção | E59: 10000 | F59: Finalização do quadro serviços auxiliares | G59: Escopo COMERC | H59: Estimado Engenharia
B60: 45533 | C60: Diamantina 2 | D60: Construção - Serviços de Construção | E60: 10000 | F60: Insumos energização | G60: Escopo COMERC | H60: Estimado Engenharia
B61: 45533 | C61: Diamantina 2 | D61: Construção - Serviços de Construção | E61: 10000 | F61: Instalação TPs e TCs | G61: Escopo COMERC | H61: Estimado Engenharia
B62: 45533 | C62: Jaboticatubas | D62: Construção - Serviços de Construção | E62: 12900 | F62: Cercamento Bacia de Contenção - Engetela | G62: Escopo COMERC | H62: Estimado Engenharia
B63: 45533 | C63: Jaboticatubas | D63: Drenagem | E63: 80000 | F63: Estimado para execução de limpeza/desassoreamento de córrego nas proximidades de UFV JABOTICATUBAS / Cercamento Engetela | G63: Escopo COMERC | H63: Estimado Engenharia
B64: 45533 | C64: Paracatu 8 | D64: Construção - Serviços de Construção | E64: 1200 | F64: Compra 02 cadeiras que foram quebradas durante implantação | G64: Escopo COMERC | H64: Estimado Engenharia
B65: 45533 | C65: Lagoa Formosa | D65: Construção - Serviços de Construção | E65: 63000 | F65: Finalização de pendências - RM Solar | G65: Escopo COMERC | H65: Estimado Engenharia | I65: Virou contrato e já salvo na pasta.
B66: 45533 | C66: Lagoa Formosa | D66: Construção - Serviços de Construção | E66: 5000 | F66: Cercamento Bacia de Contenção | G66: Escopo COMERC | H66: Estimado Engenharia
B67: 45533 | C67: Lagoa Formosa | D67: Construção - Serviços de Construção | E67: 5000 | F67: Lançamento cabos comunicação inversores | G67: Escopo COMERC | H67: Estimado Engenharia
B68: 45533 | C68: Lagoa Formosa | D68: Construção - Serviços de Construção | E68: 5000 | F68: 10 caixas danificadas pela roçagem | G68: Escopo COMERC | H68: Estimado Engenharia
B69: 45533 | C69: Lagoa Formosa | D69: Construção - Serviços de Construção | E69: 10000 | F69: Prontuário de instalações elétricas | G69: Escopo COMERC | H69: Estimado Engenharia
B70: 45533 | C70: Lagoa Formosa | D70: Desenvolvimento de projeto - Ambiental / Outros | E70: 10410 | F70: Corte madeiras da supressão vegetal | G70: Escopo COMERC | H70: Estimado Engenharia
B71: 45533 | C71: Patos de Minas 01 | D71: Construção - Serviços de Construção | E71: 2000 | F71: Desobstrução Eletrodutos CFTV | G71: Escopo COMERC | H71: Estimado Engenharia
B72: 45533 | C72: Patos de Minas 01 | D72: Serviços Auxiliares - Drenagem | E72: 40000 | F72: Recuperação Via Drenagem com Trincas | G72: Escopo COMERC | H72: Estimado Engenharia
B73: 45533 | C73: Patos de Minas 03 | D73: Serviços Auxiliares - Drenagem | E73: 148750 | F73: Adequação Drenagem | G73: Já Virou contrato | H73: Estimado Engenharia
B74: 45533 | C74: Patos de Minas 03 | D74: Construção - Serviços de Construção | E74: 5000 | F74: Cercamento Bacia de Contenção | G74: Escopo COMERC | H74: Estimado Engenharia
B75: 45533 | C75: Patos de Minas 03 | D75: Construção - Serviços de Construção | E75: 15000 | F75: Troca Poste Danificado | G75: Escopo COMERC | H75: Estimado Engenharia
B76: 45533 | C76: Patos de Minas 04 | D76: Serviços Auxiliares - Drenagem | E76: 174920 | F76: Adequação Drenagem | G76: Serviços Auxiliares - Drenagem | H76: Estimado Engenharia | I76: Virou contrato e já salvo na pasta.
B77: 45533 | C77: Patos de Minas 04 | D77: Construção - Serviços de Construção | E77: 36500 | F77: Canaleta de Drenagem - RM Solar | G77: Escopo COMERC | H77: Estimado Engenharia
B78: 45533 | C78: Patos de Minas 04 | D78: Sistemas de Monitoramento - CFTV | E78: =12000-3920 -> 8080 | F78: Recomposição Valas CFTV e Pendências Civis | G78: Escopo COMERC | H78: Estimado Engenharia
B79: 45533 | C79: Patos de Minas 04 | D79: Construção - Serviços de Construção | E79: 12000 | F79: Cercamento Bacia de Contenção | G79: Escopo COMERC | H79: Estimado Engenharia
B80: 45533 | C80: Patos de Minas 04 | D80: Construção - Serviços de Construção | E80: 5000 | F80: Cortes eucaliptos fora da área arrendada | G80: Escopo COMERC | H80: Estimado Engenharia
B81: 45533 | C81: Patos de Minas 04 | D81: Construção - Serviços de Construção | E81: 2000 | F81: Compra espuma expansiva | G81: Escopo COMERC | H81: Estimado Engenharia
B82: 45533 | C82: Patos de Minas 07 | D82: Construção - Serviços de Construção | E82: 2000 | F82: Lançamento Cabo Comunicação Communication Box | G82: Escopo COMERC | H82: Estimado Engenharia
B83: 45533 | C83: Patos de Minas 08 | D83: Sistemas de Monitoramento - CFTV | E83: 10000 | F83: Desobstrução Eletrodutos CFTV | G83: Escopo COMERC | H83: Estimado Engenharia
B84: 45533 | C84: Patos de Minas 08 | D84: Construção - Serviços de Construção | E84: 2000 | F84: Lançamento Cabo Comunicação Communication Box | G84: Escopo COMERC | H84: Estimado Engenharia
B85: 45533 | C85: Patrocínio 02 | D85: Construção - Serviços de Construção | E85: 5000 | F85: Aquisição Itens Adequação Aterramento Inversores | G85: Escopo COMERC | H85: Estimado Engenharia
B86: 45533 | C86: Patrocínio 02 | D86: Construção - Serviços de Construção | E86: 10000 | F86: Prontuário de instalações elétricas | G86: Escopo COMERC | H86: Estimado Engenharia
B87: 45533 | C87: Patrocínio 03 | D87: Construção - Serviços de Construção | E87: 5006 | F87: Aquisição Itens Adequação Aterramento Inversores | G87: Escopo COMERC | H87: Estimado Engenharia
B88: 45533 | C88: Patrocínio 03 | D88: Construção - Serviços de Construção | E88: 10000 | F88: Aquisição Equipamentos Solarimétrica | G88: Escopo COMERC Contratado (9993,78) | H88: Estimado Engenharia
B89: 45533 | C89: Patrocínio 03 | D89: Construção - Serviços de Construção | E89: 10000 | F89: Prontuário de instalações elétricas | G89: Escopo COMERC | H89: Estimado Engenharia
B90: 45533 | C90: Varjão de Minas 04 | D90: Serviços Auxiliares - Drenagem | E90: 48000 | F90: Recuperação Dispositivo Drenagem | G90: Escopo COMERC | H90: Estimado Engenharia
... B97: 45533 | C97: Divinópolis 1 | D97: Drenagem | E97: 40000 | F97: Dessasoreamento da lagoa vizinha e bacia de contenção | G97: Escopo COMERC | H97: Estimado Engenharia
B98: 45533 | C98: Divinópolis 2 | D98: Drenagem | E98: 63500 | F98: Dessasoreamento da lagoa vizinha (MAR E AR SERVIÇOS) | G98: Escopo COMERC | H98: Estimado Engenharia | I98: Virou contrato e já salvo na pasta.
B99: 45533 | C99: Divinópolis 2 | D99: Drenagem | E99: 25000 | F99: Aluguel de caminhão para dessasoreamento | G99: Escopo COMERC | H99: Estimado Engenharia
B100: 45533 | C100: Divinópolis 2 | D100: Construção - Serviços de Construção | E100: =10000+14800 -> 24800 | F100: Cercamento de bacias de contenção | G100: Escopo COMERC | H100: Estimado Engenharia
B101: 45533 | C101: Divinópolis 3 | D101: Sistemas de Monitoramento - CFTV | E101: 5000 | F101: Adequação de infra e limpeza de caixas de passagem para CFTV | G101: Escopo COMERC | H101: Estimado Engenharia
B102: 45533 | C102: Formiga 6 | D102: Construção - Serviços de Construção | E102: 10000 | F102: Cercamento de bacias de contenção | G102: Escopo COMERC | H102: Estimado Engenharia
B103: 45533 | C103: Formiga 6 | D103: Construção - Serviços de Construção | E103: 10000 | F103: Identificação geral da planta | G103: Escopo COMERC | H103: Estimado Engenharia
B104: 45533 | C104: Formiga 6 | D104: Desenvolvimento de projeto - Ambiental / Outros | E104: 44949.15 | F104: PRAD - Sobra do Contrato assinado | G104: Escopo COMERC | H104: Estimado Engenharia
B105: 45533 | C105: Formiga 6 | D105: Construção - Serviços de Construção | E105: 10000 | F105: Excecução de punch list geral (cercamento, tracker, office) | G105: Escopo COMERC | H105: Estimado Engenharia
B106: 45533 | C106: Formiga 6 | D106: Construção - Serviços de Construção | E106: 10000 | F106: Limpeza fina da obra | G106: Escopo COMERC | H106: Estimado Engenharia
B107: 45533 | C107: Pains 3 | D107: Construção - Serviços de Construção | E107: 10000 | F107: Cercamento de bacias de contenção | G107: Escopo COMERC | H107: Estimado Engenharia
B108: 45533 | C108: Passos 4 | D108: Construção - Serviços de Construção | E108: 25000 | F108: Roçagem da planta | G108: Escopo COMERC | H108: Estimado Engenharia
B109: 45533 | C109: Passos 4 | D109: Construção - Serviços de Construção | E109: 10000 | F109: Cercamento de bacias de contenção | G109: Escopo COMERC | H109: Estimado Engenharia
B110: 45533 | C110: Pedra do indaiá 1 | D110: Construção - Serviços de Construção | E110: 5000 | F110: Retoque civil | G110: Escopo COMERC | H110: Estimado Engenharia
B111: 45533 | C111: Pedra do indaiá 1 | D111: Construção - Serviços de Construção | E111: 5000 | F111: Limpeza final | G111: Escopo COMERC | H111: Estimado Engenharia
B112: 45533 | C112: Pedra do indaiá 1 | D112: Drenagem | E112: 15000 | F112: Subsituição de travessia de drenagem (problema projeto Enersolar/LM) | G112: Escopo COMERC | H112: Estimado Engenharia
... B131: 45533 | C131: São Sebastião 6 | D131: Construção - Serviços de Construção | E131: 5000 | F131: Adequação de cercamento do terreno do proprietário | G131: Escopo COMERC | H131: Estimado Engenharia
B132: 45533 | C132: Varginha 1 | D132: Drenagem | E132: 1126034.1 | F132: Valor previsto da execução do projeto ofertado pela Baldoni. Execução do serviço (em análise da LM, valor previsto na REV00 era de R$400.000,00). | G132: Drenagem | H132: Estimado Engenharia | I132: Virou contrato e já salvo na pasta.
B133: 45533 | C133: Varginha 1 | D133: Sistemas de Monitoramento - CFTV - Escopo COMERC | E133: 15000 | F133: Refazimento de trecho do CFTV, valor estimado. | G133: Escopo COMERC | H133: Estimado Engenharia | I133: Ja realizado e Fica em Escopo Comerc
B134: 45533 | C134: Varginha 2 | D134: Drenagem | E134: 832038.75 | F134: Valor previsto da execução do projeto ofertado pela Baldoni.Execução do serviço (em análise da LM, valor previsto na REV00 era de R$400.000,00). | G134: Drenagem | H134: Estimado Engenharia | I134: Virou contrato e já salvo na pasta.
B135: 45533 | C135: Varginha 2 | D135: Sistemas de Monitoramento - CFTV - Escopo COMERC | E135: 15000 | F135: Refazimento de trecho do CFTV, valor estimado. | G135: Escopo COMERC | H135: Estimado Engenharia | I135: Ja realizado e Fica em Escopo Comerc
B136: 45533 | C136: Varginha 5 | D136: Sistemas de Monitoramento - CFTV | E136: 10000 | F136: Refazimento de trecho do CFTV, valor estimado | G136: Escopo COMERC | H136: Estimado Engenharia
B137: 45533 | C137: Varginha 5 | D137: Construção - Serviços de Construção | E137: 15000 | F137: Acesso externo na usina .Acesso da usina hoje é transitável, mas as chuvas poderão dificultar o acesso, valor estimado. | G137: Escopo COMERC | H137: Estimado Engenharia
B138: 45533 | C138: Campo Belo 1 | D138: Sistemas de Monitoramento - CFTV | E138: 10000 | F138: Refazimento de trecho do CFTV, valor estimado. | G138: Escopo COMERC | H138: Estimado Engenharia
B139: 45533 | C139: Campo Belo 1 | D139: Desenvolvimento de projeto - Outros | E139: 1500 | F139: Confecção das identificações dos inversores, valor estimado. | G139: Escopo COMERC | H139: Estimado Engenharia
B140: 45533 | C140: Campo Belo 1 | D140: Desenvolvimento de projeto - Outros | E140: 1500 | F140: Confecção das identificações das combiners, valor estimado. | G140: Escopo COMERC | H140: Estimado Engenharia
B141: 45533 | C141: Campo Belo 1 | D141: Desenvolvimento de projeto - Outros | E141: 6000 | F141: Limpeza final de obra, valor estimado. | G141: Escopo COMERC | H141: Estimado Engenharia
B142: 45533 | C142: Campo Belo 1 | D142: Escopo COMERC - Segurança | E142: 44000 | F142: Considerando mais 2 meses, valor estimado. Segurança | G142: Escopo COMERC | H142: Estimado Engenharia
B143: 45533 | C143: Campo Belo 1 | D143: Desenvolvimento de projeto - Outros | E143: 500 | F143: Adquirir espumas expansivas para vedações de dutos, valor estimado. | G143: Escopo COMERC | H143: Estimado Engenharia
B144: 45533 | C144: Campo Belo 2 | D144: Construção - Serviços de Construção | E144: 20000 | F144: Fechamento do cercamento, valor base orçado. | G144: Escopo COMERC | H144: Estimado Engenharia
...

Sheet DE_PARA
B2: USINAS | C2: NATUREZA | D2: DE | E2: PARA | F2: DELTA R$: | G2: OBSERVAÇÃO:
B3: São Sebastião 0 | C3: Conexão MT - Obras | D3: R$ - | E3: 1818400 | F3: 1818400 | G3: Obras de MT | H3: Já virou contrato
B4: Campo Belo 2 | C4: Serviços Auxiliares - Terraplanagem | D4: 153773.66 | E4: 290585.06 | F4: 136811.4 | G4: São referentes a limpeza de bacias, além da manutenção da drenagem (Os dois serviços foram fechados mesmo pacote) | H4: Já virou contrato
B5: Alfenas 4 | C5: Serviços Auxiliares - Terraplanagem | D5: 136811.4 | E5: R$ - | F5: -136811.4 | H5: Já virou contrato
B6: Formiga 6 | C6: Serviços Auxiliares - Drenagem | D6: R$ - | E6: 21200 | F6: 21200 | G6: Finalização e acerto de drenagem. | H6: Já virou contrato
B7: Paracatu 4 | C7: Desenvolvimento de projeto - Coordenograma | D7: R$ - | E7: 6206.9 | F7: 6206.9 | G7: Desenvolvimento de projeto - Coordenograma | H7: Já virou contrato
B8: Paracatu 5 | C8: Desenvolvimento de projeto - Coordenograma | D8: R$ - | E8: 6206.9 | F8: 6206.9 | G8: Desenvolvimento de projeto - Coordenograma | H8: Já virou contrato
B9: Três Corações 3 | C9: Construção - Serviços de Construção - NOVA MORADA | D9: R$ - | E9: 39532.36 | F9: 39532.36 | G9: Finalizaçãodo office, e usina das atividades da GLD. | H9: Já virou contrato
B10: Muzambinho 1 | C10: Construção - Serviços de Construção - NOVA MORADA | D10: R$ - | E10: 100312.77 | F10: 100312.77 | G10: Finalizaçãodo office, e usina das atividades da GLD. | H10: Já virou contrato
B11: Pedra do indaiá 5 | C11: Construção - Serviços de Construção - NOVA MORADA | D11: R$ - | E11: 110845.13 | F11: 110845.13 | G11: Finalizaçãodo office, e usina das atividades da GLD. | H11: Já virou contrato
B12: Paracatu 4 | C12: Desenvolvimento de projeto - Projetos - Executivos | D12: R$ - | E12: 18000 | F12: 18000 | G12: Visita técnica realizada no local R$ 3.000 ADITIVO Feito na Epoca Raciatto. Solicitar acerto Contrato Augusto | H12: Já virou contrato
B13: Paracatu 5 | C13: Desenvolvimento de projeto - Projetos - Executivos | D13: R$ - | E13: 8000 | F13: 8000 | G13: Visita técnica realizada no local R$ 3.000 ADITIVO Feito na Epoca Raciatto. Solicitar acerto Contrato Augusto | H13: Já virou contrato
B14: Três Corações 3 | C14: Supressão Vegetal | D14: R$ - | E14: 18000 | F14: 18000 | G14: Supressão Vegetal com a Rima | H14: Já virou contrato
B15: Três Corações 3 | C15: Supressão Vegetal + ria | D15: R$ - | E15: 18000 | F15: 18000 | G15: Supressão Vegetal com a Rima | H15: Já virou contrato
B16: Alfenas 4 | C16: Conexão MT - Obras | D16: 500000 | E16: 1124846 | F16: 624846 | G16: Obras de MT | H16: Já virou contrato
B17: São Sebastião 0 | C17: Construção - Serviços de Construção | D17: R$ - | E17: 259146.86 | F17: 259146.86 | G17: Construção - Serviços de Construção Aditivo Gtel | H17: Já virou contrato
B18: Divinópolis 1 | C18: Construção - Serviços de Construção | D18: R$ - | E18: 259146.86 | F18: 259146.86 | G18: Construção - Serviços de Construção Aditivo Gtel | H18: Já virou contrato
B19: Divinópolis 2 | C19: Construção - Serviços de Construção | D19: R$ - | E19: 259146.86 | F19: 259146.86 | G19: Construção - Serviços de Construção Aditivo Gtel | H19: Já virou contrato
B20: Pains 3 | C20: Construção - Serviços de Construção | D20: R$ - | E20: 259146.86 | F20: 259146.86 | G20: Construção - Serviços de Construção Aditivo Gtel | H20: Já virou contrato
B21: São Sebastião 6 | C21: Construção - Serviços de Construção | D21: R$ - | E21: 259146.86 | F21: 259146.86 | G21: Construção - Serviços de Construção Aditivo Gtel | H21: Já virou contrato
B22: Paracatu 4 | C22: Construção - Serviços de Construção | D22: R$ - | E22: 67038 | F22: 67038 | G22: Construção - Serviços de Construção Aditivo Gtel | H22: Já virou contrato
B23: Paracatu 5 | C23: Construção - Serviços de Construção | D23: R$ - | E23: 173230.13 | F23: 173230.13 | G23: Construção - Serviços de Construção Aditivo Gtel | H23: Já virou contrato
B24: Passos 4 | C24: Construção - Serviços de Construção | D24: R$ - | E24: 259146.86 | F24: 259146.86 | G24: Construção - Serviços de Construção Aditivo Gtel | H24: Já virou contrato
B25: São Sebastião 4 | C25: Construção - Serviços de Construção | D25: R$ - | E25: 259146.86 | F25: 259146.86 | G25: Construção - Serviços de Construção Aditivo Gtel | H25: Já virou contrato
B26: Varginha 1 | C26: Serviços Auxiliares - Terraplanagem | D26: 18275 | E26: 18275 | F26: R$ - | G26: Limpeza de bacias já feita, será adiivado ao contrato de terraplanagem | H26: Já virou contrato
B27: Varginha 2 | C27: Serviços Auxiliares - Terraplanagem | D27: 14075 | E27: 14075 | F27: R$ - | G27: Limpeza de bacias já feita, será adiivado ao contrato de terraplanagem | H27: Já virou contrato
B28: Patos de Minas 04 | C28: Serviços Auxiliares - Drenagem | D28: 160000 | E28: 174920 | F28: 14920 | G28: Adequação Drenagem | H28: Já virou contrato
B29: Diamantina 1 | C29: Drenagem | D29: R$ - | E29: 65000 | F29: 65000 | G29: Correção Erosões | H29: Escopo Comerc | I29: Valores Estimados
B30: Diamantina 1 | C30: Construção - Serviços de Construção | D30: R$ - | E30: 10000 | F30: 10000 | G30: Insumos energização | H30: Escopo Comerc | I30: Valores Estimados
B31: Diamantina 1 | C31: Construção - Serviços de Construção | D31: R$ - | E31: 10000 | F31: 10000 | G31: Instalação TPs e TCs | H31: Escopo Comerc | I31: Valores Estimados
B32: Diamantina 1 | C32: Construção - Serviços de Construção | D32: 20000 | E32: 94815 | F32: 74815 | G32: Cercamento Bacia de Contenção - Engetela | H32: Escopo Comerc | I32: Valores Estimados
B33: Diamantina 2 | C33: Construção - Serviços de Construção | D33: 76000 | E33: 12900 | F33: -63100 | G33: Cercamento Bacia de Contenção - Engetela | H33: Escopo Comerc | I33: Valores Estimados
B34: Diamantina 2 | C34: Construção - Serviços de Construção | D34: 34000 | E34: 20000 | F34: -14000 | G34: Limpeza geral da usina | H34: Escopo Comerc | I34: Valores Estimados
B35: Diamantina 2 | C35: Construção - Serviços de Construção | D35: R$ - | E35: 10000 | F35: 10000 | G35: Finalização do quadro serviços auxiliares | H35: Escopo Comerc | I35: Valores Estimados
B36: Diamantina 2 | C36: Construção - Serviços de Construção | D36: R$ - | E36: 10000 | F36: 10000 | G36: Insumos energização | H36: Escopo Comerc | I36: Valores Estimados
B37: Diamantina 2 | C37: Construção - Serviços de Construção | D37: R$ - | E37: 10000 | F37: 10000 | G37: Instalação TPs e TCs | H37: Escopo Comerc | I37: Valores Estimados
B38: Jaboticatubas | C38: Construção - Serviços de Construção | D38: 13000 | E38: 12900 | F38: -100 | G38: Cercamento Bacia de Contenção - Engetela | H38: Escopo Comerc | I38: Valores Estimados
B39: Jaboticatubas | C39: Drenagem | D39: R$ - | E39: 80000 | F39: 80000 | G39: Estimado para execução de limpeza/desassoreamento de córrego nas proximidades de UFV JABOTICATUBAS / Cercamento Engetela | H39: Escopo Comerc | I39: Valores Estimados
B40: Paracatu 8 | C40: Construção - Serviços de Construção | D40: R$ - | E40: 1200 | F40: 1200 | G40: Compra 02 cadeiras que foram quebradas durante implantação | H40: Escopo Comerc | I40: Valores Estimados
B41: Lagoa Formosa | C41: Construção - Serviços de Construção | D41: 75000 | E41: 63000 | F41: -12000 | G41: Finalização de pendências - RM Solar | H41: Já virou contrato
B42: Lagoa Formosa | C42: Construção - Serviços de Construção | D42: R$ - | E42: 5000 | F42: 5000 | G42: Cercamento Bacia de Contenção | H42: Escopo Comerc | I42: Valores Estimados
B43: Lagoa Formosa | C43: Construção - Serviços de Construção | D43: R$ - | E43: 5000 | F43: 5000 | G43: Lançamento cabos comunicação inversores | H43: Escopo Comerc | I43: Valores Estimados
B44: Lagoa Formosa | C44: Construção - Serviços de Construção | D44: R$ - | E44: 5000 | F44: 5000 | G44: 10 caixas danificadas pela roçagem | H44: Escopo Comerc | I44: Valores Estimados
B45: Lagoa Formosa | C45: Construção - Serviços de Construção | D45: R$ - | E45: 10000 | F45: 10000 | G45: Prontuário de instalações elétricas | H45: Escopo Comerc | I45: Valores Estimados
B46: Lagoa Formosa | C46: Desenvolvimento de projeto - Ambiental / Outros | D46: R$ - | E46: 10000 | F46: 10000 | G46: Corte madeiras da supressão vegetal | H46: Escopo Comerc | I46: Valores Estimados
B47: Patos de Minas 01 | C47: Construção - Serviços de Construção | D47: 2000 | E47: 2000 | F47: R$ - | G47: Desobstrução Eletrodutos CFTV | H47: Escopo Comerc | I47: Valores Estimados
B48: Patos de Minas 01 | C48: Serviços Auxiliares - Drenagem | D48: R$ - | E48: 40000 | F48: 40000 | G48: Recuperação Via Drenagem com Trincas | H48: Escopo Comerc | I48: Valores Estimados
B49: Patos de Minas 03 | C49: Serviços Auxiliares - Drenagem | D49: 151000 | E49: 148750 | F49: R$ - | G49: Adequação Drenagem | H49: Escopo Comerc | I49: Já Virou contrato - R&M SOLAR
